Workbook

Sheet MarketData
A1: MARKET DATA — USD SOFR curve (THE ONLY HARD-CODED SHEET)
A2: All other sheets are formula-driven and reference this sheet.
A4: Valuation date | B4: 46177
A5: Spot date (T+2) | B5: 46181
A6: Day count / Lookback | B6: ACT/360 | 5 business-day lag (compounded SOFR)
A8: 1) OVERNIGHT (SOFR O/N — discounts valuation date to first FOMC step)
A10: Tenor | B10: Start | C10: End | D10: Rate
A11: 1D | B11: 46177 | C11: 46191 | D11: 0.035947
A13: 2) FOMC-DATED STEP QUOTES (near-term SOFR path)
A14: Start | B14: End | C14: Rate
A16: 46191 | B16: 46203 | C16: 0.036301
A17: 46203 | B17: 46282 | C17: 0.036711
A18: 46282 | B18: 46324 | C18: 0.037243
A19: 46324 | B19: 46366 | C19: 0.037679
A20: 46366 | B20: 46415 | C20: 0.038647
A21: 46415 | B21: 46464 | C21: 0.038641
A22: 46464 | B22: 46506 | C22: 0.039284
A23: 46506 | B23: 46548 | C23: 0.039925
A25: 3) EUSD QUARTERLY SOFR FUTURES (price + convexity; covers 2027-06 → 2029-06)
A26: Contract | B26: IMM Start | C26: IMM End | D26: Price | E26: Convexity (%)
A27: JUN27 | B27: 46554 | C27: 46645 | D27: 95.9993 | E27: 0.0035
A28: SEP27 | B28: 46645 | C28: 46736 | D28: 96.0035 | E28: 0.0054
A29: DEC27 | B29: 46736 | C29: 46827 | D29: 96.0252 | E29: 0.0079
A30: MAR28 | B30: 46827 | C30: 46925 | D30: 96.0792 | E30: 0.0112
A31: JUN28 | B31: 46925 | C31: 47016 | D31: 96.1217 | E31: 0.0154
A32: SEP28 | B32: 47016 | C32: 47107 | D32: 96.1496 | E32: 0.0201
A33: DEC28 | B33: 47107 | C33: 47198 | D33: 96.1468 | E33: 0.0257
A34: MAR29 | B34: 47198 | C34: 47289 | D34: 96.1431 | E34: 0.0308
A36: 4) PAR SOFR SWAPS (annual, ACT/360)
A37: Tenor (Y) | B37: Maturity | C37: Par Rate
A38: 4 | B38: 47642 | C38: 0.03911
A39: 5 | B39: 48007 | C39: 0.039216
A40: 6 | B40: 48373 | C40: 0.039468
A41: 7 | B41: 48738 | C41: 0.039771
A42: 8 | B42: 49103 | C42: 0.040086
A43: 9 | B43: 49468 | C43: 0.040411
A44: 10 | B44: 49834 | C44: 0.040746
A45: 11 | B45: 50199 | C45: 0.041087
A46: 12 | B46: 50564 | C46: 0.041423
A49: 5) PANDORA CURVE (reference output — for comparison only)
A50: Date | B50: Pandora DF | C50: Pandora Forward
A51: 46195 | B51: 0.99820126 | C51: 0.036236303
A52: 46223 | B52: 0.99539283 | C52: 0.036459958
A53: 46254 | B53: 0.99226985 | C53: 0.036678842
A54: 46286 | B54: 0.98903922 | C54: 0.037161226
A55: 46315 | B55: 0.98608283 | C55: 0.037432255
A56: 46346 | B56: 0.98290625 | C56: 0.03774029
A57: 46377 | B57: 0.97971001 | C57: 0.038633655
A58: 46407 | B58: 0.97655231 | C58: 0.038470168
A59: 46440 | B59: 0.97311492 | C59: 0.038597781
A60: 46468 | B60: 0.97019528 | C60: 0.039187753
A61: 46497 | B61: 0.9671369 | C61: 0.039557065
A62: 46527 | B62: 0.96394732 | C62: 0.039907075
... A98: 47623 | B98: 0.85725698 | C98: 0.038469376
A99: 47654 | B99: 0.85442543

Sheet Bootstrap
A1: BOOTSTRAP — SOFR curve built from MarketData (all formulas)
A3: FRONT — O/N + FOMC steps (exact: DF = previous DF / (1 + rate × τ), ACT/360)
A4: Node date | B4: Prev date | C4: Days | D4: τ (ACT/360) | E4: Rate | F4: DF
A5: =MarketData!$B$4 -> 46177 | F5: 1
A6: =MarketData!$C$11 -> 46191 | B6: =A5 -> 46177 | C6: =A6-B6 -> 14 | D6: =C6/360 -> 0.038888889 | E6: =MarketData!$D$11 -> 0.035947 | F6: =F5/(1+E6*D6) -> 0.99860401
A7: =MarketData!$B$16 -> 46203 | B7: =A6 -> 46191 | C7: =A7-B7 -> 12 | D7: =C7/360 -> 0.033333333 | E7: =MarketData!$C$16 -> 0.036301 | F7: =F6/(1+E7*D7) -> 0.99739713
A8: =MarketData!$B$17 -> 46282 | B8: =A7 -> 46203 | C8: =A8-B8 -> 79 | D8: =C8/360 -> 0.21944444 | E8: =MarketData!$C$17 -> 0.036711 | F8: =F7/(1+E8*D8) -> 0.98942629
A9: =MarketData!$B$18 -> 46324 | B9: =A8 -> 46282 | C9: =A9-B9 -> 42 | D9: =C9/360 -> 0.11666667 | E9: =MarketData!$C$18 -> 0.037243 | F9: =F8/(1+E9*D9) -> 0.98514581
A10: =MarketData!$B$19 -> 46366 | B10: =A9 -> 46324 | C10: =A10-B10 -> 42 | D10: =C10/360 -> 0.11666667 | E10: =MarketData!$C$19 -> 0.037679 | F10: =F9/(1+E10*D10) -> 0.98083418
A11: =MarketData!$B$20 -> 46415 | B11: =A10 -> 46366 | C11: =A11-B11 -> 49 | D11: =C11/360 -> 0.13611111 | E11: =MarketData!$C$20 -> 0.038647 | F11: =F10/(1+E11*D11) -> 0.97570171
A12: =MarketData!$B$21 -> 46464 | B12: =A11 -> 46415 | C12: =A12-B12 -> 49 | D12: =C12/360 -> 0.13611111 | E12: =MarketData!$C$21 -> 0.038641 | F12: =F11/(1+E12*D12) -> 0.97059688
A13: =MarketData!$B$22 -> 46506 | B13: =A12 -> 46464 | C13: =A13-B13 -> 42 | D13: =C13/360 -> 0.11666667 | E13: =MarketData!$C$22 -> 0.039284 | F13: =F12/(1+E13*D13) -> 0.9661688
A14: =MarketData!$B$23 -> 46548 | B14: =A13 -> 46506 | C14: =A14-B14 -> 42 | D14: =C14/360 -> 0.11666667 | E14: =MarketData!$C$23 -> 0.039925 | F14: =F13/(1+E14*D14) -> 0.96168933
A15: =MarketData!$B$27 -> 46554 | B15: =A14 -> 46548 | C15: =A15-B15 -> 6 | D15: =C15/360 -> 0.016666667 | E15: =MarketData!$C$23 -> 0.039925 | F15: =F14/(1+E15*D15) -> 0.96104984 | G15: ← anchor (last step rate extended to first IMM date)
A17: FUTURES — EUSD chain (Fwd = (100 − Price − Convexity)/100; DF telescopes from the front)
A18: Contract | B18: IMM Start | C18: IMM End | D18: Price | E18: Conv (%) | F18: Fwd | G18: Days | H18: τ | I18: DF(start) | J18: DF(end)
A19: =MarketData!$A$27 -> JUN27 | B19: =MarketData!$B$27 -> 46554 | C19: =MarketData!$C$27 -> 46645 | D19: =MarketData!$D$27 -> 95.9993 | E19: =MarketData!$E$27 -> 0.0035 | F19: =(100-D19-E19)/100 -> 0.039972 | G19: =C19-B19 -> 91 | H19: =G19/360 -> 0.25277778 | I19: =$F$15 -> 0.96104984 | J19: =I19/(1+F19*H19) -> 0.95143649
A20: =MarketData!$A$28 -> SEP27 | B20: =MarketData!$B$28 -> 46645 | C20: =MarketData!$C$28 -> 46736 | D20: =MarketData!$D$28 -> 96.0035 | E20: =MarketData!$E$28 -> 0.0054 | F20: =(100-D20-E20)/100 -> 0.039911 | G20: =C20-B20 -> 91 | H20: =G20/360 -> 0.25277778 | I20: =J19 -> 0.95143649 | J20: =I20/(1+F20*H20) -> 0.94193368
A21: =MarketData!$A$29 -> DEC27 | B21: =MarketData!$B$29 -> 46736 | C21: =MarketData!$C$29 -> 46827 | D21: =MarketData!$D$29 -> 96.0252 | E21: =MarketData!$E$29 -> 0.0079 | F21: =(100-D21-E21)/100 -> 0.039669 | G21: =C21-B21 -> 91 | H21: =G21/360 -> 0.25277778 | I21: =J20 -> 0.94193368 | J21: =I21/(1+F21*H21) -> 0.93258227
A22: =MarketData!$A$30 -> MAR28 | B22: =MarketData!$B$30 -> 46827 | C22: =MarketData!$C$30 -> 46925 | D22: =MarketData!$D$30 -> 96.0792 | E22: =MarketData!$E$30 -> 0.0112 | F22: =(100-D22-E22)/100 -> 0.039096 | G22: =C22-B22 -> 98 | H22: =G22/360 -> 0.27222222 | I22: =J21 -> 0.93258227 | J22: =I22/(1+F22*H22) -> 0.9227615
A23: =MarketData!$A$31 -> JUN28 | B23: =MarketData!$B$31 -> 46925 | C23: =MarketData!$C$31 -> 47016 | D23: =MarketData!$D$31 -> 96.1217 | E23: =MarketData!$E$31 -> 0.0154 | F23: =(100-D23-E23)/100 -> 0.038629 | G23: =C23-B23 -> 91 | H23: =G23/360 -> 0.25277778 | I23: =J22 -> 0.9227615 | J23: =I23/(1+F23*H23) -> 0.91383828
A24: =MarketData!$A$32 -> SEP28 | B24: =MarketData!$B$32 -> 47016 | C24: =MarketData!$C$32 -> 47107 | D24: =MarketData!$D$32 -> 96.1496 | E24: =MarketData!$E$32 -> 0.0201 | F24: =(100-D24-E24)/100 -> 0.038303 | G24: =C24-B24 -> 91 | H24: =G24/360 -> 0.25277778 | I24: =J23 -> 0.91383828 | J24: =I24/(1+F24*H24) -> 0.90507521
A25: =MarketData!$A$33 -> DEC28 | B25: =MarketData!$B$33 -> 47107 | C25: =MarketData!$C$33 -> 47198 | D25: =MarketData!$D$33 -> 96.1468 | E25: =MarketData!$E$33 -> 0.0257 | F25: =(100-D25-E25)/100 -> 0.038275 | G25: =C25-B25 -> 91 | H25: =G25/360 -> 0.25277778 | I25: =J24 -> 0.90507521 | J25: =I25/(1+F25*H25) -> 0.89640245
A26: =MarketData!$A$34 -> MAR29 | B26: =MarketData!$B$34 -> 47198 | C26: =MarketData!$C$34 -> 47289 | D26: =MarketData!$D$34 -> 96.1431 | E26: =MarketData!$E$34 -> 0.0308 | F26: =(100-D26-E26)/100 -> 0.038261 | G26: =C26-B26 -> 91 | H26: =G26/360 -> 0.25277778 | I26: =J25 -> 0.89640245 | J26: =I26/(1+F26*H26) -> 0.88781592
A28: SWAP SOLVES — close out the long end (annual fixed leg from spot, ACT/360; 5Y added as sentinel node)
A29: Spot date | B29: =MarketData!$B$5 -> 46181 | D29: Spot DF | E29: =1/(1+MarketData!$D$11*(B29-MarketData!$B$4)/360) -> 0.99960075
A30: Fixed date | B30: DF | C30: τ (ACT/360)
A31: =EDATE(B29,12) -> 46546 | B31: =F13*(F14/F13)^((A31-A13)/(A14-A13)) -> 0.96190217 | C31: =(A31-B29)/360 -> 1.0138889
A32: =EDATE(B29,24) -> 46912 | B32: =J21*(J22/J21)^((A32-C21)/(C22-C21)) -> 0.92405829 | C32: =(A32-A31)/360 -> 1.0166667
A33: =EDATE(B29,36) -> 47277 | B33: =J25*(J26/J25)^((A33-C25)/(C26-C25)) -> 0.88894348 | C33: =(A33-A32)/360 -> 1.0138889
A34: =MarketData!$B$38 -> 47642 | B34: =(E29-MarketData!$C$38*(C31*B31+C32*B32+C33*B33))/(1+MarketData!$C$38*C34) -> 0.8555416 | C34: =(A34-A33)/360 -> 1.0138889 | E34: ← 4Y par solve (DF at 2030 maturity)
A35: =MarketData!$B$39 -> 48007 | B35: =(E29-MarketData!$C$39*(C31*B31+C32*B32+C33*B33+C34*B34))/(1+MarketData!$C$39*C35) -> 0.82244999 | C35: =(A35-A34)/360 -> 1.0138889 | E35: ← 5Y par solve (sentinel)
A37: CURVE NODES (sorted) — the interpolation grid (log-linear on ln DF) used by the Curve and Interpolation sheets
A38: Node date | B38: Time (yrs, ACT/360) | C38: DF | D38: ln(DF)
A39: =A5 -> 46177 | B39: =(A39-MarketData!$B$4)/360 -> 0 | C39: =F5 -> 1 | D39: =LN(C39) -> 0
A40: =A6 -> 46191 | B40: =(A40-MarketData!$B$4)/360 -> 0.038888889 | C40: =F6 -> 0.99860401 | D40: =LN(C40) -> -0.0013969627
A41: =A7 -> 46203 | B41: =(A41-MarketData!$B$4)/360 -> 0.072222222 | C41: =F7 -> 0.99739713 | D41: =LN(C41) -> -0.0026062645
A42: =A8 -> 46282 | B42: =(A42-MarketData!$B$4)/360 -> 0.29166667 | C42: =F8 -> 0.98942629 | D42: =LN(C42) -> -0.010630013
A43: =A9 -> 46324 | B43: =(A43-MarketData!$B$4)/360 -> 0.40833333 | C43: =F9 -> 0.98514581 | D43: =LN(C43) -> -0.014965617
A44: =A10 -> 46366 | B44: =(A44-MarketData!$B$4)/360 -> 0.525 | C44: =F10 -> 0.98083418 | D44: =LN(C44) -> -0.019351867
A45: =A11 -> 46415 | B45: =(A45-MarketData!$B$4)/360 -> 0.66111111 | C45: =F11 -> 0.97570171 | D45: =LN(C45) -> -0.024598366
A46: =A12 -> 46464 | B46: =(A46-MarketData!$B$4)/360 -> 0.79722222 | C46: =F12 -> 0.97059688 | D46: =LN(C46) -> -0.029844053
A47: =A13 -> 46506 | B47: =(A47-MarketData!$B$4)/360 -> 0.91388889 | C47: =F13 -> 0.9661688 | D47: =LN(C47) -> -0.034416716
A48: =A14 -> 46548 | B48: =(A48-MarketData!$B$4)/360 -> 1.0305556 | C48: =F14 -> 0.96168933 | D48: =LN(C48) -> -0.039063818
A49: =A15 -> 46554 | B49: =(A49-MarketData!$B$4)/360 -> 1.0472222 | C49: =F15 -> 0.96104984 | D49: =LN(C49) -> -0.039729013
A50: =C19 -> 46645 | B50: =(A50-MarketData!$B$4)/360 -> 1.3 | C50: =J19 -> 0.95143649 | D50: =LN(C50) -> -0.049782342
A51: =C20 -> 46736 | B51: =(A51-MarketData!$B$4)/360 -> 1.5527778 | C51: =J20 -> 0.94193368 | D51: =LN(C51) -> -0.059820405
A52: =C21 -> 46827 | B52: =(A52-MarketData!$B$4)/360 -> 1.8055556 | C52: =J21 -> 0.93258227 | D52: =LN(C52) -> -0.069797906
A53: =C22 -> 46925 | B53: =(A53-MarketData!$B$4)/360 -> 2.0777778 | C53: =J22 -> 0.9227615 | D53: =LN(C53) -> -0.08038447
A54: =C23 -> 47016 | B54: =(A54-MarketData!$B$4)/360 -> 2.3305556 | C54: =J23 -> 0.91383828 | D54: =LN(C54) -> -0.090101658
A55: =C24 -> 47107 | B55: =(A55-MarketData!$B$4)/360 -> 2.5833333 | C55: =J24 -> 0.90507521 | D55: =LN(C55) -> -0.099737233
A56: =C25 -> 47198 | B56: =(A56-MarketData!$B$4)/360 -> 2.8361111 | C56: =J25 -> 0.89640245 | D56: =LN(C56) -> -0.1093658
A57: =C26 -> 47289 | B57: =(A57-MarketData!$B$4)/360 -> 3.0888889 | C57: =J26 -> 0.88781592 | D57: =LN(C57) -> -0.11899086
A58: =A34 -> 47642 | B58: =(A58-MarketData!$B$4)/360 -> 4.0694444 | C58: =B34 -> 0.8555416 | D58: =LN(C58) -> -0.15602056
A59: =A35 -> 48007 | B59: =(A59-MarketData!$B$4)/360 -> 5.0833333 | C59: =B35 -> 0.82244999 | D59: =LN(C59) -> -0.1954676

Sheet Curve
A1: CURVE — discount factor & forward rate for every date, vs Pandora
A2: DF: log-linear on ln DF over the Bootstrap node grid. Forward: compounded SOFR with 5-business-day lag (WORKDAY −5).
A4: Date | B4: Time | C4: My DF | D4: Pandora DF | E4: Δ zero (bp) mine−Pandora | F4: Next date | G4: τ | H4: Lag start | I4: Lag end | J4: DF(lag start) | K4: DF(lag end) | L4: My Forward | M4: Pandora Fwd | N4: Δ fwd (bp) mine−Pandora
A5: =MarketData!$A$51 -> 46195 | B5: =(A5-MarketData!$B$4)/360 -> 0.05 | C5: =EXP(INDEX(Bootstrap!$D$39:$D$59,MATCH($B5,Bootstrap!$B$39:$B$59,1))+(INDEX(Bootstrap!$D$39:$D$59,MATCH($B5,Bootstrap!$B$39:$B$59,1)+1)-INDEX(Bootstrap!$D$39:$D$59,MATCH($B5,Bootstrap!$B$39:$B$59,1)))*(($B5)-INDEX(Bootstrap!$B$39:$B$59,MATCH($B5,Bootstrap!$B$39:$B$59,1)))/(INDEX(Bootstrap!$B$39:$B$59,MATCH($B5,Bootstrap!$B$39:$B$59,1)+1)-INDEX(Bootstrap!$B$39:$B$59,MATCH($B5,Bootstrap!$B$39:$B$59,1)))) -> 0.99820156 | D5: =MarketData!$B$51 -> 0.99820126 | E5: =(LN(D5)-LN(C5))/B5*10000 -> -0.059677186 | F5: =A6 -> 46223 | G5: =(F5-A5)/360 -> 0.077777778 | H5: =WORKDAY(A5,-5) -> 46188 | I5: =WORKDAY(F5,-5) -> 46216 | J5: =EXP(INDEX(Bootstrap!$D$39:$D$59,MATCH((($H5-MarketData!$B$4)/360),Bootstrap!$B$39:$B$59,1))+(INDEX(Bootstrap!$D$39:$D$59,MATCH((($H5-MarketData!$B$4)/360),Bootstrap!$B$39:$B$59,1)+1)-INDEX(Bootstrap!$D$39:$D$59,MATCH((($H5-MarketData!$B$4)/360),Bootstrap!$B$39:$B$59,1)))*(((($H5-MarketData!$B$4)/360))-INDEX(Bootstrap!$B$39:$B$59,MATCH((($H5-MarketData!$B$4)/360),Bootstrap!$B$39:$B$59,1)))/(INDEX(Bootstrap!$B$39:$B$59,MATCH((($H5-MarketData!$B$4)/360),Bootstrap!$B$39:$B$59,1)+1)-INDEX(Bootstrap!$B$39:$B$59,MATCH((($H5-MarketData!$B$4)/360),Bootstrap!$B$39:$B$59,1)))) -> 0.99890299 | K5: =EXP(INDEX(Bootstrap!$D$39:$D$59,MATCH((($I5-MarketData!$B$4)/360),Bootstrap!$B$39:$B$59,1))+(INDEX(Bootstrap!$D$39:$D$59,MATCH((($I5-MarketData!$B$4)/360),Bootstrap!$B$39:$B$59,1)+1)-INDEX(Bootstrap!$D$39:$D$59,MATCH((($I5-MarketData!$B$4)/360),Bootstrap!$B$39:$B$59,1)))*(((($I5-MarketData!$B$4)/360))-INDEX(Bootstrap!$B$39:$B$59,MATCH((($I5-MarketData!$B$4)/360),Bootstrap!$B$39:$B$59,1)))/(INDEX(Bootstrap!$B$39:$B$59,MATCH((($I5-MarketData!$B$4)/360),Bootstrap!$B$39:$B$59,1)+1)-INDEX(Bootstrap!$B$39:$B$59,MATCH((($I5-MarketData!$B$4)/360),Bootstrap!$B$39:$B$59,1)))) -> 0.99608107 | L5: =(J5/K5-1)/G5 -> 0.036424544 | M5: =MarketData!$C$51 -> 0.036236303 | N5: =(L5-M5)*10000 -> 1.8824119
A6: =MarketData!$A$52 -> 46223 | B6: =(A6-MarketData!$B$4)/360 -> 0.12777778 | C6: =EXP(INDEX(Bootstrap!$D$39:$D$59,MATCH($B6,Bootstrap!$B$39:$B$59,1))+(INDEX(Bootstrap!$D$39:$D$59,MATCH($B6,Bootstrap!$B$39:$B$59,1)+1)-INDEX(Bootstrap!$D$39:$D$59,MATCH($B6,Bootstrap!$B$39:$B$59,1)))*(($B6)-INDEX(Bootstrap!$B$39:$B$59,MATCH($B6,Bootstrap!$B$39:$B$59,1)))/(INDEX(Bootstrap!$B$39:$B$59,MATCH($B6,Bootstrap!$B$39:$B$59,1)+1)-INDEX(Bootstrap!$B$39:$B$59,MATCH($B6,Bootstrap!$B$39:$B$59,1)))) -> 0.99537314 | D6: =MarketData!$B$52 -> 0.99539283 | E6: =(LN(D6)-LN(C6))/B6*10000 -> 1.5481991 | F6: =A7 -> 46254 | G6: =(F6-A6)/360 -> 0.086111111 | H6: =WORKDAY(A6,-5) -> 46216 | I6: =WORKDAY(F6,-5) -> 46247 | J6: =EXP(INDEX(Bootstrap!$D$39:$D$59,MATCH((($H6-MarketData!$B$4)/360),Bootstrap!$B$39:$B$59,1))+(INDEX(Bootstrap!$D$39:$D$59,MATCH((($H6-MarketData!$B$4)/360),Bootstrap!$B$39:$B$59,1)+1)-INDEX(Bootstrap!$D$39:$D$59,MATCH((($H6-MarketData!$B$4)/360),Bootstrap!$B$39:$B$59,1)))*(((($H6-MarketData!$B$4)/360))-INDEX(Bootstrap!$B$39:$B$59,MATCH((($H6-MarketData!$B$4)/360),Bootstrap!$B$39:$B$59,1)))/(INDEX(Bootstrap!$B$39:$B$59,MATCH((($H6-MarketData!$B$4)/360),Bootstrap!$B$39:$B$59,1)+1)-INDEX(Bootstrap!$B$39:$B$59,MATCH((($H6-MarketData!$B$4)/360),Bootstrap!$B$39:$B$59,1)))) -> 0.99608107 | K6: =EXP(INDEX(Bootstrap!$D$39:$D$59,MATCH((($I6-MarketData!$B$4)/360),Bootstrap!$B$39:$B$59,1))+(INDEX(Bootstrap!$D$39:$D$59,MATCH((($I6-MarketData!$B$4)/360),Bootstrap!$B$39:$B$59,1)+1)-INDEX(Bootstrap!$D$39:$D$59,MATCH((($I6-MarketData!$B$4)/360),Bootstrap!$B$39:$B$59,1)))*(((($I6-MarketData!$B$4)/360))-INDEX(Bootstrap!$B$39:$B$59,MATCH((($I6-MarketData!$B$4)/360),Bootstrap!$B$39:$B$59,1)))/(INDEX(Bootstrap!$B$39:$B$59,MATCH((($I6-MarketData!$B$4)/360),Bootstrap!$B$39:$B$59,1)+1)-INDEX(Bootstrap!$B$39:$B$59,MATCH((($I6-MarketData!$B$4)/360),Bootstrap!$B$39:$B$59,1)))) -> 0.99294978 | L6: =(J6/K6-1)/G6 -> 0.036621539 | M6: =MarketData!$C$52 -> 0.036459958 | N6: =(L6-M6)*10000 -> 1.6158184
A7: =MarketData!$A$53 -> 46254 | B7: =(A7-MarketData!$B$4)/360 -> 0.21388889 | C7: =EXP(INDEX(Bootstrap!$D$39:$D$59,MATCH($B7,Bootstrap!$B$39:$B$59,1))+(INDEX(Bootstrap!$D$39:$D$59,MATCH($B7,Bootstrap!$B$39:$B$59,1)+1)-INDEX(Bootstrap!$D$39:$D$59,MATCH($B7,Bootstrap!$B$39:$B$59,1)))*(($B7)-INDEX(Bootstrap!$B$39:$B$59,MATCH($B7,Bootstrap!$B$39:$B$59,1)))/(INDEX(Bootstrap!$B$39:$B$59,MATCH($B7,Bootstrap!$B$39:$B$59,1)+1)-INDEX(Bootstrap!$B$39:$B$59,MATCH($B7,Bootstrap!$B$39:$B$59,1)))) -> 0.99224408 | D7: =MarketData!$B$53 -> 0.99226985 | E7: =(LN(D7)-LN(C7))/B7*10000 -> 1.2140537 | F7: =A8 -> 46286 | G7: =(F7-A7)/360 -> 0.088888889 | H7: =WORKDAY(A7,-5) -> 46247 | I7: =WORKDAY(F7,-5) -> 46279 | J7: =EXP(INDEX(Bootstrap!$D$39:$D$59,MATCH((($H7-MarketData!$B$4)/360),Bootstrap!$B$39:$B$59,1))+(INDEX(Bootstrap!$D$39:$D$59,MATCH((($H7-MarketData!$B$4)/360),Bootstrap!$B$39:$B$59,1)+1)-INDEX(Bootstrap!$D$39:$D$59,MATCH((($H7-MarketData!$B$4)/360),Bootstrap!$B$39:$B$59,1)))*(((($H7-MarketData!$B$4)/360))-INDEX(Bootstrap!$B$39:$B$59,MATCH((($H7-MarketData!$B$4)/360),Bootstrap!$B$39:$B$59,1)))/(INDEX(Bootstrap!$B$39:$B$59,MATCH((($H7-MarketData!$B$4)/360),Bootstrap!$B$39:$B$59,1)+1)-INDEX(Bootstrap!$B$39:$B$59,MATCH((($H7-MarketData!$B$4)/360),Bootstrap!$B$39:$B$59,1)))) -> 0.99294978 | K7: =EXP(INDEX(Bootstrap!$D$39:$D$59,MATCH((($I7-MarketData!$B$4)/360),Bootstrap!$B$39:$B$59,1))+(INDEX(Bootstrap!$D$39:$D$59,MATCH((($I7-MarketData!$B$4)/360),Bootstrap!$B$39:$B$59,1)+1)-INDEX(Bootstrap!$D$39:$D$59,MATCH((($I7-MarketData!$B$4)/360),Bootstrap!$B$39:$B$59,1)))*(((($I7-MarketData!$B$4)/360))-INDEX(Bootstrap!$B$39:$B$59,MATCH((($I7-MarketData!$B$4)/360),Bootstrap!$B$39:$B$59,1)))/(INDEX(Bootstrap!$B$39:$B$59,MATCH((($I7-MarketData!$B$4)/360),Bootstrap!$B$39:$B$59,1)+1)-INDEX(Bootstrap!$B$39:$B$59,MATCH((($I7-MarketData!$B$4)/360),Bootstrap!$B$39:$B$59,1)))) -> 0.98972781 | L7: =(J7/K7-1)/G7 -> 0.0366234 | M7: =MarketData!$C$53 -> 0.036678842 | N7: =(L7-M7)*10000 -> -0.55441766
A8: =MarketData!$A$54 -> 46286 | B8: =(A8-MarketData!$B$4)/360 -> 0.30277778 | C8: =EXP(INDEX(Bootstrap!$D$39:$D$59,MATCH($B8,Bootstrap!$B$39:$B$59,1))+(INDEX(Bootstrap!$D$39:$D$59,MATCH($B8,Bootstrap!$B$39:$B$59,1)+1)-INDEX(Bootstrap!$D$39:$D$59,MATCH($B8,Bootstrap!$B$39:$B$59,1)))*(($B8)-INDEX(Bootstrap!$B$39:$B$59,MATCH($B8,Bootstrap!$B$39:$B$59,1)))/(INDEX(Bootstrap!$B$39:$B$59,MATCH($B8,Bootstrap!$B$39:$B$59,1)+1)-INDEX(Bootstrap!$B$39:$B$59,MATCH($B8,Bootstrap!$B$39:$B$59,1)))) -> 0.98901782 | D8: =MarketData!$B$54 -> 0.98903922 | E8: =(LN(D8)-LN(C8))/B8*10000 -> 0.71464196 | F8: =A9 -> 46315 | G8: =(F8-A8)/360 -> 0.080555556 | H8: =WORKDAY(A8,-5) -> 46279 | I8: =WORKDAY(F8,-5) -> 46308 | J8: =EXP(INDEX(Bootstrap!$D$39:$D$59,MATCH((($H8-MarketData!$B$4)/360),Bootstrap!$B$39:$B$59,1))+(INDEX(Bootstrap!$D$39:$D$59,MATCH((($H8-MarketData!$B$4)/360),Bootstrap!$B$39:$B$59,1)+1)-INDEX(Bootstrap!$D$39:$D$59,MATCH((($H8-MarketData!$B$4)/360),Bootstrap!$B$39:$B$59,1)))*(((($H8-MarketData!$B$4)/360))-INDEX(Bootstrap!$B$39:$B$59,MATCH((($H8-MarketData!$B$4)/360),Bootstrap!$B$39:$B$59,1)))/(INDEX(Bootstrap!$B$39:$B$59,MATCH((($H8-MarketData!$B$4)/360),Bootstrap!$B$39:$B$59,1)+1)-INDEX(Bootstrap!$B$39:$B$59,MATCH((($H8-MarketData!$B$4)/360),Bootstrap!$B$39:$B$59,1)))) -> 0.98972781 | K8: =EXP(INDEX(Bootstrap!$D$39:$D$59,MATCH((($I8-MarketData!$B$4)/360),Bootstrap!$B$39:$B$59,1))+(INDEX(Bootstrap!$D$39:$D$59,MATCH((($I8-MarketData!$B$4)/360),Bootstrap!$B$39:$B$59,1)+1)-INDEX(Bootstrap!$D$39:$D$59,MATCH((($I8-MarketData!$B$4)/360),Bootstrap!$B$39:$B$59,1)))*(((($I8-MarketData!$B$4)/360))-INDEX(Bootstrap!$B$39:$B$59,MATCH((($I8-MarketData!$B$4)/360),Bootstrap!$B$39:$B$59,1)))/(INDEX(Bootstrap!$B$39:$B$59,MATCH((($I8-MarketData!$B$4)/360),Bootstrap!$B$39:$B$59,1)+1)-INDEX(Bootstrap!$B$39:$B$59,MATCH((($I8-MarketData!$B$4)/360),Bootstrap!$B$39:$B$59,1)))) -> 0.98677428 | L8: =(J8/K8-1)/G8 -> 0.037155914 | M8: =MarketData!$C$54 -> 0.037161226 | N8: =(L8-M8)*10000 -> -0.0531181
A9: =MarketData!$A$55 -> 46315 | B9: =(A9-MarketData!$B$4)/360 -> 0.38333333 | C9: =EXP(INDEX(Bootstrap!$D$39:$D$59,MATCH($B9,Bootstrap!$B$39:$B$59,1))+(INDEX(Bootstrap!$D$39:$D$59,MATCH($B9,Bootstrap!$B$39:$B$59,1)+1)-INDEX(Bootstrap!$D$39:$D$59,MATCH($B9,Bootstrap!$B$39:$B$59,1)))*(($B9)-INDEX(Bootstrap!$B$39:$B$59,MATCH($B9,Bootstrap!$B$39:$B$59,1)))/(INDEX(Bootstrap!$B$39:$B$59,MATCH($B9,Bootstrap!$B$39:$B$59,1)+1)-INDEX(Bootstrap!$B$39:$B$59,MATCH($B9,Bootstrap!$B$39:$B$59,1)))) -> 0.98606149 | D9: =MarketData!$B$55 -> 0.98608283 | E9: =(LN(D9)-LN(C9))/B9*10000 -> 0.5644544 | F9: =A10 -> 46346 | G9: =(F9-A9)/360 -> 0.086111111 | H9: =WORKDAY(A9,-5) -> 46308 | I9: =WORKDAY(F9,-5) -> 46339 | J9: =EXP(INDEX(Bootstrap!$D$39:$D$59,MATCH((($H9-MarketData!$B$4)/360),Bootstrap!$B$39:$B$59,1))+(INDEX(Bootstrap!$D$39:$D$59,MATCH((($H9-MarketData!$B$4)/360),Bootstrap!$B$39:$B$59,1)+1)-INDEX(Bootstrap!$D$39:$D$59,MATCH((($H9-MarketData!$B$4)/360),Bootstrap!$B$39:$B$59,1)))*(((($H9-MarketData!$B$4)/360))-INDEX(Bootstrap!$B$39:$B$59,MATCH((($H9-MarketData!$B$4)/360),Bootstrap!$B$39:$B$59,1)))/(INDEX(Bootstrap!$B$39:$B$59,MATCH((($H9-MarketData!$B$4)/360),Bootstrap!$B$39:$B$59,1)+1)-INDEX(Bootstrap!$B$39:$B$59,MATCH((($H9-MarketData!$B$4)/360),Bootstrap!$B$39:$B$59,1)))) -> 0.98677428 | K9: =EXP(INDEX(Bootstrap!$D$39:$D$59,MATCH((($I9-MarketData!$B$4)/360),Bootstrap!$B$39:$B$59,1))+(INDEX(Bootstrap!$D$39:$D$59,MATCH((($I9-MarketData!$B$4)/360),Bootstrap!$B$39:$B$59,1)+1)-INDEX(Bootstrap!$D$39:$D$59,MATCH((($I9-MarketData!$B$4)/360),Bootstrap!$B$39:$B$59,1)))*(((($I9-MarketData!$B$4)/360))-INDEX(Bootstrap!$B$39:$B$59,MATCH((($I9-MarketData!$B$4)/360),Bootstrap!$B$39:$B$59,1)))/(INDEX(Bootstrap!$B$39:$B$59,MATCH((($I9-MarketData!$B$4)/360),Bootstrap!$B$39:$B$59,1)+1)-INDEX(Bootstrap!$B$39:$B$59,MATCH((($I9-MarketData!$B$4)/360),Bootstrap!$B$39:$B$59,1)))) -> 0.98360377 | L9: =(J9/K9-1)/G9 -> 0.037432573 | M9: =MarketData!$C$55 -> 0.037432255 | N9: =(L9-M9)*10000 -> 0.0031762045
A10: =MarketData!$A$56 -> 46346 | B10: =(A10-MarketData!$B$4)/360 -> 0.46944444 | C10: =EXP(INDEX(Bootstrap!$D$39:$D$59,MATCH($B10,Bootstrap!$B$39:$B$59,1))+(INDEX(Bootstrap!$D$39:$D$59,MATCH($B10,Bootstrap!$B$39:$B$59,1)+1)-INDEX(Bootstrap!$D$39:$D$59,MATCH($B10,Bootstrap!$B$39:$B$59,1)))*(($B10)-INDEX(Bootstrap!$B$39:$B$59,MATCH($B10,Bootstrap!$B$39:$B$59,1)))/(INDEX(Bootstrap!$B$39:$B$59,MATCH($B10,Bootstrap!$B$39:$B$59,1)+1)-INDEX(Bootstrap!$B$39:$B$59,MATCH($B10,Bootstrap!$B$39:$B$59,1)))) -> 0.98288498 | D10: =MarketData!$B$56 -> 0.98290625 | E10: =(LN(D10)-LN(C10))/B10*10000 -> 0.46092555 | F10: =A11 -> 46377 | G10: =(F10-A10)/360 -> 0.086111111 | H10: =WORKDAY(A10,-5) -> 46339 | I10: =WORKDAY(F10,-5) -> 46370 | J10: =EXP(INDEX(Bootstrap!$D$39:$D$59,MATCH((($H10-MarketData!$B$4)/360),Bootstrap!$B$39:$B$59,1))+(INDEX(Bootstrap!$D$39:$D$59,MATCH((($H10-MarketData!$B$4)/360),Bootstrap!$B$39:$B$59,1)+1)-INDEX(Bootstrap!$D$39:$D$59,MATCH((($H10-MarketData!$B$4)/360),Bootstrap!$B$39:$B$59,1)))*(((($H10-MarketData!$B$4)/360))-INDEX(Bootstrap!$B$39:$B$59,MATCH((($H10-MarketData!$B$4)/360),Bootstrap!$B$39:$B$59,1)))/(INDEX(Bootstrap!$B$39:$B$59,MATCH((($H10-MarketData!$B$4)/360),Bootstrap!$B$39:$B$59,1)+1)-INDEX(Bootstrap!$B$39:$B$59,MATCH((($H10-MarketData!$B$4)/360),Bootstrap!$B$39:$B$59,1)))) -> 0.98360377 | K10: =EXP(INDEX(Bootstrap!$D$39:$D$59,MATCH((($I10-MarketData!$B$4)/360),Bootstrap!$B$39:$B$59,1))+(INDEX(Bootstrap!$D$39:$D$59,MATCH((($I10-MarketData!$B$4)/360),Bootstrap!$B$39:$B$59,1)+1)-INDEX(Bootstrap!$D$39:$D$59,MATCH((($I10-MarketData!$B$4)/360),Bootstrap!$B$39:$B$59,1)))*(((($I10-MarketData!$B$4)/360))-INDEX(Bootstrap!$B$39:$B$59,MATCH((($I10-MarketData!$B$4)/360),Bootstrap!$B$39:$B$59,1)))/(INDEX(Bootstrap!$B$39:$B$59,MATCH((($I10-MarketData!$B$4)/360),Bootstrap!$B$39:$B$59,1)+1)-INDEX(Bootstrap!$B$39:$B$59,MATCH((($I10-MarketData!$B$4)/360),Bootstrap!$B$39:$B$59,1)))) -> 0.98041419 | L10: =(J10/K10-1)/G10 -> 0.037780236 | M10: =MarketData!$C$56 -> 0.03774029 | N10: =(L10-M10)*10000 -> 0.39945714
A11: =MarketData!$A$57 -> 46377 | B11: =(A11-MarketData!$B$4)/360 -> 0.55555556 | C11: =EXP(INDEX(Bootstrap!$D$39:$D$59,MATCH($B11,Bootstrap!$B$39:$B$59,1))+(INDEX(Bootstrap!$D$39:$D$59,MATCH($B11,Bootstrap!$B$39:$B$59,1)+1)-INDEX(Bootstrap!$D$39:$D$59,MATCH($B11,Bootstrap!$B$39:$B$59,1)))*(($B11)-INDEX(Bootstrap!$B$39:$B$59,MATCH($B11,Bootstrap!$B$39:$B$59,1)))/(INDEX(Bootstrap!$B$39:$B$59,MATCH($B11,Bootstrap!$B$39:$B$59,1)+1)-INDEX(Bootstrap!$B$39:$B$59,MATCH($B11,Bootstrap!$B$39:$B$59,1)))) -> 0.97967965 | D11: =MarketData!$B$57 -> 0.97971001 | E11: =(LN(D11)-LN(C11))/B11*10000 -> 0.55784127 | F11: =A12 -> 46407 | G11: =(F11-A11)/360 -> 0.083333333 | H11: =WORKDAY(A11,-5) -> 46370 | I11: =WORKDAY(F11,-5) -> 46400 | J11: =EXP(INDEX(Bootstrap!$D$39:$D$59,MATCH((($H11-MarketData!$B$4)/360),Bootstrap!$B$39:$B$59,1))+(INDEX(Bootstrap!$D$39:$D$59,MATCH((($H11-MarketData!$B$4)/360),Bootstrap!$B$39:$B$59,1)+1)-INDEX(Bootstrap!$D$39:$D$59,MATCH((($H11-MarketData!$B$4)/360),Bootstrap!$B$39:$B$59,1)))*(((($H11-MarketData!$B$4)/360))-INDEX(Bootstrap!$B$39:$B$59,MATCH((($H11-MarketData!$B$4)/360),Bootstrap!$B$39:$B$59,1)))/(INDEX(Bootstrap!$B$39:$B$59,MATCH((($H11-MarketData!$B$4)/360),Bootstrap!$B$39:$B$59,1)+1)-INDEX(Bootstrap!$B$39:$B$59,MATCH((($H11-MarketData!$B$4)/360),Bootstrap!$B$39:$B$59,1)))) -> 0.98041419 | K11: =EXP(INDEX(Bootstrap!$D$39:$D$59,MATCH((($I11-MarketData!$B$4)/360),Bootstrap!$B$39:$B$59,1))+(INDEX(Bootstrap!$D$39:$D$59,MATCH((($I11-MarketData!$B$4)/360),Bootstrap!$B$39:$B$59,1)+1)-INDEX(Bootstrap!$D$39:$D$59,MATCH((($I11-MarketData!$B$4)/360),Bootstrap!$B$39:$B$59,1)))*(((($I11-MarketData!$B$4)/360))-INDEX(Bootstrap!$B$39:$B$59,MATCH((($I11-MarketData!$B$4)/360),Bootstrap!$B$39:$B$59,1)))/(INDEX(Bootstrap!$B$39:$B$59,MATCH((($I11-MarketData!$B$4)/360),Bootstrap!$B$39:$B$59,1)+1)-INDEX(Bootstrap!$B$39:$B$59,MATCH((($I11-MarketData!$B$4)/360),Bootstrap!$B$39:$B$59,1)))) -> 0.97727001 | L11: =(J11/K11-1)/G11 -> 0.038607681 | M11: =MarketData!$C$57 -> 0.038633655 | N11: =(L11-M11)*10000 -> -0.25973289
A12: =MarketData!$A$58 -> 46407 | B12: =(A12-MarketData!$B$4)/360 -> 0.63888889 | C12: =EXP(INDEX(Bootstrap!$D$39:$D$59,MATCH($B12,Bootstrap!$B$39:$B$59,1))+(INDEX(Bootstrap!$D$39:$D$59,MATCH($B12,Bootstrap!$B$39:$B$59,1)+1)-INDEX(Bootstrap!$D$39:$D$59,MATCH($B12,Bootstrap!$B$39:$B$59,1)))*(($B12)-INDEX(Bootstrap!$B$39:$B$59,MATCH($B12,Bootstrap!$B$39:$B$59,1)))/(INDEX(Bootstrap!$B$39:$B$59,MATCH($B12,Bootstrap!$B$39:$B$59,1)+1)-INDEX(Bootstrap!$B$39:$B$59,MATCH($B12,Bootstrap!$B$39:$B$59,1)))) -> 0.97653782 | D12: =MarketData!$B$58 -> 0.97655231 | E12: =(LN(D12)-LN(C12))/B12*10000 -> 0.23219393 | F12: =A13 -> 46440 | G12: =(F12-A12)/360 -> 0.091666667 | H12: =WORKDAY(A12,-5) -> 46400 | I12: =WORKDAY(F12,-5) -> 46433 | J12: =EXP(INDEX(Bootstrap!$D$39:$D$59,MATCH((($H12-MarketData!$B$4)/360),Bootstrap!$B$39:$B$59,1))+(INDEX(Bootstrap!$D$39:$D$59,MATCH((($H12-MarketData!$B$4)/360),Bootstrap!$B$39:$B$59,1)+1)-INDEX(Bootstrap!$D$39:$D$59,MATCH((($H12-MarketData!$B$4)/360),Bootstrap!$B$39:$B$59,1)))*(((($H12-MarketData!$B$4)/360))-INDEX(Bootstrap!$B$39:$B$59,MATCH((($H12-MarketData!$B$4)/360),Bootstrap!$B$39:$B$59,1)))/(INDEX(Bootstrap!$B$39:$B$59,MATCH((($H12-MarketData!$B$4)/360),Bootstrap!$B$39:$B$59,1)+1)-INDEX(Bootstrap!$B$39:$B$59,MATCH((($H12-MarketData!$B$4)/360),Bootstrap!$B$39:$B$59,1)))) -> 0.97727001 | K12: =EXP(INDEX(Bootstrap!$D$39:$D$59,MATCH((($I12-MarketData!$B$4)/360),Bootstrap!$B$39:$B$59,1))+(INDEX(Bootstrap!$D$39:$D$59,MATCH((($I12-MarketData!$B$4)/360),Bootstrap!$B$39:$B$59,1)+1)-INDEX(Bootstrap!$D$39:$D$59,MATCH((($I12-MarketData!$B$4)/360),Bootstrap!$B$39:$B$59,1)))*(((($I12-MarketData!$B$4)/360))-INDEX(Bootstrap!$B$39:$B$59,MATCH((($I12-MarketData!$B$4)/360),Bootstrap!$B$39:$B$59,1)))/(INDEX(Bootstrap!$B$39:$B$59,MATCH((($I12-MarketData!$B$4)/360),Bootstrap!$B$39:$B$59,1)+1)-INDEX(Bootstrap!$B$39:$B$59,MATCH((($I12-MarketData!$B$4)/360),Bootstrap!$B$39:$B$59,1)))) -> 0.97382335 | L12: =(J12/K12-1)/G12 -> 0.038610619 | M12: =MarketData!$C$58 -> 0.038470168 | N12: =(L12-M12)*10000 -> 1.4045054
A13: =MarketData!$A$59 -> 46440 | B13: =(A13-MarketData!$B$4)/360 -> 0.73055556 | C13: =EXP(INDEX(Bootstrap!$D$39:$D$59,MATCH($B13,Bootstrap!$B$39:$B$59,1))+(INDEX(Bootstrap!$D$39:$D$59,MATCH($B13,Bootstrap!$B$39:$B$59,1)+1)-INDEX(Bootstrap!$D$39:$D$59,MATCH($B13,Bootstrap!$B$39:$B$59,1)))*(($B13)-INDEX(Bootstrap!$B$39:$B$59,MATCH($B13,Bootstrap!$B$39:$B$59,1)))/(INDEX(Bootstrap!$B$39:$B$59,MATCH($B13,Bootstrap!$B$39:$B$59,1)+1)-INDEX(Bootstrap!$B$39:$B$59,MATCH($B13,Bootstrap!$B$39:$B$59,1)))) -> 0.97309386 | D13: =MarketData!$B$59 -> 0.97311492 | E13: =(LN(D13)-LN(C13))/B13*10000 -> 0.29618492 | F13: =A14 -> 46468 | G13: =(F13-A13)/360 -> 0.077777778 | H13: =WORKDAY(A13,-5) -> 46433 | I13: =WORKDAY(F13,-5) -> 46461 | J13: =EXP(INDEX(Bootstrap!$D$39:$D$59,MATCH((($H13-MarketData!$B$4)/360),Bootstrap!$B$39:$B$59,1))+(INDEX(Bootstrap!$D$39:$D$59,MATCH((($H13-MarketData!$B$4)/360),Bootstrap!$B$39:$B$59,1)+1)-INDEX(Bootstrap!$D$39:$D$59,MATCH((($H13-MarketData!$B$4)/360),Bootstrap!$B$39:$B$59,1)))*(((($H13-MarketData!$B$4)/360))-INDEX(Bootstrap!$B$39:$B$59,MATCH((($H13-MarketData!$B$4)/360),Bootstrap!$B$39:$B$59,1)))/(INDEX(Bootstrap!$B$39:$B$59,MATCH((($H13-MarketData!$B$4)/360),Bootstrap!$B$39:$B$59,1)+1)-INDEX(Bootstrap!$B$39:$B$59,MATCH((($H13-MarketData!$B$4)/360),Bootstrap!$B$39:$B$59,1)))) -> 0.97382335 | K13: =EXP(INDEX(Bootstrap!$D$39:$D$59,MATCH((($I13-MarketData!$B$4)/360),Bootstrap!$B$39:$B$59,1))+(INDEX(Bootstrap!$D$39:$D$59,MATCH((($I13-MarketData!$B$4)/360),Bootstrap!$B$39:$B$59,1)+1)-INDEX(Bootstrap!$D$39:$D$59,MATCH((($I13-MarketData!$B$4)/360),Bootstrap!$B$39:$B$59,1)))*(((($I13-MarketData!$B$4)/360))-INDEX(Bootstrap!$B$39:$B$59,MATCH((($I13-MarketData!$B$4)/360),Bootstrap!$B$39:$B$59,1)))/(INDEX(Bootstrap!$B$39:$B$59,MATCH((($I13-MarketData!$B$4)/360),Bootstrap!$B$39:$B$59,1)+1)-INDEX(Bootstrap!$B$39:$B$59,MATCH((($I13-MarketData!$B$4)/360),Bootstrap!$B$39:$B$59,1)))) -> 0.97090865 | L13: =(J13/K13-1)/G13 -> 0.038597559 | M13: =MarketData!$C$59 -> 0.038597781 | N13: =(L13-M13)*10000 -> -0.0022171085
A14: =MarketData!$A$60 -> 46468 | B14: =(A14-MarketData!$B$4)/360 -> 0.80833333 | C14: =EXP(INDEX(Bootstrap!$D$39:$D$59,MATCH($B14,Bootstrap!$B$39:$B$59,1))+(INDEX(Bootstrap!$D$39:$D$59,MATCH($B14,Bootstrap!$B$39:$B$59,1)+1)-INDEX(Bootstrap!$D$39:$D$59,MATCH($B14,Bootstrap!$B$39:$B$59,1)))*(($B14)-INDEX(Bootstrap!$B$39:$B$59,MATCH($B14,Bootstrap!$B$39:$B$59,1)))/(INDEX(Bootstrap!$B$39:$B$59,MATCH($B14,Bootstrap!$B$39:$B$59,1)+1)-INDEX(Bootstrap!$B$39:$B$59,MATCH($B14,Bootstrap!$B$39:$B$59,1)))) -> 0.97017429 | D14: =MarketData!$B$60 -> 0.97019528 | E14: =(LN(D14)-LN(C14))/B14*10000 -> 0.26767931 | F14: =A15 -> 46497 | G14: =(F14-A14)/360 -> 0.080555556 | H14: =WORKDAY(A14,-5) -> 46461 | I14: =WORKDAY(F14,-5) -> 46490 | J14: =EXP(INDEX(Bootstrap!$D$39:$D$59,MATCH((($H14-MarketData!$B$4)/360),Bootstrap!$B$39:$B$59,1))+(INDEX(Bootstrap!$D$39:$D$59,MATCH((($H14-MarketData!$B$4)/360),Bootstrap!$B$39:$B$59,1)+1)-INDEX(Bootstrap!$D$39:$D$59,MATCH((($H14-MarketData!$B$4)/360),Bootstrap!$B$39:$B$59,1)))*(((($H14-MarketData!$B$4)/360))-INDEX(Bootstrap!$B$39:$B$59,MATCH((($H14-MarketData!$B$4)/360),Bootstrap!$B$39:$B$59,1)))/(INDEX(Bootstrap!$B$39:$B$59,MATCH((($H14-MarketData!$B$4)/360),Bootstrap!$B$39:$B$59,1)+1)-INDEX(Bootstrap!$B$39:$B$59,MATCH((($H14-MarketData!$B$4)/360),Bootstrap!$B$39:$B$59,1)))) -> 0.97090865 | K14: =EXP(INDEX(Bootstrap!$D$39:$D$59,MATCH((($I14-MarketData!$B$4)/360),Bootstrap!$B$39:$B$59,1))+(INDEX(Bootstrap!$D$39:$D$59,MATCH((($I14-MarketData!$B$4)/360),Bootstrap!$B$39:$B$59,1)+1)-INDEX(Bootstrap!$D$39:$D$59,MATCH((($I14-MarketData!$B$4)/360),Bootstrap!$B$39:$B$59,1)))*(((($I14-MarketData!$B$4)/360))-INDEX(Bootstrap!$B$39:$B$59,MATCH((($I14-MarketData!$B$4)/360),Bootstrap!$B$39:$B$59,1)))/(INDEX(Bootstrap!$B$39:$B$59,MATCH((($I14-MarketData!$B$4)/360),Bootstrap!$B$39:$B$59,1)+1)-INDEX(Bootstrap!$B$39:$B$59,MATCH((($I14-MarketData!$B$4)/360),Bootstrap!$B$39:$B$59,1)))) -> 0.9678533 | L14: =(J14/K14-1)/G14 -> 0.03918827 | M14: =MarketData!$C$60 -> 0.039187753 | N14: =(L14-M14)*10000 -> 0.0051641493
A15: =MarketData!$A$61 -> 46497 | B15: =(A15-MarketData!$B$4)/360 -> 0.88888889 | C15: =EXP(INDEX(Bootstrap!$D$39:$D$59,MATCH($B15,Bootstrap!$B$39:$B$59,1))+(INDEX(Bootstrap!$D$39:$D$59,MATCH($B15,Bootstrap!$B$39:$B$59,1)+1)-INDEX(Bootstrap!$D$39:$D$59,MATCH($B15,Bootstrap!$B$39:$B$59,1)))*(($B15)-INDEX(Bootstrap!$B$39:$B$59,MATCH($B15,Bootstrap!$B$39:$B$59,1)))/(INDEX(Bootstrap!$B$39:$B$59,MATCH($B15,Bootstrap!$B$39:$B$59,1)+1)-INDEX(Bootstrap!$B$39:$B$59,MATCH($B15,Bootstrap!$B$39:$B$59,1)))) -> 0.96711597 | D15: =MarketData!$B$61 -> 0.9671369 | E15: =(LN(D15)-LN(C15))/B15*10000 -> 0.24342326 | F15: =A16 -> 46527 | G15: =(F15-A15)/360 -> 0.083333333 | H15: =WORKDAY(A15,-5) -> 46490 | I15: =WORKDAY(F15,-5) -> 46520 | J15: =EXP(INDEX(Bootstrap!$D$39:$D$59,MATCH((($H15-MarketData!$B$4)/360),Bootstrap!$B$39:$B$59,1))+(INDEX(Bootstrap!$D$39:$D$59,MATCH((($H15-MarketData!$B$4)/360),Bootstrap!$B$39:$B$59,1)+1)-INDEX(Bootstrap!$D$39:$D$59,MATCH((($H15-MarketData!$B$4)/360),Bootstrap!$B$39:$B$59,1)))*(((($H15-MarketData!$B$4)/360))-INDEX(Bootstrap!$B$39:$B$59,MATCH((($H15-MarketData!$B$4)/360),Bootstrap!$B$39:$B$59,1)))/(INDEX(Bootstrap!$B$39:$B$59,MATCH((($H15-MarketData!$B$4)/360),Bootstrap!$B$39:$B$59,1)+1)-INDEX(Bootstrap!$B$39:$B$59,MATCH((($H15-MarketData!$B$4)/360),Bootstrap!$B$39:$B$59,1)))) -> 0.9678533 | K15: =EXP(INDEX(Bootstrap!$D$39:$D$59,MATCH((($I15-MarketData!$B$4)/360),Bootstrap!$B$39:$B$59,1))+(INDEX(Bootstrap!$D$39:$D$59,MATCH((($I15-MarketData!$B$4)/360),Bootstrap!$B$39:$B$59,1)+1)-INDEX(Bootstrap!$D$39:$D$59,MATCH((($I15-MarketData!$B$4)/360),Bootstrap!$B$39:$B$59,1)))*(((($I15-MarketData!$B$4)/360))-INDEX(Bootstrap!$B$39:$B$59,MATCH((($I15-MarketData!$B$4)/360),Bootstrap!$B$39:$B$59,1)))/(INDEX(Bootstrap!$B$39:$B$59,MATCH((($I15-MarketData!$B$4)/360),Bootstrap!$B$39:$B$59,1)+1)-INDEX(Bootstrap!$B$39:$B$59,MATCH((($I15-MarketData!$B$4)/360),Bootstrap!$B$39:$B$59,1)))) -> 0.96467333 | L15: =(J15/K15-1)/G15 -> 0.039557065 | M15: =MarketData!$C$61 -> 0.039557065 | N15: =(L15-M15)*10000 -> 9.6726169e-08
A16: =MarketData!$A$62 -> 46527 | B16: =(A16-MarketData!$B$4)/360 -> 0.97222222 | C16: =EXP(INDEX(Bootstrap!$D$39:$D$59,MATCH($B16,Bootstrap!$B$39:$B$59,1))+(INDEX(Bootstrap!$D$39:$D$59,MATCH($B16,Bootstrap!$B$39:$B$59,1)+1)-INDEX(Bootstrap!$D$39:$D$59,MATCH($B16,Bootstrap!$B$39:$B$59,1)))*(($B16)-INDEX(Bootstrap!$B$39:$B$59,MATCH($B16,Bootstrap!$B$39:$B$59,1)))/(INDEX(Bootstrap!$B$39:$B$59,MATCH($B16,Bootstrap!$B$39:$B$59,1)+1)-INDEX(Bootstrap!$B$39:$B$59,MATCH($B16,Bootstrap!$B$39:$B$59,1)))) -> 0.96392647 | D16: =MarketData!$B$62 -> 0.96394732 | E16: =(LN(D16)-LN(C16))/B16*10000 -> 0.22255877 | F16: =A17 -> 46559 | G16: =(F16-A16)/360 -> 0.088888889 | H16: =WORKDAY(A16,-5) -> 46520 | I16: =WORKDAY(F16,-5) -> 46552 | J16: =EXP(INDEX(Bootstrap!$D$39:$D$59,MATCH((($H16-MarketData!$B$4)/360),Bootstrap!$B$39:$B$59,1))+(INDEX(Bootstrap!$D$39:$D$59,MATCH((($H16-MarketData!$B$4)/360),Bootstrap!$B$39:$B$59,1)+1)-INDEX(Bootstrap!$D$39:$D$59,MATCH((($H16-MarketData!$B$4)/360),Bootstrap!$B$39:$B$59,1)))*(((($H16-MarketData!$B$4)/360))-INDEX(Bootstrap!$B$39:$B$59,MATCH((($H16-MarketData!$B$4)/360),Bootstrap!$B$39:$B$59,1)))/(INDEX(Bootstrap!$B$39:$B$59,MATCH((($H16-MarketData!$B$4)/360),Bootstrap!$B$39:$B$59,1)+1)-INDEX(Bootstrap!$B$39:$B$59,MATCH((($H16-MarketData!$B$4)/360),Bootstrap!$B$39:$B$59,1)))) -> 0.96467333 | K16: =EXP(INDEX(Bootstrap!$D$39:$D$59,MATCH((($I16-MarketData!$B$4)/360),Bootstrap!$B$39:$B$59,1))+(INDEX(Bootstrap!$D$39:$D$59,MATCH((($I16-MarketData!$B$4)/360),Bootstrap!$B$39:$B$59,1)+1)-INDEX(Bootstrap!$D$39:$D$59,MATCH((($I16-MarketData!$B$4)/360),Bootstrap!$B$39:$B$59,1)))*(((($I16-MarketData!$B$4)/360))-INDEX(Bootstrap!$B$39:$B$59,MATCH((($I16-MarketData!$B$4)/360),Bootstrap!$B$39:$B$59,1)))/(INDEX(Bootstrap!$B$39:$B$59,MATCH((($I16-MarketData!$B$4)/360),Bootstrap!$B$39:$B$59,1)+1)-INDEX(Bootstrap!$B$39:$B$59,MATCH((($I16-MarketData!$B$4)/360),Bootstrap!$B$39:$B$59,1)))) -> 0.96126295 | L16: =(J16/K16-1)/G16 -> 0.039912866 | M16: =MarketData!$C$62 -> 0.039907075 | N16: =(L16-M16)*10000 -> 0.057908007
A17: =MarketData!$A$63 -> 46559 | B17: =(A17-MarketData!$B$4)/360 -> 1.0611111 | C17: =EXP(INDEX(Bootstrap!$D$39:$D$59,MATCH($B17,Bootstrap!$B$39:$B$59,1))+(INDEX(Bootstrap!$D$39:$D$59,MATCH($B17,Bootstrap!$B$39:$B$59,1)+1)-INDEX(Bootstrap!$D$39:$D$59,MATCH($B17,Bootstrap!$B$39:$B$59,1)))*(($B17)-INDEX(Bootstrap!$B$39:$B$59,MATCH($B17,Bootstrap!$B$39:$B$59,1)))/(INDEX(Bootstrap!$B$39:$B$59,MATCH($B17,Bootstrap!$B$39:$B$59,1)+1)-INDEX(Bootstrap!$B$39:$B$59,MATCH($B17,Bootstrap!$B$39:$B$59,1)))) -> 0.96051912 | D17: =MarketData!$B$63 -> 0.96053938 | E17: =(LN(D17)-LN(C17))/B17*10000 -> 0.19880759 | F17: =A18 -> 46588 | G17: =(F17-A17)/360 -> 0.080555556 | H17: =WORKDAY(A17,-5) -> 46552 | I17: =WORKDAY(F17,-5) -> 46581 | J17: =EXP(INDEX(Bootstrap!$D$39:$D$59,MATCH((($H17-MarketData!$B$4)/360),Bootstrap!$B$39:$B$59,1))+(INDEX(Bootstrap!$D$39:$D$59,MATCH((($H17-MarketData!$B$4)/360),Bootstrap!$B$39:$B$59,1)+1)-INDEX(Bootstrap!$D$39:$D$59,MATCH((($H17-MarketData!$B$4)/360),Bootstrap!$B$39:$B$59,1)))*(((($H17-MarketData!$B$4)/360))-INDEX(Bootstrap!$B$39:$B$59,MATCH((($H17-MarketData!$B$4)/360),Bootstrap!$B$39:$B$59,1)))/(INDEX(Bootstrap!$B$39:$B$59,MATCH((($H17-MarketData!$B$4)/360),Bootstrap!$B$39:$B$59,1)+1)-INDEX(Bootstrap!$B$39:$B$59,MATCH((($H17-MarketData!$B$4)/360),Bootstrap!$B$39:$B$59,1)))) -> 0.96126295 | K17: =EXP(INDEX(Bootstrap!$D$39:$D$59,MATCH((($I17-MarketData!$B$4)/360),Bootstrap!$B$39:$B$59,1))+(INDEX(Bootstrap!$D$39:$D$59,MATCH((($I17-MarketData!$B$4)/360),Bootstrap!$B$39:$B$59,1)+1)-INDEX(Bootstrap!$D$39:$D$59,MATCH((($I17-MarketData!$B$4)/360),Bootstrap!$B$39:$B$59,1)))*(((($I17-MarketData!$B$4)/360))-INDEX(Bootstrap!$B$39:$B$59,MATCH((($I17-MarketData!$B$4)/360),Bootstrap!$B$39:$B$59,1)))/(INDEX(Bootstrap!$B$39:$B$59,MATCH((($I17-MarketData!$B$4)/360),Bootstrap!$B$39:$B$59,1)+1)-INDEX(Bootstrap!$B$39:$B$59,MATCH((($I17-MarketData!$B$4)/360),Bootstrap!$B$39:$B$59,1)))) -> 0.95818743 | L17: =(J17/K17-1)/G17 -> 0.039844897 | M17: =MarketData!$C$63 -> 0.03990391 | N17: =(L17-M17)*10000 -> -0.59013569
A18: =MarketData!$A$64 -> 46588 | B18: =(A18-MarketData!$B$4)/360 -> 1.1416667 | C18: =EXP(INDEX(Bootstrap!$D$39:$D$59,MATCH($B18,Bootstrap!$B$39:$B$59,1))+(INDEX(Bootstrap!$D$39:$D$59,MATCH($B18,Bootstrap!$B$39:$B$59,1)+1)-INDEX(Bootstrap!$D$39:$D$59,MATCH($B18,Bootstrap!$B$39:$B$59,1)))*(($B18)-INDEX(Bootstrap!$B$39:$B$59,MATCH($B18,Bootstrap!$B$39:$B$59,1)))/(INDEX(Bootstrap!$B$39:$B$59,MATCH($B18,Bootstrap!$B$39:$B$59,1)+1)-INDEX(Bootstrap!$B$39:$B$59,MATCH($B18,Bootstrap!$B$39:$B$59,1)))) -> 0.95744672 | D18: =MarketData!$B$64 -> 0.95746285 | E18: =(LN(D18)-LN(C18))/B18*10000 -> 0.1475412 | F18: =A19 -> 46619 | G18: =(F18-A18)/360 -> 0.086111111 | H18: =WORKDAY(A18,-5) -> 46581 | I18: =WORKDAY(F18,-5) -> 46612 | J18: =EXP(INDEX(Bootstrap!$D$39:$D$59,MATCH((($H18-MarketData!$B$4)/360),Bootstrap!$B$39:$B$59,1))+(INDEX(Bootstrap!$D$39:$D$59,MATCH((($H18-MarketData!$B$4)/360),Bootstrap!$B$39:$B$59,1)+1)-INDEX(Bootstrap!$D$39:$D$59,MATCH((($H18-MarketData!$B$4)/360),Bootstrap!$B$39:$B$59,1)))*(((($H18-MarketData!$B$4)/360))-INDEX(Bootstrap!$B$39:$B$59,MATCH((($H18-MarketData!$B$4)/360),Bootstrap!$B$39:$B$59,1)))/(INDEX(Bootstrap!$B$39:$B$59,MATCH((($H18-MarketData!$B$4)/360),Bootstrap!$B$39:$B$59,1)+1)-INDEX(Bootstrap!$B$39:$B$59,MATCH((($H18-MarketData!$B$4)/360),Bootstrap!$B$39:$B$59,1)))) -> 0.95818743 | K18: =EXP(INDEX(Bootstrap!$D$39:$D$59,MATCH((($I18-MarketData!$B$4)/360),Bootstrap!$B$39:$B$59,1))+(INDEX(Bootstrap!$D$39:$D$59,MATCH((($I18-MarketData!$B$4)/360),Bootstrap!$B$39:$B$59,1)+1)-INDEX(Bootstrap!$D$39:$D$59,MATCH((($I18-MarketData!$B$4)/360),Bootstrap!$B$39:$B$59,1)))*(((($I18-MarketData!$B$4)/360))-INDEX(Bootstrap!$B$39:$B$59,MATCH((($I18-MarketData!$B$4)/360),Bootstrap!$B$39:$B$59,1)))/(INDEX(Bootstrap!$B$39:$B$59,MATCH((($I18-MarketData!$B$4)/360),Bootstrap!$B$39:$B$59,1)+1)-INDEX(Bootstrap!$B$39:$B$59,MATCH((($I18-MarketData!$B$4)/360),Bootstrap!$B$39:$B$59,1)))) -> 0.95491148 | L18: =(J18/K18-1)/G18 -> 0.039839592 | M18: =MarketData!$C$64 -> 0.03984468 | N18: =(L18-M18)*10000 -> -0.050874797
A19: =MarketData!$A$65 -> 46619 | B19: =(A19-MarketData!$B$4)/360 -> 1.2277778 | C19: =EXP(INDEX(Bootstrap!$D$39:$D$59,MATCH($B19,Bootstrap!$B$39:$B$59,1))+(INDEX(Bootstrap!$D$39:$D$59,MATCH($B19,Bootstrap!$B$39:$B$59,1)+1)-INDEX(Bootstrap!$D$39:$D$59,MATCH($B19,Bootstrap!$B$39:$B$59,1)))*(($B19)-INDEX(Bootstrap!$B$39:$B$59,MATCH($B19,Bootstrap!$B$39:$B$59,1)))/(INDEX(Bootstrap!$B$39:$B$59,MATCH($B19,Bootstrap!$B$39:$B$59,1)+1)-INDEX(Bootstrap!$B$39:$B$59,MATCH($B19,Bootstrap!$B$39:$B$59,1)))) -> 0.95417331 | D19: =MarketData!$B$65 -> 0.95419016 | E19: =(LN(D19)-LN(C19))/B19*10000 -> 0.14382736 | F19: =A20 -> 46650 | G19: =(F19-A19)/360 -> 0.086111111 | H19: =WORKDAY(A19,-5) -> 46612 | I19: =WORKDAY(F19,-5) -> 46643 | J19: =EXP(INDEX(Bootstrap!$D$39:$D$59,MATCH((($H19-MarketData!$B$4)/360),Bootstrap!$B$39:$B$59,1))+(INDEX(Bootstrap!$D$39:$D$59,MATCH((($H19-MarketData!$B$4)/360),Bootstrap!$B$39:$B$59,1)+1)-INDEX(Bootstrap!$D$39:$D$59,MATCH((($H19-MarketData!$B$4)/360),Bootstrap!$B$39:$B$59,1)))*(((($H19-MarketData!$B$4)/360))-INDEX(Bootstrap!$B$39:$B$59,MATCH((($H19-MarketData!$B$4)/360),Bootstrap!$B$39:$B$59,1)))/(INDEX(Bootstrap!$B$39:$B$59,MATCH((($H19-MarketData!$B$4)/360),Bootstrap!$B$39:$B$59,1)+1)-INDEX(Bootstrap!$B$39:$B$59,MATCH((($H19-MarketData!$B$4)/360),Bootstrap!$B$39:$B$59,1)))) -> 0.95491148 | K19: =EXP(INDEX(Bootstrap!$D$39:$D$59,MATCH((($I19-MarketData!$B$4)/360),Bootstrap!$B$39:$B$59,1))+(INDEX(Bootstrap!$D$39:$D$59,MATCH((($I19-MarketData!$B$4)/360),Bootstrap!$B$39:$B$59,1)+1)-INDEX(Bootstrap!$D$39:$D$59,MATCH((($I19-MarketData!$B$4)/360),Bootstrap!$B$39:$B$59,1)))*(((($I19-MarketData!$B$4)/360))-INDEX(Bootstrap!$B$39:$B$59,MATCH((($I19-MarketData!$B$4)/360),Bootstrap!$B$39:$B$59,1)))/(INDEX(Bootstrap!$B$39:$B$59,MATCH((($I19-MarketData!$B$4)/360),Bootstrap!$B$39:$B$59,1)+1)-INDEX(Bootstrap!$B$39:$B$59,MATCH((($I19-MarketData!$B$4)/360),Bootstrap!$B$39:$B$59,1)))) -> 0.95164674 | L19: =(J19/K19-1)/G19 -> 0.039839592 | M19: =MarketData!$C$65 -> 0.039780505 | N19: =(L19-M19)*10000 -> 0.5908782
A20: =MarketData!$A$66 -> 46650 | B20: =(A20-MarketData!$B$4)/360 -> 1.3138889 | C20: =EXP(INDEX(Bootstrap!$D$39:$D$59,MATCH($B20,Bootstrap!$B$39:$B$59,1))+(INDEX(Bootstrap!$D$39:$D$59,MATCH($B20,Bootstrap!$B$39:$B$59,1)+1)-INDEX(Bootstrap!$D$39:$D$59,MATCH($B20,Bootstrap!$B$39:$B$59,1)))*(($B20)-INDEX(Bootstrap!$B$39:$B$59,MATCH($B20,Bootstrap!$B$39:$B$59,1)))/(INDEX(Bootstrap!$B$39:$B$59,MATCH($B20,Bootstrap!$B$39:$B$59,1)+1)-INDEX(Bootstrap!$B$39:$B$59,MATCH($B20,Bootstrap!$B$39:$B$59,1)))) -> 0.95091188 | D20: =MarketData!$B$66 -> 0.95093372 | E20: =(LN(D20)-LN(C20))/B20*10000 -> 0.17482453 | F20: =A21 -> 46680 | G20: =(F20-A20)/360 -> 0.083333333 | H20: =WORKDAY(A20,-5) -> 46643 | I20: =WORKDAY(F20,-5) -> 46673 | J20: =EXP(INDEX(Bootstrap!$D$39:$D$59,MATCH((($H20-MarketData!$B$4)/360),Bootstrap!$B$39:$B$59,1))+(INDEX(Bootstrap!$D$39:$D$59,MATCH((($H20-MarketData!$B$4)/360),Bootstrap!$B$39:$B$59,1)+1)-INDEX(Bootstrap!$D$39:$D$59,MATCH((($H20-MarketData!$B$4)/360),Bootstrap!$B$39:$B$59,1)))*(((($H20-MarketData!$B$4)/360))-INDEX(Bootstrap!$B$39:$B$59,MATCH((($H20-MarketData!$B$4)/360),Bootstrap!$B$39:$B$59,1)))/(INDEX(Bootstrap!$B$39:$B$59,MATCH((($H20-MarketData!$B$4)/360),Bootstrap!$B$39:$B$59,1)+1)-INDEX(Bootstrap!$B$39:$B$59,MATCH((($H20-MarketData!$B$4)/360),Bootstrap!$B$39:$B$59,1)))) -> 0.95164674 | K20: =EXP(INDEX(Bootstrap!$D$39:$D$59,MATCH((($I20-MarketData!$B$4)/360),Bootstrap!$B$39:$B$59,1))+(INDEX(Bootstrap!$D$39:$D$59,MATCH((($I20-MarketData!$B$4)/360),Bootstrap!$B$39:$B$59,1)+1)-INDEX(Bootstrap!$D$39:$D$59,MATCH((($I20-MarketData!$B$4)/360),Bootstrap!$B$39:$B$59,1)))*(((($I20-MarketData!$B$4)/360))-INDEX(Bootstrap!$B$39:$B$59,MATCH((($I20-MarketData!$B$4)/360),Bootstrap!$B$39:$B$59,1)))/(INDEX(Bootstrap!$B$39:$B$59,MATCH((($I20-MarketData!$B$4)/360),Bootstrap!$B$39:$B$59,1)+1)-INDEX(Bootstrap!$B$39:$B$59,MATCH((($I20-MarketData!$B$4)/360),Bootstrap!$B$39:$B$59,1)))) -> 0.94850238 | L20: =(J20/K20-1)/G20 -> 0.039780839 | M20: =MarketData!$C$66 -> 0.039706712 | N20: =(L20-M20)*10000 -> 0.74126937
A21: =MarketData!$A$67 -> 46680 | B21: =(A21-MarketData!$B$4)/360 -> 1.3972222 | C21: =EXP(INDEX(Bootstrap!$D$39:$D$59,MATCH($B21,Bootstrap!$B$39:$B$59,1))+(INDEX(Bootstrap!$D$39:$D$59,MATCH($B21,Bootstrap!$B$39:$B$59,1)+1)-INDEX(Bootstrap!$D$39:$D$59,MATCH($B21,Bootstrap!$B$39:$B$59,1)))*(($B21)-INDEX(Bootstrap!$B$39:$B$59,MATCH($B21,Bootstrap!$B$39:$B$59,1)))/(INDEX(Bootstrap!$B$39:$B$59,MATCH($B21,Bootstrap!$B$39:$B$59,1)+1)-INDEX(Bootstrap!$B$39:$B$59,MATCH($B21,Bootstrap!$B$39:$B$59,1)))) -> 0.94777027 | D21: =MarketData!$B$67 -> 0.94779996 | E21: =(LN(D21)-LN(C21))/B21*10000 -> 0.22418001 | F21: =A22 -> 46713 | G21: =(F21-A21)/360 -> 0.091666667 | H21: =WORKDAY(A21,-5) -> 46673 | I21: =WORKDAY(F21,-5) -> 46706 | J21: =EXP(INDEX(Bootstrap!$D$39:$D$59,MATCH((($H21-MarketData!$B$4)/360),Bootstrap!$B$39:$B$59,1))+(INDEX(Bootstrap!$D$39:$D$59,MATCH((($H21-MarketData!$B$4)/360),Bootstrap!$B$39:$B$59,1)+1)-INDEX(Bootstrap!$D$39:$D$59,MATCH((($H21-MarketData!$B$4)/360),Bootstrap!$B$39:$B$59,1)))*(((($H21-MarketData!$B$4)/360))-INDEX(Bootstrap!$B$39:$B$59,MATCH((($H21-MarketData!$B$4)/360),Bootstrap!$B$39:$B$59,1)))/(INDEX(Bootstrap!$B$39:$B$59,MATCH((($H21-MarketData!$B$4)/360),Bootstrap!$B$39:$B$59,1)+1)-INDEX(Bootstrap!$B$39:$B$59,MATCH((($H21-MarketData!$B$4)/360),Bootstrap!$B$39:$B$59,1)))) -> 0.94850238 | K21: =EXP(INDEX(Bootstrap!$D$39:$D$59,MATCH((($I21-MarketData!$B$4)/360),Bootstrap!$B$39:$B$59,1))+(INDEX(Bootstrap!$D$39:$D$59,MATCH((($I21-MarketData!$B$4)/360),Bootstrap!$B$39:$B$59,1)+1)-INDEX(Bootstrap!$D$39:$D$59,MATCH((($I21-MarketData!$B$4)/360),Bootstrap!$B$39:$B$59,1)))*(((($I21-MarketData!$B$4)/360))-INDEX(Bootstrap!$B$39:$B$59,MATCH((($I21-MarketData!$B$4)/360),Bootstrap!$B$39:$B$59,1)))/(INDEX(Bootstrap!$B$39:$B$59,MATCH((($I21-MarketData!$B$4)/360),Bootstrap!$B$39:$B$59,1)+1)-INDEX(Bootstrap!$B$39:$B$59,MATCH((($I21-MarketData!$B$4)/360),Bootstrap!$B$39:$B$59,1)))) -> 0.94505594 | L21: =(J21/K21-1)/G21 -> 0.039783386 | M21: =MarketData!$C$67 -> 0.03957283 | N21: =(L21-M21)*10000 -> 2.105555
A22: =MarketData!$A$68 -> 46713 | B22: =(A22-MarketData!$B$4)/360 -> 1.4888889 | C22: =EXP(INDEX(Bootstrap!$D$39:$D$59,MATCH($B22,Bootstrap!$B$39:$B$59,1))+(INDEX(Bootstrap!$D$39:$D$59,MATCH($B22,Bootstrap!$B$39:$B$59,1)+1)-INDEX(Bootstrap!$D$39:$D$59,MATCH($B22,Bootstrap!$B$39:$B$59,1)))*(($B22)-INDEX(Bootstrap!$B$39:$B$59,MATCH($B22,Bootstrap!$B$39:$B$59,1)))/(INDEX(Bootstrap!$B$39:$B$59,MATCH($B22,Bootstrap!$B$39:$B$59,1)+1)-INDEX(Bootstrap!$B$39:$B$59,MATCH($B22,Bootstrap!$B$39:$B$59,1)))) -> 0.94432649 | D22: =MarketData!$B$68 -> 0.94437708 | E22: =(LN(D22)-LN(C22))/B22*10000 -> 0.35979942 | F22: =A23 -> 46741 | G22: =(F22-A22)/360 -> 0.077777778 | H22: =WORKDAY(A22,-5) -> 46706 | I22: =WORKDAY(F22,-5) -> 46734 | J22: =EXP(INDEX(Bootstrap!$D$39:$D$59,MATCH((($H22-MarketData!$B$4)/360),Bootstrap!$B$39:$B$59,1))+(INDEX(Bootstrap!$D$39:$D$59,MATCH((($H22-MarketData!$B$4)/360),Bootstrap!$B$39:$B$59,1)+1)-INDEX(Bootstrap!$D$39:$D$59,MATCH((($H22-MarketData!$B$4)/360),Bootstrap!$B$39:$B$59,1)))*(((($H22-MarketData!$B$4)/360))-INDEX(Bootstrap!$B$39:$B$59,MATCH((($H22-MarketData!$B$4)/360),Bootstrap!$B$39:$B$59,1)))/(INDEX(Bootstrap!$B$39:$B$59,MATCH((($H22-MarketData!$B$4)/360),Bootstrap!$B$39:$B$59,1)+1)-INDEX(Bootstrap!$B$39:$B$59,MATCH((($H22-MarketData!$B$4)/360),Bootstrap!$B$39:$B$59,1)))) -> 0.94505594 | K22: =EXP(INDEX(Bootstrap!$D$39:$D$59,MATCH((($I22-MarketData!$B$4)/360),Bootstrap!$B$39:$B$59,1))+(INDEX(Bootstrap!$D$39:$D$59,MATCH((($I22-MarketData!$B$4)/360),Bootstrap!$B$39:$B$59,1)+1)-INDEX(Bootstrap!$D$39:$D$59,MATCH((($I22-MarketData!$B$4)/360),Bootstrap!$B$39:$B$59,1)))*(((($I22-MarketData!$B$4)/360))-INDEX(Bootstrap!$B$39:$B$59,MATCH((($I22-MarketData!$B$4)/360),Bootstrap!$B$39:$B$59,1)))/(INDEX(Bootstrap!$B$39:$B$59,MATCH((($I22-MarketData!$B$4)/360),Bootstrap!$B$39:$B$59,1)+1)-INDEX(Bootstrap!$B$39:$B$59,MATCH((($I22-MarketData!$B$4)/360),Bootstrap!$B$39:$B$59,1)))) -> 0.94214151 | L22: =(J22/K22-1)/G22 -> 0.03977241 | M22: =MarketData!$C$68 -> 0.039423828 | N22: =(L22-M22)*10000 -> 3.4858236
A23: =MarketData!$A$69 -> 46741 | B23: =(A23-MarketData!$B$4)/360 -> 1.5666667 | C23: =EXP(INDEX(Bootstrap!$D$39:$D$59,MATCH($B23,Bootstrap!$B$39:$B$59,1))+(INDEX(Bootstrap!$D$39:$D$59,MATCH($B23,Bootstrap!$B$39:$B$59,1)+1)-INDEX(Bootstrap!$D$39:$D$59,MATCH($B23,Bootstrap!$B$39:$B$59,1)))*(($B23)-INDEX(Bootstrap!$B$39:$B$59,MATCH($B23,Bootstrap!$B$39:$B$59,1)))/(INDEX(Bootstrap!$B$39:$B$59,MATCH($B23,Bootstrap!$B$39:$B$59,1)+1)-INDEX(Bootstrap!$B$39:$B$59,MATCH($B23,Bootstrap!$B$39:$B$59,1)))) -> 0.94141744 | D23: =MarketData!$B$69 -> 0.94149399 | E23: =(LN(D23)-LN(C23))/B23*10000 -> 0.51895077 | F23: =A24 -> 46772 | G23: =(F23-A23)/360 -> 0.086111111 | H23: =WORKDAY(A23,-5) -> 46734 | I23: =WORKDAY(F23,-5) -> 46765 | J23: =EXP(INDEX(Bootstrap!$D$39:$D$59,MATCH((($H23-MarketData!$B$4)/360),Bootstrap!$B$39:$B$59,1))+(INDEX(Bootstrap!$D$39:$D$59,MATCH((($H23-MarketData!$B$4)/360),Bootstrap!$B$39:$B$59,1)+1)-INDEX(Bootstrap!$D$39:$D$59,MATCH((($H23-MarketData!$B$4)/360),Bootstrap!$B$39:$B$59,1)))*(((($H23-MarketData!$B$4)/360))-INDEX(Bootstrap!$B$39:$B$59,MATCH((($H23-MarketData!$B$4)/360),Bootstrap!$B$39:$B$59,1)))/(INDEX(Bootstrap!$B$39:$B$59,MATCH((($H23-MarketData!$B$4)/360),Bootstrap!$B$39:$B$59,1)+1)-INDEX(Bootstrap!$B$39:$B$59,MATCH((($H23-MarketData!$B$4)/360),Bootstrap!$B$39:$B$59,1)))) -> 0.94214151 | K23: =EXP(INDEX(Bootstrap!$D$39:$D$59,MATCH((($I23-MarketData!$B$4)/360),Bootstrap!$B$39:$B$59,1))+(INDEX(Bootstrap!$D$39:$D$59,MATCH((($I23-MarketData!$B$4)/360),Bootstrap!$B$39:$B$59,1)+1)-INDEX(Bootstrap!$D$39:$D$59,MATCH((($I23-MarketData!$B$4)/360),Bootstrap!$B$39:$B$59,1)))*(((($I23-MarketData!$B$4)/360))-INDEX(Bootstrap!$B$39:$B$59,MATCH((($I23-MarketData!$B$4)/360),Bootstrap!$B$39:$B$59,1)))/(INDEX(Bootstrap!$B$39:$B$59,MATCH((($I23-MarketData!$B$4)/360),Bootstrap!$B$39:$B$59,1)+1)-INDEX(Bootstrap!$B$39:$B$59,MATCH((($I23-MarketData!$B$4)/360),Bootstrap!$B$39:$B$59,1)))) -> 0.93894343 | L23: =(J23/K23-1)/G23 -> 0.039554097 | M23: =MarketData!$C$69 -> 0.039187225 | N23: =(L23-M23)*10000 -> 3.6687188
A24: =MarketData!$A$70 -> 46772 | B24: =(A24-MarketData!$B$4)/360 -> 1.6527778 | C24: =EXP(INDEX(Bootstrap!$D$39:$D$59,MATCH($B24,Bootstrap!$B$39:$B$59,1))+(INDEX(Bootstrap!$D$39:$D$59,MATCH($B24,Bootstrap!$B$39:$B$59,1)+1)-INDEX(Bootstrap!$D$39:$D$59,MATCH($B24,Bootstrap!$B$39:$B$59,1)))*(($B24)-INDEX(Bootstrap!$B$39:$B$59,MATCH($B24,Bootstrap!$B$39:$B$59,1)))/(INDEX(Bootstrap!$B$39:$B$59,MATCH($B24,Bootstrap!$B$39:$B$59,1)+1)-INDEX(Bootstrap!$B$39:$B$59,MATCH($B24,Bootstrap!$B$39:$B$59,1)))) -> 0.93822307 | D24: =MarketData!$B$70 -> 0.93833149 | E24: =(LN(D24)-LN(C24))/B24*10000 -> 0.69916184 | F24: =A25 -> 46805 | G24: =(F24-A24)/360 -> 0.091666667 | H24: =WORKDAY(A24,-5) -> 46765 | I24: =WORKDAY(F24,-5) -> 46798 | J24: =EXP(INDEX(Bootstrap!$D$39:$D$59,MATCH((($H24-MarketData!$B$4)/360),Bootstrap!$B$39:$B$59,1))+(INDEX(Bootstrap!$D$39:$D$59,MATCH((($H24-MarketData!$B$4)/360),Bootstrap!$B$39:$B$59,1)+1)-INDEX(Bootstrap!$D$39:$D$59,MATCH((($H24-MarketData!$B$4)/360),Bootstrap!$B$39:$B$59,1)))*(((($H24-MarketData!$B$4)/360))-INDEX(Bootstrap!$B$39:$B$59,MATCH((($H24-MarketData!$B$4)/360),Bootstrap!$B$39:$B$59,1)))/(INDEX(Bootstrap!$B$39:$B$59,MATCH((($H24-MarketData!$B$4)/360),Bootstrap!$B$39:$B$59,1)+1)-INDEX(Bootstrap!$B$39:$B$59,MATCH((($H24-MarketData!$B$4)/360),Bootstrap!$B$39:$B$59,1)))) -> 0.93894343 | K24: =EXP(INDEX(Bootstrap!$D$39:$D$59,MATCH((($I24-MarketData!$B$4)/360),Bootstrap!$B$39:$B$59,1))+(INDEX(Bootstrap!$D$39:$D$59,MATCH((($I24-MarketData!$B$4)/360),Bootstrap!$B$39:$B$59,1)+1)-INDEX(Bootstrap!$D$39:$D$59,MATCH((($I24-MarketData!$B$4)/360),Bootstrap!$B$39:$B$59,1)))*(((($I24-MarketData!$B$4)/360))-INDEX(Bootstrap!$B$39:$B$59,MATCH((($I24-MarketData!$B$4)/360),Bootstrap!$B$39:$B$59,1)))/(INDEX(Bootstrap!$B$39:$B$59,MATCH((($I24-MarketData!$B$4)/360),Bootstrap!$B$39:$B$59,1)+1)-INDEX(Bootstrap!$B$39:$B$59,MATCH((($I24-MarketData!$B$4)/360),Bootstrap!$B$39:$B$59,1)))) -> 0.93555227 | L24: =(J24/K24-1)/G24 -> 0.039542925 | M24: =MarketData!$C$70 -> 0.039005663 | N24: =(L24-M24)*10000 -> 5.3726181
A25: =MarketData!$A$71 -> 46805 | B25: =(A25-MarketData!$B$4)/360 -> 1.7444444 | C25: =EXP(INDEX(Bootstrap!$D$39:$D$59,MATCH($B25,Bootstrap!$B$39:$B$59,1))+(INDEX(Bootstrap!$D$39:$D$59,MATCH($B25,Bootstrap!$B$39:$B$59,1)+1)-INDEX(Bootstrap!$D$39:$D$59,MATCH($B25,Bootstrap!$B$39:$B$59,1)))*(($B25)-INDEX(Bootstrap!$B$39:$B$59,MATCH($B25,Bootstrap!$B$39:$B$59,1)))/(INDEX(Bootstrap!$B$39:$B$59,MATCH($B25,Bootstrap!$B$39:$B$59,1)+1)-INDEX(Bootstrap!$B$39:$B$59,MATCH($B25,Bootstrap!$B$39:$B$59,1)))) -> 0.93483451 | D25: =MarketData!$B$71 -> 0.93499187 | E25: =(LN(D25)-LN(C25))/B25*10000 -> 0.96485611 | F25: =A26 -> 46832 | G25: =(F25-A25)/360 -> 0.075 | H25: =WORKDAY(A25,-5) -> 46798 | I25: =WORKDAY(F25,-5) -> 46825 | J25: =EXP(INDEX(Bootstrap!$D$39:$D$59,MATCH((($H25-MarketData!$B$4)/360),Bootstrap!$B$39:$B$59,1))+(INDEX(Bootstrap!$D$39:$D$59,MATCH((($H25-MarketData!$B$4)/360),Bootstrap!$B$39:$B$59,1)+1)-INDEX(Bootstrap!$D$39:$D$59,MATCH((($H25-MarketData!$B$4)/360),Bootstrap!$B$39:$B$59,1)))*(((($H25-MarketData!$B$4)/360))-INDEX(Bootstrap!$B$39:$B$59,MATCH((($H25-MarketData!$B$4)/360),Bootstrap!$B$39:$B$59,1)))/(INDEX(Bootstrap!$B$39:$B$59,MATCH((($H25-MarketData!$B$4)/360),Bootstrap!$B$39:$B$59,1)+1)-INDEX(Bootstrap!$B$39:$B$59,MATCH((($H25-MarketData!$B$4)/360),Bootstrap!$B$39:$B$59,1)))) -> 0.93555227 | K25: =EXP(INDEX(Bootstrap!$D$39:$D$59,MATCH((($I25-MarketData!$B$4)/360),Bootstrap!$B$39:$B$59,1))+(INDEX(Bootstrap!$D$39:$D$59,MATCH((($I25-MarketData!$B$4)/360),Bootstrap!$B$39:$B$59,1)+1)-INDEX(Bootstrap!$D$39:$D$59,MATCH((($I25-MarketData!$B$4)/360),Bootstrap!$B$39:$B$59,1)))*(((($I25-MarketData!$B$4)/360))-INDEX(Bootstrap!$B$39:$B$59,MATCH((($I25-MarketData!$B$4)/360),Bootstrap!$B$39:$B$59,1)))/(INDEX(Bootstrap!$B$39:$B$59,MATCH((($I25-MarketData!$B$4)/360),Bootstrap!$B$39:$B$59,1)+1)-INDEX(Bootstrap!$B$39:$B$59,MATCH((($I25-MarketData!$B$4)/360),Bootstrap!$B$39:$B$59,1)))) -> 0.93278679 | L25: =(J25/K25-1)/G25 -> 0.039529913 | M25: =MarketData!$C$71 -> 0.038826478 | N25: =(L25-M25)*10000 -> 7.0343432
A26: =MarketData!$A$72 -> 46832 | B26: =(A26-MarketData!$B$4)/360 -> 1.8194444 | C26: =EXP(INDEX(Bootstrap!$D$39:$D$59,MATCH($B26,Bootstrap!$B$39:$B$59,1))+(INDEX(Bootstrap!$D$39:$D$59,MATCH($B26,Bootstrap!$B$39:$B$59,1)+1)-INDEX(Bootstrap!$D$39:$D$59,MATCH($B26,Bootstrap!$B$39:$B$59,1)))*(($B26)-INDEX(Bootstrap!$B$39:$B$59,MATCH($B26,Bootstrap!$B$39:$B$59,1)))/(INDEX(Bootstrap!$B$39:$B$59,MATCH($B26,Bootstrap!$B$39:$B$59,1)+1)-INDEX(Bootstrap!$B$39:$B$59,MATCH($B26,Bootstrap!$B$39:$B$59,1)))) -> 0.93207869 | D26: =MarketData!$B$72 -> 0.93228031 | E26: =(LN(D26)-LN(C26))/B26*10000 -> 1.1887702 | F26: =A27 -> 46863 | G26: =(F26-A26)/360 -> 0.086111111 | H26: =WORKDAY(A26,-5) -> 46825 | I26: =WORKDAY(F26,-5) -> 46856 | J26: =EXP(INDEX(Bootstrap!$D$39:$D$59,MATCH((($H26-MarketData!$B$4)/360),Bootstrap!$B$39:$B$59,1))+(INDEX(Bootstrap!$D$39:$D$59,MATCH((($H26-MarketData!$B$4)/360),Bootstrap!$B$39:$B$59,1)+1)-INDEX(Bootstrap!$D$39:$D$59,MATCH((($H26-MarketData!$B$4)/360),Bootstrap!$B$39:$B$59,1)))*(((($H26-MarketData!$B$4)/360))-INDEX(Bootstrap!$B$39:$B$59,MATCH((($H26-MarketData!$B$4)/360),Bootstrap!$B$39:$B$59,1)))/(INDEX(Bootstrap!$B$39:$B$59,MATCH((($H26-MarketData!$B$4)/360),Bootstrap!$B$39:$B$59,1)+1)-INDEX(Bootstrap!$B$39:$B$59,MATCH((($H26-MarketData!$B$4)/360),Bootstrap!$B$39:$B$59,1)))) -> 0.93278679 | K26: =EXP(INDEX(Bootstrap!$D$39:$D$59,MATCH((($I26-MarketData!$B$4)/360),Bootstrap!$B$39:$B$59,1))+(INDEX(Bootstrap!$D$39:$D$59,MATCH((($I26-MarketData!$B$4)/360),Bootstrap!$B$39:$B$59,1)+1)-INDEX(Bootstrap!$D$39:$D$59,MATCH((($I26-MarketData!$B$4)/360),Bootstrap!$B$39:$B$59,1)))*(((($I26-MarketData!$B$4)/360))-INDEX(Bootstrap!$B$39:$B$59,MATCH((($I26-MarketData!$B$4)/360),Bootstrap!$B$39:$B$59,1)))/(INDEX(Bootstrap!$B$39:$B$59,MATCH((($I26-MarketData!$B$4)/360),Bootstrap!$B$39:$B$59,1)+1)-INDEX(Bootstrap!$B$39:$B$59,MATCH((($I26-MarketData!$B$4)/360),Bootstrap!$B$39:$B$59,1)))) -> 0.92966529 | L26: =(J26/K26-1)/G26 -> 0.038992284 | M26: =MarketData!$C$72 -> 0.038666567 | N26: =(L26-M26)*10000 -> 3.2571683
A27: =MarketData!$A$73 -> 46863 | B27: =(A27-MarketData!$B$4)/360 -> 1.9055556 | C27: =EXP(INDEX(Bootstrap!$D$39:$D$59,MATCH($B27,Bootstrap!$B$39:$B$59,1))+(INDEX(Bootstrap!$D$39:$D$59,MATCH($B27,Bootstrap!$B$39:$B$59,1)+1)-INDEX(Bootstrap!$D$39:$D$59,MATCH($B27,Bootstrap!$B$39:$B$59,1)))*(($B27)-INDEX(Bootstrap!$B$39:$B$59,MATCH($B27,Bootstrap!$B$39:$B$59,1)))/(INDEX(Bootstrap!$B$39:$B$59,MATCH($B27,Bootstrap!$B$39:$B$59,1)+1)-INDEX(Bootstrap!$B$39:$B$59,MATCH($B27,Bootstrap!$B$39:$B$59,1)))) -> 0.92896255 | D27: =MarketData!$B$73 -> 0.92918873 | E27: =(LN(D27)-LN(C27))/B27*10000 -> 1.2775611 | F27: =A28 -> 46895 | G27: =(F27-A27)/360 -> 0.088888889 | H27: =WORKDAY(A27,-5) -> 46856 | I27: =WORKDAY(F27,-5) -> 46888 | J27: =EXP(INDEX(Bootstrap!$D$39:$D$59,MATCH((($H27-MarketData!$B$4)/360),Bootstrap!$B$39:$B$59,1))+(INDEX(Bootstrap!$D$39:$D$59,MATCH((($H27-MarketData!$B$4)/360),Bootstrap!$B$39:$B$59,1)+1)-INDEX(Bootstrap!$D$39:$D$59,MATCH((($H27-MarketData!$B$4)/360),Bootstrap!$B$39:$B$59,1)))*(((($H27-MarketData!$B$4)/360))-INDEX(Bootstrap!$B$39:$B$59,MATCH((($H27-MarketData!$B$4)/360),Bootstrap!$B$39:$B$59,1)))/(INDEX(Bootstrap!$B$39:$B$59,MATCH((($H27-MarketData!$B$4)/360),Bootstrap!$B$39:$B$59,1)+1)-INDEX(Bootstrap!$B$39:$B$59,MATCH((($H27-MarketData!$B$4)/360),Bootstrap!$B$39:$B$59,1)))) -> 0.92966529 | K27: =EXP(INDEX(Bootstrap!$D$39:$D$59,MATCH((($I27-MarketData!$B$4)/360),Bootstrap!$B$39:$B$59,1))+(INDEX(Bootstrap!$D$39:$D$59,MATCH((($I27-MarketData!$B$4)/360),Bootstrap!$B$39:$B$59,1)+1)-INDEX(Bootstrap!$D$39:$D$59,MATCH((($I27-MarketData!$B$4)/360),Bootstrap!$B$39:$B$59,1)))*(((($I27-MarketData!$B$4)/360))-INDEX(Bootstrap!$B$39:$B$59,MATCH((($I27-MarketData!$B$4)/360),Bootstrap!$B$39:$B$59,1)))/(INDEX(Bootstrap!$B$39:$B$59,MATCH((($I27-MarketData!$B$4)/360),Bootstrap!$B$39:$B$59,1)+1)-INDEX(Bootstrap!$B$39:$B$59,MATCH((($I27-MarketData!$B$4)/360),Bootstrap!$B$39:$B$59,1)))) -> 0.92645713 | L27: =(J27/K27-1)/G27 -> 0.038956714 | M27: =MarketData!$C$73 -> 0.038551188 | N27: =(L27-M27)*10000 -> 4.055255
A28: =MarketData!$A$74 -> 46895 | B28: =(A28-MarketData!$B$4)/360 -> 1.9944444 | C28: =EXP(INDEX(Bootstrap!$D$39:$D$59,MATCH($B28,Bootstrap!$B$39:$B$59,1))+(INDEX(Bootstrap!$D$39:$D$59,MATCH($B28,Bootstrap!$B$39:$B$59,1)+1)-INDEX(Bootstrap!$D$39:$D$59,MATCH($B28,Bootstrap!$B$39:$B$59,1)))*(($B28)-INDEX(Bootstrap!$B$39:$B$59,MATCH($B28,Bootstrap!$B$39:$B$59,1)))/(INDEX(Bootstrap!$B$39:$B$59,MATCH($B28,Bootstrap!$B$39:$B$59,1)+1)-INDEX(Bootstrap!$B$39:$B$59,MATCH($B28,Bootstrap!$B$39:$B$59,1)))) -> 0.92575683 | D28: =MarketData!$B$74 -> 0.92601763 | E28: =(LN(D28)-LN(C28))/B28*10000 -> 1.412315 | F28: =A29 -> 46924 | G28: =(F28-A28)/360 -> 0.080555556 | H28: =WORKDAY(A28,-5) -> 46888 | I28: =WORKDAY(F28,-5) -> 46917 | J28: =EXP(INDEX(Bootstrap!$D$39:$D$59,MATCH((($H28-MarketData!$B$4)/360),Bootstrap!$B$39:$B$59,1))+(INDEX(Bootstrap!$D$39:$D$59,MATCH((($H28-MarketData!$B$4)/360),Bootstrap!$B$39:$B$59,1)+1)-INDEX(Bootstrap!$D$39:$D$59,MATCH((($H28-MarketData!$B$4)/360),Bootstrap!$B$39:$B$59,1)))*(((($H28-MarketData!$B$4)/360))-INDEX(Bootstrap!$B$39:$B$59,MATCH((($H28-MarketData!$B$4)/360),Bootstrap!$B$39:$B$59,1)))/(INDEX(Bootstrap!$B$39:$B$59,MATCH((($H28-MarketData!$B$4)/360),Bootstrap!$B$39:$B$59,1)+1)-INDEX(Bootstrap!$B$39:$B$59,MATCH((($H28-MarketData!$B$4)/360),Bootstrap!$B$39:$B$59,1)))) -> 0.92645713 | K28: =EXP(INDEX(Bootstrap!$D$39:$D$59,MATCH((($I28-MarketData!$B$4)/360),Bootstrap!$B$39:$B$59,1))+(INDEX(Bootstrap!$D$39:$D$59,MATCH((($I28-MarketData!$B$4)/360),Bootstrap!$B$39:$B$59,1)+1)-INDEX(Bootstrap!$D$39:$D$59,MATCH((($I28-MarketData!$B$4)/360),Bootstrap!$B$39:$B$59,1)))*(((($I28-MarketData!$B$4)/360))-INDEX(Bootstrap!$B$39:$B$59,MATCH((($I28-MarketData!$B$4)/360),Bootstrap!$B$39:$B$59,1)))/(INDEX(Bootstrap!$B$39:$B$59,MATCH((($I28-MarketData!$B$4)/360),Bootstrap!$B$39:$B$59,1)+1)-INDEX(Bootstrap!$B$39:$B$59,MATCH((($I28-MarketData!$B$4)/360),Bootstrap!$B$39:$B$59,1)))) -> 0.92355931 | L28: =(J28/K28-1)/G28 -> 0.038950398 | M28: =MarketData!$C$74 -> 0.038434123 | N28: =(L28-M28)*10000 -> 5.1627563
A29: =MarketData!$A$75 -> 46924 | B29: =(A29-MarketData!$B$4)/360 -> 2.075 | C29: =EXP(INDEX(Bootstrap!$D$39:$D$59,MATCH($B29,Bootstrap!$B$39:$B$59,1))+(INDEX(Bootstrap!$D$39:$D$59,MATCH($B29,Bootstrap!$B$39:$B$59,1)+1)-INDEX(Bootstrap!$D$39:$D$59,MATCH($B29,Bootstrap!$B$39:$B$59,1)))*(($B29)-INDEX(Bootstrap!$B$39:$B$59,MATCH($B29,Bootstrap!$B$39:$B$59,1)))/(INDEX(Bootstrap!$B$39:$B$59,MATCH($B29,Bootstrap!$B$39:$B$59,1)+1)-INDEX(Bootstrap!$B$39:$B$59,MATCH($B29,Bootstrap!$B$39:$B$59,1)))) -> 0.92286119 | D29: =MarketData!$B$75 -> 0.92316083 | E29: =(LN(D29)-LN(C29))/B29*10000 -> 1.5645034 | F29: =A30 -> 46954 | G29: =(F29-A29)/360 -> 0.083333333 | H29: =WORKDAY(A29,-5) -> 46917 | I29: =WORKDAY(F29,-5) -> 46947 | J29: =EXP(INDEX(Bootstrap!$D$39:$D$59,MATCH((($H29-MarketData!$B$4)/360),Bootstrap!$B$39:$B$59,1))+(INDEX(Bootstrap!$D$39:$D$59,MATCH((($H29-MarketData!$B$4)/360),Bootstrap!$B$39:$B$59,1)+1)-INDEX(Bootstrap!$D$39:$D$59,MATCH((($H29-MarketData!$B$4)/360),Bootstrap!$B$39:$B$59,1)))*(((($H29-MarketData!$B$4)/360))-INDEX(Bootstrap!$B$39:$B$59,MATCH((($H29-MarketData!$B$4)/360),Bootstrap!$B$39:$B$59,1)))/(INDEX(Bootstrap!$B$39:$B$59,MATCH((($H29-MarketData!$B$4)/360),Bootstrap!$B$39:$B$59,1)+1)-INDEX(Bootstrap!$B$39:$B$59,MATCH((($H29-MarketData!$B$4)/360),Bootstrap!$B$39:$B$59,1)))) -> 0.92355931 | K29: =EXP(INDEX(Bootstrap!$D$39:$D$59,MATCH((($I29-MarketData!$B$4)/360),Bootstrap!$B$39:$B$59,1))+(INDEX(Bootstrap!$D$39:$D$59,MATCH((($I29-MarketData!$B$4)/360),Bootstrap!$B$39:$B$59,1)+1)-INDEX(Bootstrap!$D$39:$D$59,MATCH((($I29-MarketData!$B$4)/360),Bootstrap!$B$39:$B$59,1)))*(((($I29-MarketData!$B$4)/360))-INDEX(Bootstrap!$B$39:$B$59,MATCH((($I29-MarketData!$B$4)/360),Bootstrap!$B$39:$B$59,1)))/(INDEX(Bootstrap!$B$39:$B$59,MATCH((($I29-MarketData!$B$4)/360),Bootstrap!$B$39:$B$59,1)+1)-INDEX(Bootstrap!$B$39:$B$59,MATCH((($I29-MarketData!$B$4)/360),Bootstrap!$B$39:$B$59,1)))) -> 0.92059629 | L29: =(J29/K29-1)/G29 -> 0.038623057 | M29: =MarketData!$C$75 -> 0.038388691 | N29: =(L29-M29)*10000 -> 2.3436585
A30: =MarketData!$A$76 -> 46954 | B30: =(A30-MarketData!$B$4)/360 -> 2.1583333 | C30: =EXP(INDEX(Bootstrap!$D$39:$D$59,MATCH($B30,Bootstrap!$B$39:$B$59,1))+(INDEX(Bootstrap!$D$39:$D$59,MATCH($B30,Bootstrap!$B$39:$B$59,1)+1)-INDEX(Bootstrap!$D$39:$D$59,MATCH($B30,Bootstrap!$B$39:$B$59,1)))*(($B30)-INDEX(Bootstrap!$B$39:$B$59,MATCH($B30,Bootstrap!$B$39:$B$59,1)))/(INDEX(Bootstrap!$B$39:$B$59,MATCH($B30,Bootstrap!$B$39:$B$59,1)+1)-INDEX(Bootstrap!$B$39:$B$59,MATCH($B30,Bootstrap!$B$39:$B$59,1)))) -> 0.91990842 | D30: =MarketData!$B$76 -> 0.92021781 | E30: =(LN(D30)-LN(C30))/B30*10000 -> 1.5579789 | F30: =A31 -> 46986 | G30: =(F30-A30)/360 -> 0.088888889 | H30: =WORKDAY(A30,-5) -> 46947 | I30: =WORKDAY(F30,-5) -> 46979 | J30: =EXP(INDEX(Bootstrap!$D$39:$D$59,MATCH((($H30-MarketData!$B$4)/360),Bootstrap!$B$39:$B$59,1))+(INDEX(Bootstrap!$D$39:$D$59,MATCH((($H30-MarketData!$B$4)/360),Bootstrap!$B$39:$B$59,1)+1)-INDEX(Bootstrap!$D$39:$D$59,MATCH((($H30-MarketData!$B$4)/360),Bootstrap!$B$39:$B$59,1)))*(((($H30-MarketData!$B$4)/360))-INDEX(Bootstrap!$B$39:$B$59,MATCH((($H30-MarketData!$B$4)/360),Bootstrap!$B$39:$B$59,1)))/(INDEX(Bootstrap!$B$39:$B$59,MATCH((($H30-MarketData!$B$4)/360),Bootstrap!$B$39:$B$59,1)+1)-INDEX(Bootstrap!$B$39:$B$59,MATCH((($H30-MarketData!$B$4)/360),Bootstrap!$B$39:$B$59,1)))) -> 0.92059629 | K30: =EXP(INDEX(Bootstrap!$D$39:$D$59,MATCH((($I30-MarketData!$B$4)/360),Bootstrap!$B$39:$B$59,1))+(INDEX(Bootstrap!$D$39:$D$59,MATCH((($I30-MarketData!$B$4)/360),Bootstrap!$B$39:$B$59,1)+1)-INDEX(Bootstrap!$D$39:$D$59,MATCH((($I30-MarketData!$B$4)/360),Bootstrap!$B$39:$B$59,1)))*(((($I30-MarketData!$B$4)/360))-INDEX(Bootstrap!$B$39:$B$59,MATCH((($I30-MarketData!$B$4)/360),Bootstrap!$B$39:$B$59,1)))/(INDEX(Bootstrap!$B$39:$B$59,MATCH((($I30-MarketData!$B$4)/360),Bootstrap!$B$39:$B$59,1)+1)-INDEX(Bootstrap!$B$39:$B$59,MATCH((($I30-MarketData!$B$4)/360),Bootstrap!$B$39:$B$59,1)))) -> 0.91745595 | L30: =(J30/K30-1)/G30 -> 0.038507374 | M30: =MarketData!$C$76 -> 0.038335963 | N30: =(L30-M30)*10000 -> 1.7141105
A31: =MarketData!$A$77 -> 46986 | B31: =(A31-MarketData!$B$4)/360 -> 2.2472222 | C31: =EXP(INDEX(Bootstrap!$D$39:$D$59,MATCH($B31,Bootstrap!$B$39:$B$59,1))+(INDEX(Bootstrap!$D$39:$D$59,MATCH($B31,Bootstrap!$B$39:$B$59,1)+1)-INDEX(Bootstrap!$D$39:$D$59,MATCH($B31,Bootstrap!$B$39:$B$59,1)))*(($B31)-INDEX(Bootstrap!$B$39:$B$59,MATCH($B31,Bootstrap!$B$39:$B$59,1)))/(INDEX(Bootstrap!$B$39:$B$59,MATCH($B31,Bootstrap!$B$39:$B$59,1)+1)-INDEX(Bootstrap!$B$39:$B$59,MATCH($B31,Bootstrap!$B$39:$B$59,1)))) -> 0.91677043 | D31: =MarketData!$B$77 -> 0.91709378 | E31: =(LN(D31)-LN(C31))/B31*10000 -> 1.5692555 | F31: =A32 -> 47016 | G31: =(F31-A31)/360 -> 0.083333333 | H31: =WORKDAY(A31,-5) -> 46979 | I31: =WORKDAY(F31,-5) -> 47009 | J31: =EXP(INDEX(Bootstrap!$D$39:$D$59,MATCH((($H31-MarketData!$B$4)/360),Bootstrap!$B$39:$B$59,1))+(INDEX(Bootstrap!$D$39:$D$59,MATCH((($H31-MarketData!$B$4)/360),Bootstrap!$B$39:$B$59,1)+1)-INDEX(Bootstrap!$D$39:$D$59,MATCH((($H31-MarketData!$B$4)/360),Bootstrap!$B$39:$B$59,1)))*(((($H31-MarketData!$B$4)/360))-INDEX(Bootstrap!$B$39:$B$59,MATCH((($H31-MarketData!$B$4)/360),Bootstrap!$B$39:$B$59,1)))/(INDEX(Bootstrap!$B$39:$B$59,MATCH((($H31-MarketData!$B$4)/360),Bootstrap!$B$39:$B$59,1)+1)-INDEX(Bootstrap!$B$39:$B$59,MATCH((($H31-MarketData!$B$4)/360),Bootstrap!$B$39:$B$59,1)))) -> 0.91745595 | K31: =EXP(INDEX(Bootstrap!$D$39:$D$59,MATCH((($I31-MarketData!$B$4)/360),Bootstrap!$B$39:$B$59,1))+(INDEX(Bootstrap!$D$39:$D$59,MATCH((($I31-MarketData!$B$4)/360),Bootstrap!$B$39:$B$59,1)+1)-INDEX(Bootstrap!$D$39:$D$59,MATCH((($I31-MarketData!$B$4)/360),Bootstrap!$B$39:$B$59,1)))*(((($I31-MarketData!$B$4)/360))-INDEX(Bootstrap!$B$39:$B$59,MATCH((($I31-MarketData!$B$4)/360),Bootstrap!$B$39:$B$59,1)))/(INDEX(Bootstrap!$B$39:$B$59,MATCH((($I31-MarketData!$B$4)/360),Bootstrap!$B$39:$B$59,1)+1)-INDEX(Bootstrap!$B$39:$B$59,MATCH((($I31-MarketData!$B$4)/360),Bootstrap!$B$39:$B$59,1)))) -> 0.91452161 | L31: =(J31/K31-1)/G31 -> 0.03850326 | M31: =MarketData!$C$77 -> 0.038272335 | N31: =(L31-M31)*10000 -> 2.309258
A32: =MarketData!$A$78 -> 47016 | B32: =(A32-MarketData!$B$4)/360 -> 2.3305556 | C32: =EXP(INDEX(Bootstrap!$D$39:$D$59,MATCH($B32,Bootstrap!$B$39:$B$59,1))+(INDEX(Bootstrap!$D$39:$D$59,MATCH($B32,Bootstrap!$B$39:$B$59,1)+1)-INDEX(Bootstrap!$D$39:$D$59,MATCH($B32,Bootstrap!$B$39:$B$59,1)))*(($B32)-INDEX(Bootstrap!$B$39:$B$59,MATCH($B32,Bootstrap!$B$39:$B$59,1)))/(INDEX(Bootstrap!$B$39:$B$59,MATCH($B32,Bootstrap!$B$39:$B$59,1)+1)-INDEX(Bootstrap!$B$39:$B$59,MATCH($B32,Bootstrap!$B$39:$B$59,1)))) -> 0.91383828 | D32: =MarketData!$B$78 -> 0.91417919 | E32: =(LN(D32)-LN(C32))/B32*10000 -> 1.6003867 | F32: =A33 -> 47046 | G32: =(F32-A32)/360 -> 0.083333333 | H32: =WORKDAY(A32,-5) -> 47009 | I32: =WORKDAY(F32,-5) -> 47039 | J32: =EXP(INDEX(Bootstrap!$D$39:$D$59,MATCH((($H32-MarketData!$B$4)/360),Bootstrap!$B$39:$B$59,1))+(INDEX(Bootstrap!$D$39:$D$59,MATCH((($H32-MarketData!$B$4)/360),Bootstrap!$B$39:$B$59,1)+1)-INDEX(Bootstrap!$D$39:$D$59,MATCH((($H32-MarketData!$B$4)/360),Bootstrap!$B$39:$B$59,1)))*(((($H32-MarketData!$B$4)/360))-INDEX(Bootstrap!$B$39:$B$59,MATCH((($H32-MarketData!$B$4)/360),Bootstrap!$B$39:$B$59,1)))/(INDEX(Bootstrap!$B$39:$B$59,MATCH((($H32-MarketData!$B$4)/360),Bootstrap!$B$39:$B$59,1)+1)-INDEX(Bootstrap!$B$39:$B$59,MATCH((($H32-MarketData!$B$4)/360),Bootstrap!$B$39:$B$59,1)))) -> 0.91452161 | K32: =EXP(INDEX(Bootstrap!$D$39:$D$59,MATCH((($I32-MarketData!$B$4)/360),Bootstrap!$B$39:$B$59,1))+(INDEX(Bootstrap!$D$39:$D$59,MATCH((($I32-MarketData!$B$4)/360),Bootstrap!$B$39:$B$59,1)+1)-INDEX(Bootstrap!$D$39:$D$59,MATCH((($I32-MarketData!$B$4)/360),Bootstrap!$B$39:$B$59,1)))*(((($I32-MarketData!$B$4)/360))-INDEX(Bootstrap!$B$39:$B$59,MATCH((($I32-MarketData!$B$4)/360),Bootstrap!$B$39:$B$59,1)))/(INDEX(Bootstrap!$B$39:$B$59,MATCH((($I32-MarketData!$B$4)/360),Bootstrap!$B$39:$B$59,1)+1)-INDEX(Bootstrap!$B$39:$B$59,MATCH((($I32-MarketData!$B$4)/360),Bootstrap!$B$39:$B$59,1)))) -> 0.91161546 | L32: =(J32/K32-1)/G32 -> 0.038254942 | M32: =MarketData!$C$78 -> 0.038215849 | N32: =(L32-M32)*10000 -> 0.390932
A33: =MarketData!$A$79 -> 47046 | B33: =(A33-MarketData!$B$4)/360 -> 2.4138889 | C33: =EXP(INDEX(Bootstrap!$D$39:$D$59,MATCH($B33,Bootstrap!$B$39:$B$59,1))+(INDEX(Bootstrap!$D$39:$D$59,MATCH($B33,Bootstrap!$B$39:$B$59,1)+1)-INDEX(Bootstrap!$D$39:$D$59,MATCH($B33,Bootstrap!$B$39:$B$59,1)))*(($B33)-INDEX(Bootstrap!$B$39:$B$59,MATCH($B33,Bootstrap!$B$39:$B$59,1)))/(INDEX(Bootstrap!$B$39:$B$59,MATCH($B33,Bootstrap!$B$39:$B$59,1)+1)-INDEX(Bootstrap!$B$39:$B$59,MATCH($B33,Bootstrap!$B$39:$B$59,1)))) -> 0.91094002 | D33: =MarketData!$B$79 -> 0.91127779 | E33: =(LN(D33)-LN(C33))/B33*10000 -> 1.535776 | F33: =A34 -> 47077 | G33: =(F33-A33)/360 -> 0.086111111 | H33: =WORKDAY(A33,-5) -> 47039 | I33: =WORKDAY(F33,-5) -> 47070 | J33: =EXP(INDEX(Bootstrap!$D$39:$D$59,MATCH((($H33-MarketData!$B$4)/360),Bootstrap!$B$39:$B$59,1))+(INDEX(Bootstrap!$D$39:$D$59,MATCH((($H33-MarketData!$B$4)/360),Bootstrap!$B$39:$B$59,1)+1)-INDEX(Bootstrap!$D$39:$D$59,MATCH((($H33-MarketData!$B$4)/360),Bootstrap!$B$39:$B$59,1)))*(((($H33-MarketData!$B$4)/360))-INDEX(Bootstrap!$B$39:$B$59,MATCH((($H33-MarketData!$B$4)/360),Bootstrap!$B$39:$B$59,1)))/(INDEX(Bootstrap!$B$39:$B$59,MATCH((($H33-MarketData!$B$4)/360),Bootstrap!$B$39:$B$59,1)+1)-INDEX(Bootstrap!$B$39:$B$59,MATCH((($H33-MarketData!$B$4)/360),Bootstrap!$B$39:$B$59,1)))) -> 0.91161546 | K33: =EXP(INDEX(Bootstrap!$D$39:$D$59,MATCH((($I33-MarketData!$B$4)/360),Bootstrap!$B$39:$B$59,1))+(INDEX(Bootstrap!$D$39:$D$59,MATCH((($I33-MarketData!$B$4)/360),Bootstrap!$B$39:$B$59,1)+1)-INDEX(Bootstrap!$D$39:$D$59,MATCH((($I33-MarketData!$B$4)/360),Bootstrap!$B$39:$B$59,1)))*(((($I33-MarketData!$B$4)/360))-INDEX(Bootstrap!$B$39:$B$59,MATCH((($I33-MarketData!$B$4)/360),Bootstrap!$B$39:$B$59,1)))/(INDEX(Bootstrap!$B$39:$B$59,MATCH((($I33-MarketData!$B$4)/360),Bootstrap!$B$39:$B$59,1)+1)-INDEX(Bootstrap!$B$39:$B$59,MATCH((($I33-MarketData!$B$4)/360),Bootstrap!$B$39:$B$59,1)))) -> 0.90862803 | L33: =(J33/K33-1)/G33 -> 0.038181391 | M33: =MarketData!$C$79 -> 0.038187484 | N33: =(L33-M33)*10000 -> -0.060929269
A34: =MarketData!$A$80 -> 47077 | B34: =(A34-MarketData!$B$4)/360 -> 2.5 | C34: =EXP(INDEX(Bootstrap!$D$39:$D$59,MATCH($B34,Bootstrap!$B$39:$B$59,1))+(INDEX(Bootstrap!$D$39:$D$59,MATCH($B34,Bootstrap!$B$39:$B$59,1)+1)-INDEX(Bootstrap!$D$39:$D$59,MATCH($B34,Bootstrap!$B$39:$B$59,1)))*(($B34)-INDEX(Bootstrap!$B$39:$B$59,MATCH($B34,Bootstrap!$B$39:$B$59,1)))/(INDEX(Bootstrap!$B$39:$B$59,MATCH($B34,Bootstrap!$B$39:$B$59,1)+1)-INDEX(Bootstrap!$B$39:$B$59,MATCH($B34,Bootstrap!$B$39:$B$59,1)))) -> 0.90795481 | D34: =MarketData!$B$80 -> 0.90829148 | E34: =(LN(D34)-LN(C34))/B34*10000 -> 1.4829114 | F34: =A35 -> 47107 | G34: =(F34-A34)/360 -> 0.083333333 | H34: =WORKDAY(A34,-5) -> 47070 | I34: =WORKDAY(F34,-5) -> 47100 | J34: =EXP(INDEX(Bootstrap!$D$39:$D$59,MATCH((($H34-MarketData!$B$4)/360),Bootstrap!$B$39:$B$59,1))+(INDEX(Bootstrap!$D$39:$D$59,MATCH((($H34-MarketData!$B$4)/360),Bootstrap!$B$39:$B$59,1)+1)-INDEX(Bootstrap!$D$39:$D$59,MATCH((($H34-MarketData!$B$4)/360),Bootstrap!$B$39:$B$59,1)))*(((($H34-MarketData!$B$4)/360))-INDEX(Bootstrap!$B$39:$B$59,MATCH((($H34-MarketData!$B$4)/360),Bootstrap!$B$39:$B$59,1)))/(INDEX(Bootstrap!$B$39:$B$59,MATCH((($H34-MarketData!$B$4)/360),Bootstrap!$B$39:$B$59,1)+1)-INDEX(Bootstrap!$B$39:$B$59,MATCH((($H34-MarketData!$B$4)/360),Bootstrap!$B$39:$B$59,1)))) -> 0.90862803 | K34: =EXP(INDEX(Bootstrap!$D$39:$D$59,MATCH((($I34-MarketData!$B$4)/360),Bootstrap!$B$39:$B$59,1))+(INDEX(Bootstrap!$D$39:$D$59,MATCH((($I34-MarketData!$B$4)/360),Bootstrap!$B$39:$B$59,1)+1)-INDEX(Bootstrap!$D$39:$D$59,MATCH((($I34-MarketData!$B$4)/360),Bootstrap!$B$39:$B$59,1)))*(((($I34-MarketData!$B$4)/360))-INDEX(Bootstrap!$B$39:$B$59,MATCH((($I34-MarketData!$B$4)/360),Bootstrap!$B$39:$B$59,1)))/(INDEX(Bootstrap!$B$39:$B$59,MATCH((($I34-MarketData!$B$4)/360),Bootstrap!$B$39:$B$59,1)+1)-INDEX(Bootstrap!$B$39:$B$59,MATCH((($I34-MarketData!$B$4)/360),Bootstrap!$B$39:$B$59,1)))) -> 0.9057463 | L34: =(J34/K34-1)/G34 -> 0.038179368 | M34: =MarketData!$C$80 -> 0.038158465 | N34: =(L34-M34)*10000 -> 0.20902712
A35: =MarketData!$A$81 -> 47107 | B35: =(A35-MarketData!$B$4)/360 -> 2.5833333 | C35: =EXP(INDEX(Bootstrap!$D$39:$D$59,MATCH($B35,Bootstrap!$B$39:$B$59,1))+(INDEX(Bootstrap!$D$39:$D$59,MATCH($B35,Bootstrap!$B$39:$B$59,1)+1)-INDEX(Bootstrap!$D$39:$D$59,MATCH($B35,Bootstrap!$B$39:$B$59,1)))*(($B35)-INDEX(Bootstrap!$B$39:$B$59,MATCH($B35,Bootstrap!$B$39:$B$59,1)))/(INDEX(Bootstrap!$B$39:$B$59,MATCH($B35,Bootstrap!$B$39:$B$59,1)+1)-INDEX(Bootstrap!$B$39:$B$59,MATCH($B35,Bootstrap!$B$39:$B$59,1)))) -> 0.90507521 | D35: =MarketData!$B$81 -> 0.90541285 | E35: =(LN(D35)-LN(C35))/B35*10000 -> 1.4437918 | F35: =A36 -> 47140 | G35: =(F35-A35)/360 -> 0.091666667 | H35: =WORKDAY(A35,-5) -> 47100 | I35: =WORKDAY(F35,-5) -> 47133 | J35: =EXP(INDEX(Bootstrap!$D$39:$D$59,MATCH((($H35-MarketData!$B$4)/360),Bootstrap!$B$39:$B$59,1))+(INDEX(Bootstrap!$D$39:$D$59,MATCH((($H35-MarketData!$B$4)/360),Bootstrap!$B$39:$B$59,1)+1)-INDEX(Bootstrap!$D$39:$D$59,MATCH((($H35-MarketData!$B$4)/360),Bootstrap!$B$39:$B$59,1)))*(((($H35-MarketData!$B$4)/360))-INDEX(Bootstrap!$B$39:$B$59,MATCH((($H35-MarketData!$B$4)/360),Bootstrap!$B$39:$B$59,1)))/(INDEX(Bootstrap!$B$39:$B$59,MATCH((($H35-MarketData!$B$4)/360),Bootstrap!$B$39:$B$59,1)+1)-INDEX(Bootstrap!$B$39:$B$59,MATCH((($H35-MarketData!$B$4)/360),Bootstrap!$B$39:$B$59,1)))) -> 0.9057463 | K35: =EXP(INDEX(Bootstrap!$D$39:$D$59,MATCH((($I35-MarketData!$B$4)/360),Bootstrap!$B$39:$B$59,1))+(INDEX(Bootstrap!$D$39:$D$59,MATCH((($I35-MarketData!$B$4)/360),Bootstrap!$B$39:$B$59,1)+1)-INDEX(Bootstrap!$D$39:$D$59,MATCH((($I35-MarketData!$B$4)/360),Bootstrap!$B$39:$B$59,1)))*(((($I35-MarketData!$B$4)/360))-INDEX(Bootstrap!$B$39:$B$59,MATCH((($I35-MarketData!$B$4)/360),Bootstrap!$B$39:$B$59,1)))/(INDEX(Bootstrap!$B$39:$B$59,MATCH((($I35-MarketData!$B$4)/360),Bootstrap!$B$39:$B$59,1)+1)-INDEX(Bootstrap!$B$39:$B$59,MATCH((($I35-MarketData!$B$4)/360),Bootstrap!$B$39:$B$59,1)))) -> 0.90258875 | L35: =(J35/K35-1)/G35 -> 0.03816351 | M35: =MarketData!$C$81 -> 0.03816104 | N35: =(L35-M35)*10000 -> 0.0247083
A36: =MarketData!$A$82 -> 47140 | B36: =(A36-MarketData!$B$4)/360 -> 2.675 | C36: =EXP(INDEX(Bootstrap!$D$39:$D$59,MATCH($B36,Bootstrap!$B$39:$B$59,1))+(INDEX(Bootstrap!$D$39:$D$59,MATCH($B36,Bootstrap!$B$39:$B$59,1)+1)-INDEX(Bootstrap!$D$39:$D$59,MATCH($B36,Bootstrap!$B$39:$B$59,1)))*(($B36)-INDEX(Bootstrap!$B$39:$B$59,MATCH($B36,Bootstrap!$B$39:$B$59,1)))/(INDEX(Bootstrap!$B$39:$B$59,MATCH($B36,Bootstrap!$B$39:$B$59,1)+1)-INDEX(Bootstrap!$B$39:$B$59,MATCH($B36,Bootstrap!$B$39:$B$59,1)))) -> 0.90192049 | D36: =MarketData!$B$82 -> 0.90225624 | E36: =(LN(D36)-LN(C36))/B36*10000 -> 1.3913616 | F36: =A37 -> 47169 | G36: =(F36-A36)/360 -> 0.080555556 | H36: =WORKDAY(A36,-5) -> 47133 | I36: =WORKDAY(F36,-5) -> 47162 | J36: =EXP(INDEX(Bootstrap!$D$39:$D$59,MATCH((($H36-MarketData!$B$4)/360),Bootstrap!$B$39:$B$59,1))+(INDEX(Bootstrap!$D$39:$D$59,MATCH((($H36-MarketData!$B$4)/360),Bootstrap!$B$39:$B$59,1)+1)-INDEX(Bootstrap!$D$39:$D$59,MATCH((($H36-MarketData!$B$4)/360),Bootstrap!$B$39:$B$59,1)))*(((($H36-MarketData!$B$4)/360))-INDEX(Bootstrap!$B$39:$B$59,MATCH((($H36-MarketData!$B$4)/360),Bootstrap!$B$39:$B$59,1)))/(INDEX(Bootstrap!$B$39:$B$59,MATCH((($H36-MarketData!$B$4)/360),Bootstrap!$B$39:$B$59,1)+1)-INDEX(Bootstrap!$B$39:$B$59,MATCH((($H36-MarketData!$B$4)/360),Bootstrap!$B$39:$B$59,1)))) -> 0.90258875 | K36: =EXP(INDEX(Bootstrap!$D$39:$D$59,MATCH((($I36-MarketData!$B$4)/360),Bootstrap!$B$39:$B$59,1))+(INDEX(Bootstrap!$D$39:$D$59,MATCH((($I36-MarketData!$B$4)/360),Bootstrap!$B$39:$B$59,1)+1)-INDEX(Bootstrap!$D$39:$D$59,MATCH((($I36-MarketData!$B$4)/360),Bootstrap!$B$39:$B$59,1)))*(((($I36-MarketData!$B$4)/360))-INDEX(Bootstrap!$B$39:$B$59,MATCH((($I36-MarketData!$B$4)/360),Bootstrap!$B$39:$B$59,1)))/(INDEX(Bootstrap!$B$39:$B$59,MATCH((($I36-MarketData!$B$4)/360),Bootstrap!$B$39:$B$59,1)+1)-INDEX(Bootstrap!$B$39:$B$59,MATCH((($I36-MarketData!$B$4)/360),Bootstrap!$B$39:$B$59,1)))) -> 0.89982346 | L36: =(J36/K36-1)/G36 -> 0.038149529 | M36: =MarketData!$C$82 -> 0.038152549 | N36: =(L36-M36)*10000 -> -0.030202579
A37: =MarketData!$A$83 -> 47169 | B37: =(A37-MarketData!$B$4)/360 -> 2.7555556 | C37: =EXP(INDEX(Bootstrap!$D$39:$D$59,MATCH($B37,Bootstrap!$B$39:$B$59,1))+(INDEX(Bootstrap!$D$39:$D$59,MATCH($B37,Bootstrap!$B$39:$B$59,1)+1)-INDEX(Bootstrap!$D$39:$D$59,MATCH($B37,Bootstrap!$B$39:$B$59,1)))*(($B37)-INDEX(Bootstrap!$B$39:$B$59,MATCH($B37,Bootstrap!$B$39:$B$59,1)))/(INDEX(Bootstrap!$B$39:$B$59,MATCH($B37,Bootstrap!$B$39:$B$59,1)+1)-INDEX(Bootstrap!$B$39:$B$59,MATCH($B37,Bootstrap!$B$39:$B$59,1)))) -> 0.89915724 | D37: =MarketData!$B$83 -> 0.89949185 | E37: =(LN(D37)-LN(C37))/B37*10000 -> 1.3502694 | F37: =A38 -> 47197 | G37: =(F37-A37)/360 -> 0.077777778 | H37: =WORKDAY(A37,-5) -> 47162 | I37: =WORKDAY(F37,-5) -> 47190 | J37: =EXP(INDEX(Bootstrap!$D$39:$D$59,MATCH((($H37-MarketData!$B$4)/360),Bootstrap!$B$39:$B$59,1))+(INDEX(Bootstrap!$D$39:$D$59,MATCH((($H37-MarketData!$B$4)/360),Bootstrap!$B$39:$B$59,1)+1)-INDEX(Bootstrap!$D$39:$D$59,MATCH((($H37-MarketData!$B$4)/360),Bootstrap!$B$39:$B$59,1)))*(((($H37-MarketData!$B$4)/360))-INDEX(Bootstrap!$B$39:$B$59,MATCH((($H37-MarketData!$B$4)/360),Bootstrap!$B$39:$B$59,1)))/(INDEX(Bootstrap!$B$39:$B$59,MATCH((($H37-MarketData!$B$4)/360),Bootstrap!$B$39:$B$59,1)+1)-INDEX(Bootstrap!$B$39:$B$59,MATCH((($H37-MarketData!$B$4)/360),Bootstrap!$B$39:$B$59,1)))) -> 0.89982346 | K37: =EXP(INDEX(Bootstrap!$D$39:$D$59,MATCH((($I37-MarketData!$B$4)/360),Bootstrap!$B$39:$B$59,1))+(INDEX(Bootstrap!$D$39:$D$59,MATCH((($I37-MarketData!$B$4)/360),Bootstrap!$B$39:$B$59,1)+1)-INDEX(Bootstrap!$D$39:$D$59,MATCH((($I37-MarketData!$B$4)/360),Bootstrap!$B$39:$B$59,1)))*(((($I37-MarketData!$B$4)/360))-INDEX(Bootstrap!$B$39:$B$59,MATCH((($I37-MarketData!$B$4)/360),Bootstrap!$B$39:$B$59,1)))/(INDEX(Bootstrap!$B$39:$B$59,MATCH((($I37-MarketData!$B$4)/360),Bootstrap!$B$39:$B$59,1)+1)-INDEX(Bootstrap!$B$39:$B$59,MATCH((($I37-MarketData!$B$4)/360),Bootstrap!$B$39:$B$59,1)))) -> 0.89716155 | L37: =(J37/K37-1)/G37 -> 0.03814751 | M37: =MarketData!$C$83 -> 0.038143814 | N37: =(L37-M37)*10000 -> 0.036961106
A38: =MarketData!$A$84 -> 47197 | B38: =(A38-MarketData!$B$4)/360 -> 2.8333333 | C38: =EXP(INDEX(Bootstrap!$D$39:$D$59,MATCH($B38,Bootstrap!$B$39:$B$59,1))+(INDEX(Bootstrap!$D$39:$D$59,MATCH($B38,Bootstrap!$B$39:$B$59,1)+1)-INDEX(Bootstrap!$D$39:$D$59,MATCH($B38,Bootstrap!$B$39:$B$59,1)))*(($B38)-INDEX(Bootstrap!$B$39:$B$59,MATCH($B38,Bootstrap!$B$39:$B$59,1)))/(INDEX(Bootstrap!$B$39:$B$59,MATCH($B38,Bootstrap!$B$39:$B$59,1)+1)-INDEX(Bootstrap!$B$39:$B$59,MATCH($B38,Bootstrap!$B$39:$B$59,1)))) -> 0.89649731 | D38: =MarketData!$B$84 -> 0.89683129 | E38: =(LN(D38)-LN(C38))/B38*10000 -> 1.3146237 | F38: =A39 -> 47228 | G38: =(F38-A38)/360 -> 0.086111111 | H38: =WORKDAY(A38,-5) -> 47190 | I38: =WORKDAY(F38,-5) -> 47221 | J38: =EXP(INDEX(Bootstrap!$D$39:$D$59,MATCH((($H38-MarketData!$B$4)/360),Bootstrap!$B$39:$B$59,1))+(INDEX(Bootstrap!$D$39:$D$59,MATCH((($H38-MarketData!$B$4)/360),Bootstrap!$B$39:$B$59,1)+1)-INDEX(Bootstrap!$D$39:$D$59,MATCH((($H38-MarketData!$B$4)/360),Bootstrap!$B$39:$B$59,1)))*(((($H38-MarketData!$B$4)/360))-INDEX(Bootstrap!$B$39:$B$59,MATCH((($H38-MarketData!$B$4)/360),Bootstrap!$B$39:$B$59,1)))/(INDEX(Bootstrap!$B$39:$B$59,MATCH((($H38-MarketData!$B$4)/360),Bootstrap!$B$39:$B$59,1)+1)-INDEX(Bootstrap!$B$39:$B$59,MATCH((($H38-MarketData!$B$4)/360),Bootstrap!$B$39:$B$59,1)))) -> 0.89716155 | K38: =EXP(INDEX(Bootstrap!$D$39:$D$59,MATCH((($I38-MarketData!$B$4)/360),Bootstrap!$B$39:$B$59,1))+(INDEX(Bootstrap!$D$39:$D$59,MATCH((($I38-MarketData!$B$4)/360),Bootstrap!$B$39:$B$59,1)+1)-INDEX(Bootstrap!$D$39:$D$59,MATCH((($I38-MarketData!$B$4)/360),Bootstrap!$B$39:$B$59,1)))*(((($I38-MarketData!$B$4)/360))-INDEX(Bootstrap!$B$39:$B$59,MATCH((($I38-MarketData!$B$4)/360),Bootstrap!$B$39:$B$59,1)))/(INDEX(Bootstrap!$B$39:$B$59,MATCH((($I38-MarketData!$B$4)/360),Bootstrap!$B$39:$B$59,1)+1)-INDEX(Bootstrap!$B$39:$B$59,MATCH((($I38-MarketData!$B$4)/360),Bootstrap!$B$39:$B$59,1)))) -> 0.89422442 | L38: =(J38/K38-1)/G38 -> 0.038143246 | M38: =MarketData!$C$84 -> 0.038131911 | N38: =(L38-M38)*10000 -> 0.11334956
A39: =MarketData!$A$85 -> 47228 | B39: =(A39-MarketData!$B$4)/360 -> 2.9194444 | C39: =EXP(INDEX(Bootstrap!$D$39:$D$59,MATCH($B39,Bootstrap!$B$39:$B$59,1))+(INDEX(Bootstrap!$D$39:$D$59,MATCH($B39,Bootstrap!$B$39:$B$59,1)+1)-INDEX(Bootstrap!$D$39:$D$59,MATCH($B39,Bootstrap!$B$39:$B$59,1)))*(($B39)-INDEX(Bootstrap!$B$39:$B$59,MATCH($B39,Bootstrap!$B$39:$B$59,1)))/(INDEX(Bootstrap!$B$39:$B$59,MATCH($B39,Bootstrap!$B$39:$B$59,1)+1)-INDEX(Bootstrap!$B$39:$B$59,MATCH($B39,Bootstrap!$B$39:$B$59,1)))) -> 0.89356259 | D39: =MarketData!$B$85 -> 0.8938963 | E39: =(LN(D39)-LN(C39))/B39*10000 -> 1.2789792 | F39: =A40 -> 47259 | G39: =(F39-A39)/360 -> 0.086111111 | H39: =WORKDAY(A39,-5) -> 47221 | I39: =WORKDAY(F39,-5) -> 47252 | J39: =EXP(INDEX(Bootstrap!$D$39:$D$59,MATCH((($H39-MarketData!$B$4)/360),Bootstrap!$B$39:$B$59,1))+(INDEX(Bootstrap!$D$39:$D$59,MATCH((($H39-MarketData!$B$4)/360),Bootstrap!$B$39:$B$59,1)+1)-INDEX(Bootstrap!$D$39:$D$59,MATCH((($H39-MarketData!$B$4)/360),Bootstrap!$B$39:$B$59,1)))*(((($H39-MarketData!$B$4)/360))-INDEX(Bootstrap!$B$39:$B$59,MATCH((($H39-MarketData!$B$4)/360),Bootstrap!$B$39:$B$59,1)))/(INDEX(Bootstrap!$B$39:$B$59,MATCH((($H39-MarketData!$B$4)/360),Bootstrap!$B$39:$B$59,1)+1)-INDEX(Bootstrap!$B$39:$B$59,MATCH((($H39-MarketData!$B$4)/360),Bootstrap!$B$39:$B$59,1)))) -> 0.89422442 | K39: =EXP(INDEX(Bootstrap!$D$39:$D$59,MATCH((($I39-MarketData!$B$4)/360),Bootstrap!$B$39:$B$59,1))+(INDEX(Bootstrap!$D$39:$D$59,MATCH((($I39-MarketData!$B$4)/360),Bootstrap!$B$39:$B$59,1)+1)-INDEX(Bootstrap!$D$39:$D$59,MATCH((($I39-MarketData!$B$4)/360),Bootstrap!$B$39:$B$59,1)))*(((($I39-MarketData!$B$4)/360))-INDEX(Bootstrap!$B$39:$B$59,MATCH((($I39-MarketData!$B$4)/360),Bootstrap!$B$39:$B$59,1)))/(INDEX(Bootstrap!$B$39:$B$59,MATCH((($I39-MarketData!$B$4)/360),Bootstrap!$B$39:$B$59,1)+1)-INDEX(Bootstrap!$B$39:$B$59,MATCH((($I39-MarketData!$B$4)/360),Bootstrap!$B$39:$B$59,1)))) -> 0.89129718 | L39: =(J39/K39-1)/G39 -> 0.038139656 | M39: =MarketData!$C$85 -> 0.038135694 | N39: =(L39-M39)*10000 -> 0.03962814
A40: =MarketData!$A$86 -> 47259 | B40: =(A40-MarketData!$B$4)/360 -> 3.0055556 | C40: =EXP(INDEX(Bootstrap!$D$39:$D$59,MATCH($B40,Bootstrap!$B$39:$B$59,1))+(INDEX(Bootstrap!$D$39:$D$59,MATCH($B40,Bootstrap!$B$39:$B$59,1)+1)-INDEX(Bootstrap!$D$39:$D$59,MATCH($B40,Bootstrap!$B$39:$B$59,1)))*(($B40)-INDEX(Bootstrap!$B$39:$B$59,MATCH($B40,Bootstrap!$B$39:$B$59,1)))/(INDEX(Bootstrap!$B$39:$B$59,MATCH($B40,Bootstrap!$B$39:$B$59,1)+1)-INDEX(Bootstrap!$B$39:$B$59,MATCH($B40,Bootstrap!$B$39:$B$59,1)))) -> 0.89063752 | D40: =MarketData!$B$86 -> 0.8909703 | E40: =(LN(D40)-LN(C40))/B40*10000 -> 1.2429483 | F40: =A41 -> 47289 | G40: =(F40-A40)/360 -> 0.083333333 | H40: =WORKDAY(A40,-5) -> 47252 | I40: =WORKDAY(F40,-5) -> 47282 | J40: =EXP(INDEX(Bootstrap!$D$39:$D$59,MATCH((($H40-MarketData!$B$4)/360),Bootstrap!$B$39:$B$59,1))+(INDEX(Bootstrap!$D$39:$D$59,MATCH((($H40-MarketData!$B$4)/360),Bootstrap!$B$39:$B$59,1)+1)-INDEX(Bootstrap!$D$39:$D$59,MATCH((($H40-MarketData!$B$4)/360),Bootstrap!$B$39:$B$59,1)))*(((($H40-MarketData!$B$4)/360))-INDEX(Bootstrap!$B$39:$B$59,MATCH((($H40-MarketData!$B$4)/360),Bootstrap!$B$39:$B$59,1)))/(INDEX(Bootstrap!$B$39:$B$59,MATCH((($H40-MarketData!$B$4)/360),Bootstrap!$B$39:$B$59,1)+1)-INDEX(Bootstrap!$B$39:$B$59,MATCH((($H40-MarketData!$B$4)/360),Bootstrap!$B$39:$B$59,1)))) -> 0.89129718 | K40: =EXP(INDEX(Bootstrap!$D$39:$D$59,MATCH((($I40-MarketData!$B$4)/360),Bootstrap!$B$39:$B$59,1))+(INDEX(Bootstrap!$D$39:$D$59,MATCH((($I40-MarketData!$B$4)/360),Bootstrap!$B$39:$B$59,1)+1)-INDEX(Bootstrap!$D$39:$D$59,MATCH((($I40-MarketData!$B$4)/360),Bootstrap!$B$39:$B$59,1)))*(((($I40-MarketData!$B$4)/360))-INDEX(Bootstrap!$B$39:$B$59,MATCH((($I40-MarketData!$B$4)/360),Bootstrap!$B$39:$B$59,1)))/(INDEX(Bootstrap!$B$39:$B$59,MATCH((($I40-MarketData!$B$4)/360),Bootstrap!$B$39:$B$59,1)+1)-INDEX(Bootstrap!$B$39:$B$59,MATCH((($I40-MarketData!$B$4)/360),Bootstrap!$B$39:$B$59,1)))) -> 0.88847349 | L40: =(J40/K40-1)/G40 -> 0.038137638 | M40: =MarketData!$C$86 -> 0.038140788 | N40: =(L40-M40)*10000 -> -0.031491309
A41: =MarketData!$A$87 -> 47289 | B41: =(A41-MarketData!$B$4)/360 -> 3.0888889 | C41: =EXP(INDEX(Bootstrap!$D$39:$D$59,MATCH($B41,Bootstrap!$B$39:$B$59,1))+(INDEX(Bootstrap!$D$39:$D$59,MATCH($B41,Bootstrap!$B$39:$B$59,1)+1)-INDEX(Bootstrap!$D$39:$D$59,MATCH($B41,Bootstrap!$B$39:$B$59,1)))*(($B41)-INDEX(Bootstrap!$B$39:$B$59,MATCH($B41,Bootstrap!$B$39:$B$59,1)))/(INDEX(Bootstrap!$B$39:$B$59,MATCH($B41,Bootstrap!$B$39:$B$59,1)+1)-INDEX(Bootstrap!$B$39:$B$59,MATCH($B41,Bootstrap!$B$39:$B$59,1)))) -> 0.88781592 | D41: =MarketData!$B$87 -> 0.88814722 | E41: =(LN(D41)-LN(C41))/B41*10000 -> 1.2078607 | F41: =A42 -> 47319 | G41: =(F41-A41)/360 -> 0.083333333 | H41: =WORKDAY(A41,-5) -> 47282 | I41: =WORKDAY(F41,-5) -> 47312 | J41: =EXP(INDEX(Bootstrap!$D$39:$D$59,MATCH((($H41-MarketData!$B$4)/360),Bootstrap!$B$39:$B$59,1))+(INDEX(Bootstrap!$D$39:$D$59,MATCH((($H41-MarketData!$B$4)/360),Bootstrap!$B$39:$B$59,1)+1)-INDEX(Bootstrap!$D$39:$D$59,MATCH((($H41-MarketData!$B$4)/360),Bootstrap!$B$39:$B$59,1)))*(((($H41-MarketData!$B$4)/360))-INDEX(Bootstrap!$B$39:$B$59,MATCH((($H41-MarketData!$B$4)/360),Bootstrap!$B$39:$B$59,1)))/(INDEX(Bootstrap!$B$39:$B$59,MATCH((($H41-MarketData!$B$4)/360),Bootstrap!$B$39:$B$59,1)+1)-INDEX(Bootstrap!$B$39:$B$59,MATCH((($H41-MarketData!$B$4)/360),Bootstrap!$B$39:$B$59,1)))) -> 0.88847349 | K41: =EXP(INDEX(Bootstrap!$D$39:$D$59,MATCH((($I41-MarketData!$B$4)/360),Bootstrap!$B$39:$B$59,1))+(INDEX(Bootstrap!$D$39:$D$59,MATCH((($I41-MarketData!$B$4)/360),Bootstrap!$B$39:$B$59,1)+1)-INDEX(Bootstrap!$D$39:$D$59,MATCH((($I41-MarketData!$B$4)/360),Bootstrap!$B$39:$B$59,1)))*(((($I41-MarketData!$B$4)/360))-INDEX(Bootstrap!$B$39:$B$59,MATCH((($I41-MarketData!$B$4)/360),Bootstrap!$B$39:$B$59,1)))/(INDEX(Bootstrap!$B$39:$B$59,MATCH((($I41-MarketData!$B$4)/360),Bootstrap!$B$39:$B$59,1)+1)-INDEX(Bootstrap!$B$39:$B$59,MATCH((($I41-MarketData!$B$4)/360),Bootstrap!$B$39:$B$59,1)))) -> 0.88567646 | L41: =(J41/K41-1)/G41 -> 0.037896789 | M41: =MarketData!$C$87 -> 0.038032271 | N41: =(L41-M41)*10000 -> -1.354819
A42: =MarketData!$A$88 -> 47319 | B42: =(A42-MarketData!$B$4)/360 -> 3.1722222 | C42: =EXP(INDEX(Bootstrap!$D$39:$D$59,MATCH($B42,Bootstrap!$B$39:$B$59,1))+(INDEX(Bootstrap!$D$39:$D$59,MATCH($B42,Bootstrap!$B$39:$B$59,1)+1)-INDEX(Bootstrap!$D$39:$D$59,MATCH($B42,Bootstrap!$B$39:$B$59,1)))*(($B42)-INDEX(Bootstrap!$B$39:$B$59,MATCH($B42,Bootstrap!$B$39:$B$59,1)))/(INDEX(Bootstrap!$B$39:$B$59,MATCH($B42,Bootstrap!$B$39:$B$59,1)+1)-INDEX(Bootstrap!$B$39:$B$59,MATCH($B42,Bootstrap!$B$39:$B$59,1)))) -> 0.88502635 | D42: =MarketData!$B$88 -> 0.88534345 | E42: =(LN(D42)-LN(C42))/B42*10000 -> 1.129285 | F42: =A43 -> 47350 | G42: =(F42-A42)/360 -> 0.086111111 | H42: =WORKDAY(A42,-5) -> 47312 | I42: =WORKDAY(F42,-5) -> 47343 | J42: =EXP(INDEX(Bootstrap!$D$39:$D$59,MATCH((($H42-MarketData!$B$4)/360),Bootstrap!$B$39:$B$59,1))+(INDEX(Bootstrap!$D$39:$D$59,MATCH((($H42-MarketData!$B$4)/360),Bootstrap!$B$39:$B$59,1)+1)-INDEX(Bootstrap!$D$39:$D$59,MATCH((($H42-MarketData!$B$4)/360),Bootstrap!$B$39:$B$59,1)))*(((($H42-MarketData!$B$4)/360))-INDEX(Bootstrap!$B$39:$B$59,MATCH((($H42-MarketData!$B$4)/360),Bootstrap!$B$39:$B$59,1)))/(INDEX(Bootstrap!$B$39:$B$59,MATCH((($H42-MarketData!$B$4)/360),Bootstrap!$B$39:$B$59,1)+1)-INDEX(Bootstrap!$B$39:$B$59,MATCH((($H42-MarketData!$B$4)/360),Bootstrap!$B$39:$B$59,1)))) -> 0.88567646 | K42: =EXP(INDEX(Bootstrap!$D$39:$D$59,MATCH((($I42-MarketData!$B$4)/360),Bootstrap!$B$39:$B$59,1))+(INDEX(Bootstrap!$D$39:$D$59,MATCH((($I42-MarketData!$B$4)/360),Bootstrap!$B$39:$B$59,1)+1)-INDEX(Bootstrap!$D$39:$D$59,MATCH((($I42-MarketData!$B$4)/360),Bootstrap!$B$39:$B$59,1)))*(((($I42-MarketData!$B$4)/360))-INDEX(Bootstrap!$B$39:$B$59,MATCH((($I42-MarketData!$B$4)/360),Bootstrap!$B$39:$B$59,1)))/(INDEX(Bootstrap!$B$39:$B$59,MATCH((($I42-MarketData!$B$4)/360),Bootstrap!$B$39:$B$59,1)+1)-INDEX(Bootstrap!$B$39:$B$59,MATCH((($I42-MarketData!$B$4)/360),Bootstrap!$B$39:$B$59,1)))) -> 0.88280101 | L42: =(J42/K42-1)/G42 -> 0.037825473 | M42: =MarketData!$C$88 -> 0.038032518 | N42: =(L42-M42)*10000 -> -2.0704428
A43: =MarketData!$A$89 -> 47350 | B43: =(A43-MarketData!$B$4)/360 -> 3.2583333 | C43: =EXP(INDEX(Bootstrap!$D$39:$D$59,MATCH($B43,Bootstrap!$B$39:$B$59,1))+(INDEX(Bootstrap!$D$39:$D$59,MATCH($B43,Bootstrap!$B$39:$B$59,1)+1)-INDEX(Bootstrap!$D$39:$D$59,MATCH($B43,Bootstrap!$B$39:$B$59,1)))*(($B43)-INDEX(Bootstrap!$B$39:$B$59,MATCH($B43,Bootstrap!$B$39:$B$59,1)))/(INDEX(Bootstrap!$B$39:$B$59,MATCH($B43,Bootstrap!$B$39:$B$59,1)+1)-INDEX(Bootstrap!$B$39:$B$59,MATCH($B43,Bootstrap!$B$39:$B$59,1)))) -> 0.88215301 | D43: =MarketData!$B$89 -> 0.88245264 | E43: =(LN(D43)-LN(C43))/B43*10000 -> 1.0422459 | F43: =A44 -> 47381 | G43: =(F43-A43)/360 -> 0.086111111 | H43: =WORKDAY(A43,-5) -> 47343 | I43: =WORKDAY(F43,-5) -> 47374 | J43: =EXP(INDEX(Bootstrap!$D$39:$D$59,MATCH((($H43-MarketData!$B$4)/360),Bootstrap!$B$39:$B$59,1))+(INDEX(Bootstrap!$D$39:$D$59,MATCH((($H43-MarketData!$B$4)/360),Bootstrap!$B$39:$B$59,1)+1)-INDEX(Bootstrap!$D$39:$D$59,MATCH((($H43-MarketData!$B$4)/360),Bootstrap!$B$39:$B$59,1)))*(((($H43-MarketData!$B$4)/360))-INDEX(Bootstrap!$B$39:$B$59,MATCH((($H43-MarketData!$B$4)/360),Bootstrap!$B$39:$B$59,1)))/(INDEX(Bootstrap!$B$39:$B$59,MATCH((($H43-MarketData!$B$4)/360),Bootstrap!$B$39:$B$59,1)+1)-INDEX(Bootstrap!$B$39:$B$59,MATCH((($H43-MarketData!$B$4)/360),Bootstrap!$B$39:$B$59,1)))) -> 0.88280101 | K43: =EXP(INDEX(Bootstrap!$D$39:$D$59,MATCH((($I43-MarketData!$B$4)/360),Bootstrap!$B$39:$B$59,1))+(INDEX(Bootstrap!$D$39:$D$59,MATCH((($I43-MarketData!$B$4)/360),Bootstrap!$B$39:$B$59,1)+1)-INDEX(Bootstrap!$D$39:$D$59,MATCH((($I43-MarketData!$B$4)/360),Bootstrap!$B$39:$B$59,1)))*(((($I43-MarketData!$B$4)/360))-INDEX(Bootstrap!$B$39:$B$59,MATCH((($I43-MarketData!$B$4)/360),Bootstrap!$B$39:$B$59,1)))/(INDEX(Bootstrap!$B$39:$B$59,MATCH((($I43-MarketData!$B$4)/360),Bootstrap!$B$39:$B$59,1)+1)-INDEX(Bootstrap!$B$39:$B$59,MATCH((($I43-MarketData!$B$4)/360),Bootstrap!$B$39:$B$59,1)))) -> 0.87993489 | L43: =(J43/K43-1)/G43 -> 0.037825473 | M43: =MarketData!$C$89 -> 0.038076154 | N43: =(L43-M43)*10000 -> -2.5068078
A44: =MarketData!$A$90 -> 47381 | B44: =(A44-MarketData!$B$4)/360 -> 3.3444444 | C44: =EXP(INDEX(Bootstrap!$D$39:$D$59,MATCH($B44,Bootstrap!$B$39:$B$59,1))+(INDEX(Bootstrap!$D$39:$D$59,MATCH($B44,Bootstrap!$B$39:$B$59,1)+1)-INDEX(Bootstrap!$D$39:$D$59,MATCH($B44,Bootstrap!$B$39:$B$59,1)))*(($B44)-INDEX(Bootstrap!$B$39:$B$59,MATCH($B44,Bootstrap!$B$39:$B$59,1)))/(INDEX(Bootstrap!$B$39:$B$59,MATCH($B44,Bootstrap!$B$39:$B$59,1)+1)-INDEX(Bootstrap!$B$39:$B$59,MATCH($B44,Bootstrap!$B$39:$B$59,1)))) -> 0.87928899 | D44: =MarketData!$B$90 -> 0.87956788 | E44: =(LN(D44)-LN(C44))/B44*10000 -> 0.94822227 | F44: =A45 -> 47413 | G44: =(F44-A44)/360 -> 0.088888889 | H44: =WORKDAY(A44,-5) -> 47374 | I44: =WORKDAY(F44,-5) -> 47406 | J44: =EXP(INDEX(Bootstrap!$D$39:$D$59,MATCH((($H44-MarketData!$B$4)/360),Bootstrap!$B$39:$B$59,1))+(INDEX(Bootstrap!$D$39:$D$59,MATCH((($H44-MarketData!$B$4)/360),Bootstrap!$B$39:$B$59,1)+1)-INDEX(Bootstrap!$D$39:$D$59,MATCH((($H44-MarketData!$B$4)/360),Bootstrap!$B$39:$B$59,1)))*(((($H44-MarketData!$B$4)/360))-INDEX(Bootstrap!$B$39:$B$59,MATCH((($H44-MarketData!$B$4)/360),Bootstrap!$B$39:$B$59,1)))/(INDEX(Bootstrap!$B$39:$B$59,MATCH((($H44-MarketData!$B$4)/360),Bootstrap!$B$39:$B$59,1)+1)-INDEX(Bootstrap!$B$39:$B$59,MATCH((($H44-MarketData!$B$4)/360),Bootstrap!$B$39:$B$59,1)))) -> 0.87993489 | K44: =EXP(INDEX(Bootstrap!$D$39:$D$59,MATCH((($I44-MarketData!$B$4)/360),Bootstrap!$B$39:$B$59,1))+(INDEX(Bootstrap!$D$39:$D$59,MATCH((($I44-MarketData!$B$4)/360),Bootstrap!$B$39:$B$59,1)+1)-INDEX(Bootstrap!$D$39:$D$59,MATCH((($I44-MarketData!$B$4)/360),Bootstrap!$B$39:$B$59,1)))*(((($I44-MarketData!$B$4)/360))-INDEX(Bootstrap!$B$39:$B$59,MATCH((($I44-MarketData!$B$4)/360),Bootstrap!$B$39:$B$59,1)))/(INDEX(Bootstrap!$B$39:$B$59,MATCH((($I44-MarketData!$B$4)/360),Bootstrap!$B$39:$B$59,1)+1)-INDEX(Bootstrap!$B$39:$B$59,MATCH((($I44-MarketData!$B$4)/360),Bootstrap!$B$39:$B$59,1)))) -> 0.87698608 | L44: =(J44/K44-1)/G44 -> 0.037827458 | M44: =MarketData!$C$90 -> 0.038123594 | N44: =(L44-M44)*10000 -> -2.9613598
A45: =MarketData!$A$91 -> 47413 | B45: =(A45-MarketData!$B$4)/360 -> 3.4333333 | C45: =EXP(INDEX(Bootstrap!$D$39:$D$59,MATCH($B45,Bootstrap!$B$39:$B$59,1))+(INDEX(Bootstrap!$D$39:$D$59,MATCH($B45,Bootstrap!$B$39:$B$59,1)+1)-INDEX(Bootstrap!$D$39:$D$59,MATCH($B45,Bootstrap!$B$39:$B$59,1)))*(($B45)-INDEX(Bootstrap!$B$39:$B$59,MATCH($B45,Bootstrap!$B$39:$B$59,1)))/(INDEX(Bootstrap!$B$39:$B$59,MATCH($B45,Bootstrap!$B$39:$B$59,1)+1)-INDEX(Bootstrap!$B$39:$B$59,MATCH($B45,Bootstrap!$B$39:$B$59,1)))) -> 0.87634234 | D45: =MarketData!$B$91 -> 0.87659644 | E45: =(LN(D45)-LN(C45))/B45*10000 -> 0.84439824 | F45: =A46 -> 47442 | G45: =(F45-A45)/360 -> 0.080555556 | H45: =WORKDAY(A45,-5) -> 47406 | I45: =WORKDAY(F45,-5) -> 47435 | J45: =EXP(INDEX(Bootstrap!$D$39:$D$59,MATCH((($H45-MarketData!$B$4)/360),Bootstrap!$B$39:$B$59,1))+(INDEX(Bootstrap!$D$39:$D$59,MATCH((($H45-MarketData!$B$4)/360),Bootstrap!$B$39:$B$59,1)+1)-INDEX(Bootstrap!$D$39:$D$59,MATCH((($H45-MarketData!$B$4)/360),Bootstrap!$B$39:$B$59,1)))*(((($H45-MarketData!$B$4)/360))-INDEX(Bootstrap!$B$39:$B$59,MATCH((($H45-MarketData!$B$4)/360),Bootstrap!$B$39:$B$59,1)))/(INDEX(Bootstrap!$B$39:$B$59,MATCH((($H45-MarketData!$B$4)/360),Bootstrap!$B$39:$B$59,1)+1)-INDEX(Bootstrap!$B$39:$B$59,MATCH((($H45-MarketData!$B$4)/360),Bootstrap!$B$39:$B$59,1)))) -> 0.87698608 | K45: =EXP(INDEX(Bootstrap!$D$39:$D$59,MATCH((($I45-MarketData!$B$4)/360),Bootstrap!$B$39:$B$59,1))+(INDEX(Bootstrap!$D$39:$D$59,MATCH((($I45-MarketData!$B$4)/360),Bootstrap!$B$39:$B$59,1)+1)-INDEX(Bootstrap!$D$39:$D$59,MATCH((($I45-MarketData!$B$4)/360),Bootstrap!$B$39:$B$59,1)))*(((($I45-MarketData!$B$4)/360))-INDEX(Bootstrap!$B$39:$B$59,MATCH((($I45-MarketData!$B$4)/360),Bootstrap!$B$39:$B$59,1)))/(INDEX(Bootstrap!$B$39:$B$59,MATCH((($I45-MarketData!$B$4)/360),Bootstrap!$B$39:$B$59,1)+1)-INDEX(Bootstrap!$B$39:$B$59,MATCH((($I45-MarketData!$B$4)/360),Bootstrap!$B$39:$B$59,1)))) -> 0.87432225 | L45: =(J45/K45-1)/G45 -> 0.037821504 | M45: =MarketData!$C$91 -> 0.038161383 | N45: =(L45-M45)*10000 -> -3.3987984
A46: =MarketData!$A$92 -> 47442 | B46: =(A46-MarketData!$B$4)/360 -> 3.5138889 | C46: =EXP(INDEX(Bootstrap!$D$39:$D$59,MATCH($B46,Bootstrap!$B$39:$B$59,1))+(INDEX(Bootstrap!$D$39:$D$59,MATCH($B46,Bootstrap!$B$39:$B$59,1)+1)-INDEX(Bootstrap!$D$39:$D$59,MATCH($B46,Bootstrap!$B$39:$B$59,1)))*(($B46)-INDEX(Bootstrap!$B$39:$B$59,MATCH($B46,Bootstrap!$B$39:$B$59,1)))/(INDEX(Bootstrap!$B$39:$B$59,MATCH($B46,Bootstrap!$B$39:$B$59,1)+1)-INDEX(Bootstrap!$B$39:$B$59,MATCH($B46,Bootstrap!$B$39:$B$59,1)))) -> 0.87368047 | D46: =MarketData!$B$92 -> 0.87390916 | E46: =(LN(D46)-LN(C46))/B46*10000 -> 0.74480335 | F46: =A47 -> 47472 | G46: =(F46-A46)/360 -> 0.083333333 | H46: =WORKDAY(A46,-5) -> 47435 | I46: =WORKDAY(F46,-5) -> 47465 | J46: =EXP(INDEX(Bootstrap!$D$39:$D$59,MATCH((($H46-MarketData!$B$4)/360),Bootstrap!$B$39:$B$59,1))+(INDEX(Bootstrap!$D$39:$D$59,MATCH((($H46-MarketData!$B$4)/360),Bootstrap!$B$39:$B$59,1)+1)-INDEX(Bootstrap!$D$39:$D$59,MATCH((($H46-MarketData!$B$4)/360),Bootstrap!$B$39:$B$59,1)))*(((($H46-MarketData!$B$4)/360))-INDEX(Bootstrap!$B$39:$B$59,MATCH((($H46-MarketData!$B$4)/360),Bootstrap!$B$39:$B$59,1)))/(INDEX(Bootstrap!$B$39:$B$59,MATCH((($H46-MarketData!$B$4)/360),Bootstrap!$B$39:$B$59,1)+1)-INDEX(Bootstrap!$B$39:$B$59,MATCH((($H46-MarketData!$B$4)/360),Bootstrap!$B$39:$B$59,1)))) -> 0.87432225 | K46: =EXP(INDEX(Bootstrap!$D$39:$D$59,MATCH((($I46-MarketData!$B$4)/360),Bootstrap!$B$39:$B$59,1))+(INDEX(Bootstrap!$D$39:$D$59,MATCH((($I46-MarketData!$B$4)/360),Bootstrap!$B$39:$B$59,1)+1)-INDEX(Bootstrap!$D$39:$D$59,MATCH((($I46-MarketData!$B$4)/360),Bootstrap!$B$39:$B$59,1)))*(((($I46-MarketData!$B$4)/360))-INDEX(Bootstrap!$B$39:$B$59,MATCH((($I46-MarketData!$B$4)/360),Bootstrap!$B$39:$B$59,1)))/(INDEX(Bootstrap!$B$39:$B$59,MATCH((($I46-MarketData!$B$4)/360),Bootstrap!$B$39:$B$59,1)+1)-INDEX(Bootstrap!$B$39:$B$59,MATCH((($I46-MarketData!$B$4)/360),Bootstrap!$B$39:$B$59,1)))) -> 0.87157508 | L46: =(J46/K46-1)/G46 -> 0.037823488 | M46: =MarketData!$C$92 -> 0.03820613 | N46: =(L46-M46)*10000 -> -3.8264193
A47: =MarketData!$A$93 -> 47472 | B47: =(A47-MarketData!$B$4)/360 -> 3.5972222 | C47: =EXP(INDEX(Bootstrap!$D$39:$D$59,MATCH($B47,Bootstrap!$B$39:$B$59,1))+(INDEX(Bootstrap!$D$39:$D$59,MATCH($B47,Bootstrap!$B$39:$B$59,1)+1)-INDEX(Bootstrap!$D$39:$D$59,MATCH($B47,Bootstrap!$B$39:$B$59,1)))*(($B47)-INDEX(Bootstrap!$B$39:$B$59,MATCH($B47,Bootstrap!$B$39:$B$59,1)))/(INDEX(Bootstrap!$B$39:$B$59,MATCH($B47,Bootstrap!$B$39:$B$59,1)+1)-INDEX(Bootstrap!$B$39:$B$59,MATCH($B47,Bootstrap!$B$39:$B$59,1)))) -> 0.87093532 | D47: =MarketData!$B$93 -> 0.8711348 | E47: =(LN(D47)-LN(C47))/B47*10000 -> 0.63664932 | F47: =A48 -> 47505 | G47: =(F47-A47)/360 -> 0.091666667 | H47: =WORKDAY(A47,-5) -> 47465 | I47: =WORKDAY(F47,-5) -> 47498 | J47: =EXP(INDEX(Bootstrap!$D$39:$D$59,MATCH((($H47-MarketData!$B$4)/360),Bootstrap!$B$39:$B$59,1))+(INDEX(Bootstrap!$D$39:$D$59,MATCH((($H47-MarketData!$B$4)/360),Bootstrap!$B$39:$B$59,1)+1)-INDEX(Bootstrap!$D$39:$D$59,MATCH((($H47-MarketData!$B$4)/360),Bootstrap!$B$39:$B$59,1)))*(((($H47-MarketData!$B$4)/360))-INDEX(Bootstrap!$B$39:$B$59,MATCH((($H47-MarketData!$B$4)/360),Bootstrap!$B$39:$B$59,1)))/(INDEX(Bootstrap!$B$39:$B$59,MATCH((($H47-MarketData!$B$4)/360),Bootstrap!$B$39:$B$59,1)+1)-INDEX(Bootstrap!$B$39:$B$59,MATCH((($H47-MarketData!$B$4)/360),Bootstrap!$B$39:$B$59,1)))) -> 0.87157508 | K47: =EXP(INDEX(Bootstrap!$D$39:$D$59,MATCH((($I47-MarketData!$B$4)/360),Bootstrap!$B$39:$B$59,1))+(INDEX(Bootstrap!$D$39:$D$59,MATCH((($I47-MarketData!$B$4)/360),Bootstrap!$B$39:$B$59,1)+1)-INDEX(Bootstrap!$D$39:$D$59,MATCH((($I47-MarketData!$B$4)/360),Bootstrap!$B$39:$B$59,1)))*(((($I47-MarketData!$B$4)/360))-INDEX(Bootstrap!$B$39:$B$59,MATCH((($I47-MarketData!$B$4)/360),Bootstrap!$B$39:$B$59,1)))/(INDEX(Bootstrap!$B$39:$B$59,MATCH((($I47-MarketData!$B$4)/360),Bootstrap!$B$39:$B$59,1)+1)-INDEX(Bootstrap!$B$39:$B$59,MATCH((($I47-MarketData!$B$4)/360),Bootstrap!$B$39:$B$59,1)))) -> 0.86856317 | L47: =(J47/K47-1)/G47 -> 0.037829444 | M47: =MarketData!$C$93 -> 0.038256581 | N47: =(L47-M47)*10000 -> -4.2713766
A48: =MarketData!$A$94 -> 47505 | B48: =(A48-MarketData!$B$4)/360 -> 3.6888889 | C48: =EXP(INDEX(Bootstrap!$D$39:$D$59,MATCH($B48,Bootstrap!$B$39:$B$59,1))+(INDEX(Bootstrap!$D$39:$D$59,MATCH($B48,Bootstrap!$B$39:$B$59,1)+1)-INDEX(Bootstrap!$D$39:$D$59,MATCH($B48,Bootstrap!$B$39:$B$59,1)))*(($B48)-INDEX(Bootstrap!$B$39:$B$59,MATCH($B48,Bootstrap!$B$39:$B$59,1)))/(INDEX(Bootstrap!$B$39:$B$59,MATCH($B48,Bootstrap!$B$39:$B$59,1)+1)-INDEX(Bootstrap!$B$39:$B$59,MATCH($B48,Bootstrap!$B$39:$B$59,1)))) -> 0.86792562 | D48: =MarketData!$B$94 -> 0.86808959 | E48: =(LN(D48)-LN(C48))/B48*10000 -> 0.5120843 | F48: =A49 -> 47534 | G48: =(F48-A48)/360 -> 0.080555556 | H48: =WORKDAY(A48,-5) -> 47498 | I48: =WORKDAY(F48,-5) -> 47527 | J48: =EXP(INDEX(Bootstrap!$D$39:$D$59,MATCH((($H48-MarketData!$B$4)/360),Bootstrap!$B$39:$B$59,1))+(INDEX(Bootstrap!$D$39:$D$59,MATCH((($H48-MarketData!$B$4)/360),Bootstrap!$B$39:$B$59,1)+1)-INDEX(Bootstrap!$D$39:$D$59,MATCH((($H48-MarketData!$B$4)/360),Bootstrap!$B$39:$B$59,1)))*(((($H48-MarketData!$B$4)/360))-INDEX(Bootstrap!$B$39:$B$59,MATCH((($H48-MarketData!$B$4)/360),Bootstrap!$B$39:$B$59,1)))/(INDEX(Bootstrap!$B$39:$B$59,MATCH((($H48-MarketData!$B$4)/360),Bootstrap!$B$39:$B$59,1)+1)-INDEX(Bootstrap!$B$39:$B$59,MATCH((($H48-MarketData!$B$4)/360),Bootstrap!$B$39:$B$59,1)))) -> 0.86856317 | K48: =EXP(INDEX(Bootstrap!$D$39:$D$59,MATCH((($I48-MarketData!$B$4)/360),Bootstrap!$B$39:$B$59,1))+(INDEX(Bootstrap!$D$39:$D$59,MATCH((($I48-MarketData!$B$4)/360),Bootstrap!$B$39:$B$59,1)+1)-INDEX(Bootstrap!$D$39:$D$59,MATCH((($I48-MarketData!$B$4)/360),Bootstrap!$B$39:$B$59,1)))*(((($I48-MarketData!$B$4)/360))-INDEX(Bootstrap!$B$39:$B$59,MATCH((($I48-MarketData!$B$4)/360),Bootstrap!$B$39:$B$59,1)))/(INDEX(Bootstrap!$B$39:$B$59,MATCH((($I48-MarketData!$B$4)/360),Bootstrap!$B$39:$B$59,1)+1)-INDEX(Bootstrap!$B$39:$B$59,MATCH((($I48-MarketData!$B$4)/360),Bootstrap!$B$39:$B$59,1)))) -> 0.86592493 | L48: =(J48/K48-1)/G48 -> 0.037821504 | M48: =MarketData!$C$94 -> 0.03829388 | N48: =(L48-M48)*10000 -> -4.7237614
A49: =MarketData!$A$95 -> 47534 | B49: =(A49-MarketData!$B$4)/360 -> 3.7694444 | C49: =EXP(INDEX(Bootstrap!$D$39:$D$59,MATCH($B49,Bootstrap!$B$39:$B$59,1))+(INDEX(Bootstrap!$D$39:$D$59,MATCH($B49,Bootstrap!$B$39:$B$59,1)+1)-INDEX(Bootstrap!$D$39:$D$59,MATCH($B49,Bootstrap!$B$39:$B$59,1)))*(($B49)-INDEX(Bootstrap!$B$39:$B$59,MATCH($B49,Bootstrap!$B$39:$B$59,1)))/(INDEX(Bootstrap!$B$39:$B$59,MATCH($B49,Bootstrap!$B$39:$B$59,1)+1)-INDEX(Bootstrap!$B$39:$B$59,MATCH($B49,Bootstrap!$B$39:$B$59,1)))) -> 0.86528931 | D49: =MarketData!$B$95 -> 0.86541917 | E49: =(LN(D49)-LN(C49))/B49*10000 -> 0.39810295 | F49: =A50 -> 47562 | G49: =(F49-A49)/360 -> 0.077777778 | H49: =WORKDAY(A49,-5) -> 47527 | I49: =WORKDAY(F49,-5) -> 47555 | J49: =EXP(INDEX(Bootstrap!$D$39:$D$59,MATCH((($H49-MarketData!$B$4)/360),Bootstrap!$B$39:$B$59,1))+(INDEX(Bootstrap!$D$39:$D$59,MATCH((($H49-MarketData!$B$4)/360),Bootstrap!$B$39:$B$59,1)+1)-INDEX(Bootstrap!$D$39:$D$59,MATCH((($H49-MarketData!$B$4)/360),Bootstrap!$B$39:$B$59,1)))*(((($H49-MarketData!$B$4)/360))-INDEX(Bootstrap!$B$39:$B$59,MATCH((($H49-MarketData!$B$4)/360),Bootstrap!$B$39:$B$59,1)))/(INDEX(Bootstrap!$B$39:$B$59,MATCH((($H49-MarketData!$B$4)/360),Bootstrap!$B$39:$B$59,1)+1)-INDEX(Bootstrap!$B$39:$B$59,MATCH((($H49-MarketData!$B$4)/360),Bootstrap!$B$39:$B$59,1)))) -> 0.86592493 | K49: =EXP(INDEX(Bootstrap!$D$39:$D$59,MATCH((($I49-MarketData!$B$4)/360),Bootstrap!$B$39:$B$59,1))+(INDEX(Bootstrap!$D$39:$D$59,MATCH((($I49-MarketData!$B$4)/360),Bootstrap!$B$39:$B$59,1)+1)-INDEX(Bootstrap!$D$39:$D$59,MATCH((($I49-MarketData!$B$4)/360),Bootstrap!$B$39:$B$59,1)))*(((($I49-MarketData!$B$4)/360))-INDEX(Bootstrap!$B$39:$B$59,MATCH((($I49-MarketData!$B$4)/360),Bootstrap!$B$39:$B$59,1)))/(INDEX(Bootstrap!$B$39:$B$59,MATCH((($I49-MarketData!$B$4)/360),Bootstrap!$B$39:$B$59,1)+1)-INDEX(Bootstrap!$B$39:$B$59,MATCH((($I49-MarketData!$B$4)/360),Bootstrap!$B$39:$B$59,1)))) -> 0.86338526 | L49: =(J49/K49-1)/G49 -> 0.037819519 | M49: =MarketData!$C$95 -> 0.038333357 | N49: =(L49-M49)*10000 -> -5.1383862
A50: =MarketData!$A$96 -> 47562 | B50: =(A50-MarketData!$B$4)/360 -> 3.8472222 | C50: =EXP(INDEX(Bootstrap!$D$39:$D$59,MATCH($B50,Bootstrap!$B$39:$B$59,1))+(INDEX(Bootstrap!$D$39:$D$59,MATCH($B50,Bootstrap!$B$39:$B$59,1)+1)-INDEX(Bootstrap!$D$39:$D$59,MATCH($B50,Bootstrap!$B$39:$B$59,1)))*(($B50)-INDEX(Bootstrap!$B$39:$B$59,MATCH($B50,Bootstrap!$B$39:$B$59,1)))/(INDEX(Bootstrap!$B$39:$B$59,MATCH($B50,Bootstrap!$B$39:$B$59,1)+1)-INDEX(Bootstrap!$B$39:$B$59,MATCH($B50,Bootstrap!$B$39:$B$59,1)))) -> 0.86275151 | D50: =MarketData!$B$96 -> 0.86284589 | E50: =(LN(D50)-LN(C50))/B50*10000 -> 0.28430508 | F50: =A51 -> 47596 | G50: =(F50-A50)/360 -> 0.094444444 | H50: =WORKDAY(A50,-5) -> 47555 | I50: =WORKDAY(F50,-5) -> 47589 | J50: =EXP(INDEX(Bootstrap!$D$39:$D$59,MATCH((($H50-MarketData!$B$4)/360),Bootstrap!$B$39:$B$59,1))+(INDEX(Bootstrap!$D$39:$D$59,MATCH((($H50-MarketData!$B$4)/360),Bootstrap!$B$39:$B$59,1)+1)-INDEX(Bootstrap!$D$39:$D$59,MATCH((($H50-MarketData!$B$4)/360),Bootstrap!$B$39:$B$59,1)))*(((($H50-MarketData!$B$4)/360))-INDEX(Bootstrap!$B$39:$B$59,MATCH((($H50-MarketData!$B$4)/360),Bootstrap!$B$39:$B$59,1)))/(INDEX(Bootstrap!$B$39:$B$59,MATCH((($H50-MarketData!$B$4)/360),Bootstrap!$B$39:$B$59,1)+1)-INDEX(Bootstrap!$B$39:$B$59,MATCH((($H50-MarketData!$B$4)/360),Bootstrap!$B$39:$B$59,1)))) -> 0.86338526 | K50: =EXP(INDEX(Bootstrap!$D$39:$D$59,MATCH((($I50-MarketData!$B$4)/360),Bootstrap!$B$39:$B$59,1))+(INDEX(Bootstrap!$D$39:$D$59,MATCH((($I50-MarketData!$B$4)/360),Bootstrap!$B$39:$B$59,1)+1)-INDEX(Bootstrap!$D$39:$D$59,MATCH((($I50-MarketData!$B$4)/360),Bootstrap!$B$39:$B$59,1)))*(((($I50-MarketData!$B$4)/360))-INDEX(Bootstrap!$B$39:$B$59,MATCH((($I50-MarketData!$B$4)/360),Bootstrap!$B$39:$B$59,1)))/(INDEX(Bootstrap!$B$39:$B$59,MATCH((($I50-MarketData!$B$4)/360),Bootstrap!$B$39:$B$59,1)+1)-INDEX(Bootstrap!$B$39:$B$59,MATCH((($I50-MarketData!$B$4)/360),Bootstrap!$B$39:$B$59,1)))) -> 0.8603114 | L50: =(J50/K50-1)/G50 -> 0.037831429 | M50: =MarketData!$C$96 -> 0.038390047 | N50: =(L50-M50)*10000 -> -5.5861779
A51: =MarketData!$A$97 -> 47596 | B51: =(A51-MarketData!$B$4)/360 -> 3.9416667 | C51: =EXP(INDEX(Bootstrap!$D$39:$D$59,MATCH($B51,Bootstrap!$B$39:$B$59,1))+(INDEX(Bootstrap!$D$39:$D$59,MATCH($B51,Bootstrap!$B$39:$B$59,1)+1)-INDEX(Bootstrap!$D$39:$D$59,MATCH($B51,Bootstrap!$B$39:$B$59,1)))*(($B51)-INDEX(Bootstrap!$B$39:$B$59,MATCH($B51,Bootstrap!$B$39:$B$59,1)))/(INDEX(Bootstrap!$B$39:$B$59,MATCH($B51,Bootstrap!$B$39:$B$59,1)+1)-INDEX(Bootstrap!$B$39:$B$59,MATCH($B51,Bootstrap!$B$39:$B$59,1)))) -> 0.8596799 | D51: =MarketData!$B$97 -> 0.85972785 | E51: =(LN(D51)-LN(C51))/B51*10000 -> 0.14149123 | F51: =A52 -> 47623 | G51: =(F51-A51)/360 -> 0.075 | H51: =WORKDAY(A51,-5) -> 47589 | I51: =WORKDAY(F51,-5) -> 47616 | J51: =EXP(INDEX(Bootstrap!$D$39:$D$59,MATCH((($H51-MarketData!$B$4)/360),Bootstrap!$B$39:$B$59,1))+(INDEX(Bootstrap!$D$39:$D$59,MATCH((($H51-MarketData!$B$4)/360),Bootstrap!$B$39:$B$59,1)+1)-INDEX(Bootstrap!$D$39:$D$59,MATCH((($H51-MarketData!$B$4)/360),Bootstrap!$B$39:$B$59,1)))*(((($H51-MarketData!$B$4)/360))-INDEX(Bootstrap!$B$39:$B$59,MATCH((($H51-MarketData!$B$4)/360),Bootstrap!$B$39:$B$59,1)))/(INDEX(Bootstrap!$B$39:$B$59,MATCH((($H51-MarketData!$B$4)/360),Bootstrap!$B$39:$B$59,1)+1)-INDEX(Bootstrap!$B$39:$B$59,MATCH((($H51-MarketData!$B$4)/360),Bootstrap!$B$39:$B$59,1)))) -> 0.8603114 | K51: =EXP(INDEX(Bootstrap!$D$39:$D$59,MATCH((($I51-MarketData!$B$4)/360),Bootstrap!$B$39:$B$59,1))+(INDEX(Bootstrap!$D$39:$D$59,MATCH((($I51-MarketData!$B$4)/360),Bootstrap!$B$39:$B$59,1)+1)-INDEX(Bootstrap!$D$39:$D$59,MATCH((($I51-MarketData!$B$4)/360),Bootstrap!$B$39:$B$59,1)))*(((($I51-MarketData!$B$4)/360))-INDEX(Bootstrap!$B$39:$B$59,MATCH((($I51-MarketData!$B$4)/360),Bootstrap!$B$39:$B$59,1)))/(INDEX(Bootstrap!$B$39:$B$59,MATCH((($I51-MarketData!$B$4)/360),Bootstrap!$B$39:$B$59,1)+1)-INDEX(Bootstrap!$B$39:$B$59,MATCH((($I51-MarketData!$B$4)/360),Bootstrap!$B$39:$B$59,1)))) -> 0.85787819 | L51: =(J51/K51-1)/G51 -> 0.037817534 | M51: =MarketData!$C$97 -> 0.038420602 | N51: =(L51-M51)*10000 -> -6.0306735
A52: =MarketData!$A$98 -> 47623 | B52: =(A52-MarketData!$B$4)/360 -> 4.0166667 | C52: =EXP(INDEX(Bootstrap!$D$39:$D$59,MATCH($B52,Bootstrap!$B$39:$B$59,1))+(INDEX(Bootstrap!$D$39:$D$59,MATCH($B52,Bootstrap!$B$39:$B$59,1)+1)-INDEX(Bootstrap!$D$39:$D$59,MATCH($B52,Bootstrap!$B$39:$B$59,1)))*(($B52)-INDEX(Bootstrap!$B$39:$B$59,MATCH($B52,Bootstrap!$B$39:$B$59,1)))/(INDEX(Bootstrap!$B$39:$B$59,MATCH($B52,Bootstrap!$B$39:$B$59,1)+1)-INDEX(Bootstrap!$B$39:$B$59,MATCH($B52,Bootstrap!$B$39:$B$59,1)))) -> 0.85724848 | D52: =MarketData!$B$98 -> 0.85725698 | E52: =(LN(D52)-LN(C52))/B52*10000 -> 0.024686898 | F52: =A53 -> 47654 | G52: =(F52-A52)/360 -> 0.086111111 | H52: =WORKDAY(A52,-5) -> 47616 | I52: =WORKDAY(F52,-5) -> 47647 | J52: =EXP(INDEX(Bootstrap!$D$39:$D$59,MATCH((($H52-MarketData!$B$4)/360),Bootstrap!$B$39:$B$59,1))+(INDEX(Bootstrap!$D$39:$D$59,MATCH((($H52-MarketData!$B$4)/360),Bootstrap!$B$39:$B$59,1)+1)-INDEX(Bootstrap!$D$39:$D$59,MATCH((($H52-MarketData!$B$4)/360),Bootstrap!$B$39:$B$59,1)))*(((($H52-MarketData!$B$4)/360))-INDEX(Bootstrap!$B$39:$B$59,MATCH((($H52-MarketData!$B$4)/360),Bootstrap!$B$39:$B$59,1)))/(INDEX(Bootstrap!$B$39:$B$59,MATCH((($H52-MarketData!$B$4)/360),Bootstrap!$B$39:$B$59,1)+1)-INDEX(Bootstrap!$B$39:$B$59,MATCH((($H52-MarketData!$B$4)/360),Bootstrap!$B$39:$B$59,1)))) -> 0.85787819 | K52: =EXP(INDEX(Bootstrap!$D$39:$D$59,MATCH((($I52-MarketData!$B$4)/360),Bootstrap!$B$39:$B$59,1))+(INDEX(Bootstrap!$D$39:$D$59,MATCH((($I52-MarketData!$B$4)/360),Bootstrap!$B$39:$B$59,1)+1)-INDEX(Bootstrap!$D$39:$D$59,MATCH((($I52-MarketData!$B$4)/360),Bootstrap!$B$39:$B$59,1)))*(((($I52-MarketData!$B$4)/360))-INDEX(Bootstrap!$B$39:$B$59,MATCH((($I52-MarketData!$B$4)/360),Bootstrap!$B$39:$B$59,1)))/(INDEX(Bootstrap!$B$39:$B$59,MATCH((($I52-MarketData!$B$4)/360),Bootstrap!$B$39:$B$59,1)+1)-INDEX(Bootstrap!$B$39:$B$59,MATCH((($I52-MarketData!$B$4)/360),Bootstrap!$B$39:$B$59,1)))) -> 0.85507941 | L52: =(J52/K52-1)/G52 -> 0.038010375 | M52: =MarketData!$C$98 -> 0.038469376 | N52: =(L52-M52)*10000 -> -4.5900082
A53: =MarketData!$A$99 -> 47654 | B53: =(A53-MarketData!$B$4)/360 -> 4.1027778 | C53: =EXP(INDEX(Bootstrap!$D$39:$D$59,MATCH($B53,Bootstrap!$B$39:$B$59,1))+(INDEX(Bootstrap!$D$39:$D$59,MATCH($B53,Bootstrap!$B$39:$B$59,1)+1)-INDEX(Bootstrap!$D$39:$D$59,MATCH($B53,Bootstrap!$B$39:$B$59,1)))*(($B53)-INDEX(Bootstrap!$B$39:$B$59,MATCH($B53,Bootstrap!$B$39:$B$59,1)))/(INDEX(Bootstrap!$B$39:$B$59,MATCH($B53,Bootstrap!$B$39:$B$59,1)+1)-INDEX(Bootstrap!$B$39:$B$59,MATCH($B53,Bootstrap!$B$39:$B$59,1)))) -> 0.85443277 | D53: =MarketData!$B$99 -> 0.85442543 | E53: =(LN(D53)-LN(C53))/B53*10000 -> -0.020943644
A55: Mean |Δ zero| (bp) | C55: {=AVERAGE(ABS(E5:E53))} -> 0.79510803
A56: Max |Δ zero| (bp) | C56: {=MAX(ABS(E5:E53))} -> 1.6003867
A57: Mean |Δ fwd| (bp) | C57: {=AVERAGE(ABS(N5:N52))} -> 2.0024294
A58: Max |Δ fwd| (bp) | C58: {=MAX(ABS(N5:N52))} -> 7.0343432

Sheet Interpolation
A1: INTERPOLATION TEMPLATE — enter any date(s); everything else is a formula
A2: Blue cells are inputs you can change. All outputs interpolate the Bootstrap node grid (log-linear on ln DF).
A4: A) DISCOUNT FACTOR — enter a date
A5: Input date | B5: Time (yrs) | C5: Discount factor | D5: Zero rate (cont, ACT/360)
A6: 46924 | B6: =(A6-MarketData!$B$4)/360 -> 2.075 | C6: =EXP(INDEX(Bootstrap!$D$39:$D$59,MATCH($B6,Bootstrap!$B$39:$B$59,1))+(INDEX(Bootstrap!$D$39:$D$59,MATCH($B6,Bootstrap!$B$39:$B$59,1)+1)-INDEX(Bootstrap!$D$39:$D$59,MATCH($B6,Bootstrap!$B$39:$B$59,1)))*(($B6)-INDEX(Bootstrap!$B$39:$B$59,MATCH($B6,Bootstrap!$B$39:$B$59,1)))/(INDEX(Bootstrap!$B$39:$B$59,MATCH($B6,Bootstrap!$B$39:$B$59,1)+1)-INDEX(Bootstrap!$B$39:$B$59,MATCH($B6,Bootstrap!$B$39:$B$59,1)))) -> 0.92286119 | D6: =-LN(C6)/B6 -> 0.038687443
A7: 47289 | B7: =(A7-MarketData!$B$4)/360 -> 3.0888889 | C7: =EXP(INDEX(Bootstrap!$D$39:$D$59,MATCH($B7,Bootstrap!$B$39:$B$59,1))+(INDEX(Bootstrap!$D$39:$D$59,MATCH($B7,Bootstrap!$B$39:$B$59,1)+1)-INDEX(Bootstrap!$D$39:$D$59,MATCH($B7,Bootstrap!$B$39:$B$59,1)))*(($B7)-INDEX(Bootstrap!$B$39:$B$59,MATCH($B7,Bootstrap!$B$39:$B$59,1)))/(INDEX(Bootstrap!$B$39:$B$59,MATCH($B7,Bootstrap!$B$39:$B$59,1)+1)-INDEX(Bootstrap!$B$39:$B$59,MATCH($B7,Bootstrap!$B$39:$B$59,1)))) -> 0.88781592 | D7: =-LN(C7)/B7 -> 0.038522221
A8: 47654 | B8: =(A8-MarketData!$B$4)/360 -> 4.1027778 | C8: =EXP(INDEX(Bootstrap!$D$39:$D$59,MATCH($B8,Bootstrap!$B$39:$B$59,1))+(INDEX(Bootstrap!$D$39:$D$59,MATCH($B8,Bootstrap!$B$39:$B$59,1)+1)-INDEX(Bootstrap!$D$39:$D$59,MATCH($B8,Bootstrap!$B$39:$B$59,1)))*(($B8)-INDEX(Bootstrap!$B$39:$B$59,MATCH($B8,Bootstrap!$B$39:$B$59,1)))/(INDEX(Bootstrap!$B$39:$B$59,MATCH($B8,Bootstrap!$B$39:$B$59,1)+1)-INDEX(Bootstrap!$B$39:$B$59,MATCH($B8,Bootstrap!$B$39:$B$59,1)))) -> 0.85443277 | D8: =-LN(C8)/B8 -> 0.038344132
A9: 46559 | B9: =(A9-MarketData!$B$4)/360 -> 1.0611111 | C9: =EXP(INDEX(Bootstrap!$D$39:$D$59,MATCH($B9,Bootstrap!$B$39:$B$59,1))+(INDEX(Bootstrap!$D$39:$D$59,MATCH($B9,Bootstrap!$B$39:$B$59,1)+1)-INDEX(Bootstrap!$D$39:$D$59,MATCH($B9,Bootstrap!$B$39:$B$59,1)))*(($B9)-INDEX(Bootstrap!$B$39:$B$59,MATCH($B9,Bootstrap!$B$39:$B$59,1)))/(INDEX(Bootstrap!$B$39:$B$59,MATCH($B9,Bootstrap!$B$39:$B$59,1)+1)-INDEX(Bootstrap!$B$39:$B$59,MATCH($B9,Bootstrap!$B$39:$B$59,1)))) -> 0.96051912 | D9: =-LN(C9)/B9 -> 0.037961523
A10: 47472 | B10: =(A10-MarketData!$B$4)/360 -> 3.5972222 | C10: =EXP(INDEX(Bootstrap!$D$39:$D$59,MATCH($B10,Bootstrap!$B$39:$B$59,1))+(INDEX(Bootstrap!$D$39:$D$59,MATCH($B10,Bootstrap!$B$39:$B$59,1)+1)-INDEX(Bootstrap!$D$39:$D$59,MATCH($B10,Bootstrap!$B$39:$B$59,1)))*(($B10)-INDEX(Bootstrap!$B$39:$B$59,MATCH($B10,Bootstrap!$B$39:$B$59,1)))/(INDEX(Bootstrap!$B$39:$B$59,MATCH($B10,Bootstrap!$B$39:$B$59,1)+1)-INDEX(Bootstrap!$B$39:$B$59,MATCH($B10,Bootstrap!$B$39:$B$59,1)))) -> 0.87093532 | D10: =-LN(C10)/B10 -> 0.038415075
A13: B) FORWARD RATE — enter start & end date (compounded SOFR forward, 5-business-day lag)
A14: Start | B14: End | C14: τ (ACT/360) | D14: DF(lag start) | E14: DF(lag end) | F14: Forward (5bd lag) | G14: Forward (no lag)
A15: 46924 | B15: 47654 | C15: =(B15-A15)/360 -> 2.0277778 | D15: =EXP(INDEX(Bootstrap!$D$39:$D$59,MATCH(((WORKDAY(A15,-5)-MarketData!$B$4)/360),Bootstrap!$B$39:$B$59,1))+(INDEX(Bootstrap!$D$39:$D$59,MATCH(((WORKDAY(A15,-5)-MarketData!$B$4)/360),Bootstrap!$B$39:$B$59,1)+1)-INDEX(Bootstrap!$D$39:$D$59,MATCH(((WORKDAY(A15,-5)-MarketData!$B$4)/360),Bootstrap!$B$39:$B$59,1)))*((((WORKDAY(A15,-5)-MarketData!$B$4)/360))-INDEX(Bootstrap!$B$39:$B$59,MATCH(((WORKDAY(A15,-5)-MarketData!$B$4)/360),Bootstrap!$B$39:$B$59,1)))/(INDEX(Bootstrap!$B$39:$B$59,MATCH(((WORKDAY(A15,-5)-MarketData!$B$4)/360),Bootstrap!$B$39:$B$59,1)+1)-INDEX(Bootstrap!$B$39:$B$59,MATCH(((WORKDAY(A15,-5)-MarketData!$B$4)/360),Bootstrap!$B$39:$B$59,1)))) -> 0.92355931 | E15: =EXP(INDEX(Bootstrap!$D$39:$D$59,MATCH(((WORKDAY(B15,-5)-MarketData!$B$4)/360),Bootstrap!$B$39:$B$59,1))+(INDEX(Bootstrap!$D$39:$D$59,MATCH(((WORKDAY(B15,-5)-MarketData!$B$4)/360),Bootstrap!$B$39:$B$59,1)+1)-INDEX(Bootstrap!$D$39:$D$59,MATCH(((WORKDAY(B15,-5)-MarketData!$B$4)/360),Bootstrap!$B$39:$B$59,1)))*((((WORKDAY(B15,-5)-MarketData!$B$4)/360))-INDEX(Bootstrap!$B$39:$B$59,MATCH(((WORKDAY(B15,-5)-MarketData!$B$4)/360),Bootstrap!$B$39:$B$59,1)))/(INDEX(Bootstrap!$B$39:$B$59,MATCH(((WORKDAY(B15,-5)-MarketData!$B$4)/360),Bootstrap!$B$39:$B$59,1)+1)-INDEX(Bootstrap!$B$39:$B$59,MATCH(((WORKDAY(B15,-5)-MarketData!$B$4)/360),Bootstrap!$B$39:$B$59,1)))) -> 0.85507941 | F15: =(D15/E15-1)/C15 -> 0.039494469 | G15: =(EXP(INDEX(Bootstrap!$D$39:$D$59,MATCH((($A15-MarketData!$B$4)/360),Bootstrap!$B$39:$B$59,1))+(INDEX(Bootstrap!$D$39:$D$59,MATCH((($A15-MarketData!$B$4)/360),Bootstrap!$B$39:$B$59,1)+1)-INDEX(Bootstrap!$D$39:$D$59,MATCH((($A15-MarketData!$B$4)/360),Bootstrap!$B$39:$B$59,1)))*(((($A15-MarketData!$B$4)/360))-INDEX(Bootstrap!$B$39:$B$59,MATCH((($A15-MarketData!$B$4)/360),Bootstrap!$B$39:$B$59,1)))/(INDEX(Bootstrap!$B$39:$B$59,MATCH((($A15-MarketData!$B$4)/360),Bootstrap!$B$39:$B$59,1)+1)-INDEX(Bootstrap!$B$39:$B$59,MATCH((($A15-MarketData!$B$4)/360),Bootstrap!$B$39:$B$59,1))))/EXP(INDEX(Bootstrap!$D$39:$D$59,MATCH((($B15-MarketData!$B$4)/360),Bootstrap!$B$39:$B$59,1))+(INDEX(Bootstrap!$D$39:$D$59,MATCH((($B15-MarketData!$B$4)/360),Bootstrap!$B$39:$B$59,1)+1)-INDEX(Bootstrap!$D$39:$D$59,MATCH((($B15-MarketData!$B$4)/360),Bootstrap!$B$39:$B$59,1)))*(((($B15-MarketData!$B$4)/360))-INDEX(Bootstrap!$B$39:$B$59,MATCH((($B15-MarketData!$B$4)/360),Bootstrap!$B$39:$B$59,1)))/(INDEX(Bootstrap!$B$39:$B$59,MATCH((($B15-MarketData!$B$4)/360),Bootstrap!$B$39:$B$59,1)+1)-INDEX(Bootstrap!$B$39:$B$59,MATCH((($B15-MarketData!$B$4)/360),Bootstrap!$B$39:$B$59,1))))-1)/C15 -> 0.039494647
A16: 46924 | B16: 47289 | C16: =(B16-A16)/360 -> 1.0138889 | D16: =EXP(INDEX(Bootstrap!$D$39:$D$59,MATCH(((WORKDAY(A16,-5)-MarketData!$B$4)/360),Bootstrap!$B$39:$B$59,1))+(INDEX(Bootstrap!$D$39:$D$59,MATCH(((WORKDAY(A16,-5)-MarketData!$B$4)/360),Bootstrap!$B$39:$B$59,1)+1)-INDEX(Bootstrap!$D$39:$D$59,MATCH(((WORKDAY(A16,-5)-MarketData!$B$4)/360),Bootstrap!$B$39:$B$59,1)))*((((WORKDAY(A16,-5)-MarketData!$B$4)/360))-INDEX(Bootstrap!$B$39:$B$59,MATCH(((WORKDAY(A16,-5)-MarketData!$B$4)/360),Bootstrap!$B$39:$B$59,1)))/(INDEX(Bootstrap!$B$39:$B$59,MATCH(((WORKDAY(A16,-5)-MarketData!$B$4)/360),Bootstrap!$B$39:$B$59,1)+1)-INDEX(Bootstrap!$B$39:$B$59,MATCH(((WORKDAY(A16,-5)-MarketData!$B$4)/360),Bootstrap!$B$39:$B$59,1)))) -> 0.92355931 | E16: =EXP(INDEX(Bootstrap!$D$39:$D$59,MATCH(((WORKDAY(B16,-5)-MarketData!$B$4)/360),Bootstrap!$B$39:$B$59,1))+(INDEX(Bootstrap!$D$39:$D$59,MATCH(((WORKDAY(B16,-5)-MarketData!$B$4)/360),Bootstrap!$B$39:$B$59,1)+1)-INDEX(Bootstrap!$D$39:$D$59,MATCH(((WORKDAY(B16,-5)-MarketData!$B$4)/360),Bootstrap!$B$39:$B$59,1)))*((((WORKDAY(B16,-5)-MarketData!$B$4)/360))-INDEX(Bootstrap!$B$39:$B$59,MATCH(((WORKDAY(B16,-5)-MarketData!$B$4)/360),Bootstrap!$B$39:$B$59,1)))/(INDEX(Bootstrap!$B$39:$B$59,MATCH(((WORKDAY(B16,-5)-MarketData!$B$4)/360),Bootstrap!$B$39:$B$59,1)+1)-INDEX(Bootstrap!$B$39:$B$59,MATCH(((WORKDAY(B16,-5)-MarketData!$B$4)/360),Bootstrap!$B$39:$B$59,1)))) -> 0.88847349 | F16: =(D16/E16-1)/C16 -> 0.038949042 | G16: =(EXP(INDEX(Bootstrap!$D$39:$D$59,MATCH((($A16-MarketData!$B$4)/360),Bootstrap!$B$39:$B$59,1))+(INDEX(Bootstrap!$D$39:$D$59,MATCH((($A16-MarketData!$B$4)/360),Bootstrap!$B$39:$B$59,1)+1)-INDEX(Bootstrap!$D$39:$D$59,MATCH((($A16-MarketData!$B$4)/360),Bootstrap!$B$39:$B$59,1)))*(((($A16-MarketData!$B$4)/360))-INDEX(Bootstrap!$B$39:$B$59,MATCH((($A16-MarketData!$B$4)/360),Bootstrap!$B$39:$B$59,1)))/(INDEX(Bootstrap!$B$39:$B$59,MATCH((($A16-MarketData!$B$4)/360),Bootstrap!$B$39:$B$59,1)+1)-INDEX(Bootstrap!$B$39:$B$59,MATCH((($A16-MarketData!$B$4)/360),Bootstrap!$B$39:$B$59,1))))/EXP(INDEX(Bootstrap!$D$39:$D$59,MATCH((($B16-MarketData!$B$4)/360),Bootstrap!$B$39:$B$59,1))+(INDEX(Bootstrap!$D$39:$D$59,MATCH((($B16-MarketData!$B$4)/360),Bootstrap!$B$39:$B$59,1)+1)-INDEX(Bootstrap!$D$39:$D$59,MATCH((($B16-MarketData!$B$4)/360),Bootstrap!$B$39:$B$59,1)))*(((($B16-MarketData!$B$4)/360))-INDEX(Bootstrap!$B$39:$B$59,MATCH((($B16-MarketData!$B$4)/360),Bootstrap!$B$39:$B$59,1)))/(INDEX(Bootstrap!$B$39:$B$59,MATCH((($B16-MarketData!$B$4)/360),Bootstrap!$B$39:$B$59,1)+1)-INDEX(Bootstrap!$B$39:$B$59,MATCH((($B16-MarketData!$B$4)/360),Bootstrap!$B$39:$B$59,1))))-1)/C16 -> 0.03893285
A17: 47289 | B17: 47654 | C17: =(B17-A17)/360 -> 1.0138889 | D17: =EXP(INDEX(Bootstrap!$D$39:$D$59,MATCH(((WORKDAY(A17,-5)-MarketData!$B$4)/360),Bootstrap!$B$39:$B$59,1))+(INDEX(Bootstrap!$D$39:$D$59,MATCH(((WORKDAY(A17,-5)-MarketData!$B$4)/360),Bootstrap!$B$39:$B$59,1)+1)-INDEX(Bootstrap!$D$39:$D$59,MATCH(((WORKDAY(A17,-5)-MarketData!$B$4)/360),Bootstrap!$B$39:$B$59,1)))*((((WORKDAY(A17,-5)-MarketData!$B$4)/360))-INDEX(Bootstrap!$B$39:$B$59,MATCH(((WORKDAY(A17,-5)-MarketData!$B$4)/360),Bootstrap!$B$39:$B$59,1)))/(INDEX(Bootstrap!$B$39:$B$59,MATCH(((WORKDAY(A17,-5)-MarketData!$B$4)/360),Bootstrap!$B$39:$B$59,1)+1)-INDEX(Bootstrap!$B$39:$B$59,MATCH(((WORKDAY(A17,-5)-MarketData!$B$4)/360),Bootstrap!$B$39:$B$59,1)))) -> 0.88847349 | E17: =EXP(INDEX(Bootstrap!$D$39:$D$59,MATCH(((WORKDAY(B17,-5)-MarketData!$B$4)/360),Bootstrap!$B$39:$B$59,1))+(INDEX(Bootstrap!$D$39:$D$59,MATCH(((WORKDAY(B17,-5)-MarketData!$B$4)/360),Bootstrap!$B$39:$B$59,1)+1)-INDEX(Bootstrap!$D$39:$D$59,MATCH(((WORKDAY(B17,-5)-MarketData!$B$4)/360),Bootstrap!$B$39:$B$59,1)))*((((WORKDAY(B17,-5)-MarketData!$B$4)/360))-INDEX(Bootstrap!$B$39:$B$59,MATCH(((WORKDAY(B17,-5)-MarketData!$B$4)/360),Bootstrap!$B$39:$B$59,1)))/(INDEX(Bootstrap!$B$39:$B$59,MATCH(((WORKDAY(B17,-5)-MarketData!$B$4)/360),Bootstrap!$B$39:$B$59,1)+1)-INDEX(Bootstrap!$B$39:$B$59,MATCH(((WORKDAY(B17,-5)-MarketData!$B$4)/360),Bootstrap!$B$39:$B$59,1)))) -> 0.85507941 | F17: =(D17/E17-1)/C17 -> 0.038518788 | G17: =(EXP(INDEX(Bootstrap!$D$39:$D$59,MATCH((($A17-MarketData!$B$4)/360),Bootstrap!$B$39:$B$59,1))+(INDEX(Bootstrap!$D$39:$D$59,MATCH((($A17-MarketData!$B$4)/360),Bootstrap!$B$39:$B$59,1)+1)-INDEX(Bootstrap!$D$39:$D$59,MATCH((($A17-MarketData!$B$4)/360),Bootstrap!$B$39:$B$59,1)))*(((($A17-MarketData!$B$4)/360))-INDEX(Bootstrap!$B$39:$B$59,MATCH((($A17-MarketData!$B$4)/360),Bootstrap!$B$39:$B$59,1)))/(INDEX(Bootstrap!$B$39:$B$59,MATCH((($A17-MarketData!$B$4)/360),Bootstrap!$B$39:$B$59,1)+1)-INDEX(Bootstrap!$B$39:$B$59,MATCH((($A17-MarketData!$B$4)/360),Bootstrap!$B$39:$B$59,1))))/EXP(INDEX(Bootstrap!$D$39:$D$59,MATCH((($B17-MarketData!$B$4)/360),Bootstrap!$B$39:$B$59,1))+(INDEX(Bootstrap!$D$39:$D$59,MATCH((($B17-MarketData!$B$4)/360),Bootstrap!$B$39:$B$59,1)+1)-INDEX(Bootstrap!$D$39:$D$59,MATCH((($B17-MarketData!$B$4)/360),Bootstrap!$B$39:$B$59,1)))*(((($B17-MarketData!$B$4)/360))-INDEX(Bootstrap!$B$39:$B$59,MATCH((($B17-MarketData!$B$4)/360),Bootstrap!$B$39:$B$59,1)))/(INDEX(Bootstrap!$B$39:$B$59,MATCH((($B17-MarketData!$B$4)/360),Bootstrap!$B$39:$B$59,1)+1)-INDEX(Bootstrap!$B$39:$B$59,MATCH((($B17-MarketData!$B$4)/360),Bootstrap!$B$39:$B$59,1))))-1)/C17 -> 0.038535318
A18: 46195 | B18: 46223 | C18: =(B18-A18)/360 -> 0.077777778 | D18: =EXP(INDEX(Bootstrap!$D$39:$D$59,MATCH(((WORKDAY(A18,-5)-MarketData!$B$4)/360),Bootstrap!$B$39:$B$59,1))+(INDEX(Bootstrap!$D$39:$D$59,MATCH(((WORKDAY(A18,-5)-MarketData!$B$4)/360),Bootstrap!$B$39:$B$59,1)+1)-INDEX(Bootstrap!$D$39:$D$59,MATCH(((WORKDAY(A18,-5)-MarketData!$B$4)/360),Bootstrap!$B$39:$B$59,1)))*((((WORKDAY(A18,-5)-MarketData!$B$4)/360))-INDEX(Bootstrap!$B$39:$B$59,MATCH(((WORKDAY(A18,-5)-MarketData!$B$4)/360),Bootstrap!$B$39:$B$59,1)))/(INDEX(Bootstrap!$B$39:$B$59,MATCH(((WORKDAY(A18,-5)-MarketData!$B$4)/360),Bootstrap!$B$39:$B$59,1)+1)-INDEX(Bootstrap!$B$39:$B$59,MATCH(((WORKDAY(A18,-5)-MarketData!$B$4)/360),Bootstrap!$B$39:$B$59,1)))) -> 0.99890299 | E18: =EXP(INDEX(Bootstrap!$D$39:$D$59,MATCH(((WORKDAY(B18,-5)-MarketData!$B$4)/360),Bootstrap!$B$39:$B$59,1))+(INDEX(Bootstrap!$D$39:$D$59,MATCH(((WORKDAY(B18,-5)-MarketData!$B$4)/360),Bootstrap!$B$39:$B$59,1)+1)-INDEX(Bootstrap!$D$39:$D$59,MATCH(((WORKDAY(B18,-5)-MarketData!$B$4)/360),Bootstrap!$B$39:$B$59,1)))*((((WORKDAY(B18,-5)-MarketData!$B$4)/360))-INDEX(Bootstrap!$B$39:$B$59,MATCH(((WORKDAY(B18,-5)-MarketData!$B$4)/360),Bootstrap!$B$39:$B$59,1)))/(INDEX(Bootstrap!$B$39:$B$59,MATCH(((WORKDAY(B18,-5)-MarketData!$B$4)/360),Bootstrap!$B$39:$B$59,1)+1)-INDEX(Bootstrap!$B$39:$B$59,MATCH(((WORKDAY(B18,-5)-MarketData!$B$4)/360),Bootstrap!$B$39:$B$59,1)))) -> 0.99608107 | F18: =(D18/E18-1)/C18 -> 0.036424544 | G18: =(EXP(INDEX(Bootstrap!$D$39:$D$59,MATCH((($A18-MarketData!$B$4)/360),Bootstrap!$B$39:$B$59,1))+(INDEX(Bootstrap!$D$39:$D$59,MATCH((($A18-MarketData!$B$4)/360),Bootstrap!$B$39:$B$59,1)+1)-INDEX(Bootstrap!$D$39:$D$59,MATCH((($A18-MarketData!$B$4)/360),Bootstrap!$B$39:$B$59,1)))*(((($A18-MarketData!$B$4)/360))-INDEX(Bootstrap!$B$39:$B$59,MATCH((($A18-MarketData!$B$4)/360),Bootstrap!$B$39:$B$59,1)))/(INDEX(Bootstrap!$B$39:$B$59,MATCH((($A18-MarketData!$B$4)/360),Bootstrap!$B$39:$B$59,1)+1)-INDEX(Bootstrap!$B$39:$B$59,MATCH((($A18-MarketData!$B$4)/360),Bootstrap!$B$39:$B$59,1))))/EXP(INDEX(Bootstrap!$D$39:$D$59,MATCH((($B18-MarketData!$B$4)/360),Bootstrap!$B$39:$B$59,1))+(INDEX(Bootstrap!$D$39:$D$59,MATCH((($B18-MarketData!$B$4)/360),Bootstrap!$B$39:$B$59,1)+1)-INDEX(Bootstrap!$D$39:$D$59,MATCH((($B18-MarketData!$B$4)/360),Bootstrap!$B$39:$B$59,1)))*(((($B18-MarketData!$B$4)/360))-INDEX(Bootstrap!$B$39:$B$59,MATCH((($B18-MarketData!$B$4)/360),Bootstrap!$B$39:$B$59,1)))/(INDEX(Bootstrap!$B$39:$B$59,MATCH((($B18-MarketData!$B$4)/360),Bootstrap!$B$39:$B$59,1)+1)-INDEX(Bootstrap!$B$39:$B$59,MATCH((($B18-MarketData!$B$4)/360),Bootstrap!$B$39:$B$59,1))))-1)/C18 -> 0.036534337
A19: 46559 | B19: 46650 | C19: =(B19-A19)/360 -> 0.25277778 | D19: =EXP(INDEX(Bootstrap!$D$39:$D$59,MATCH(((WORKDAY(A19,-5)-MarketData!$B$4)/360),Bootstrap!$B$39:$B$59,1))+(INDEX(Bootstrap!$D$39:$D$59,MATCH(((WORKDAY(A19,-5)-MarketData!$B$4)/360),Bootstrap!$B$39:$B$59,1)+1)-INDEX(Bootstrap!$D$39:$D$59,MATCH(((WORKDAY(A19,-5)-MarketData!$B$4)/360),Bootstrap!$B$39:$B$59,1)))*((((WORKDAY(A19,-5)-MarketData!$B$4)/360))-INDEX(Bootstrap!$B$39:$B$59,MATCH(((WORKDAY(A19,-5)-MarketData!$B$4)/360),Bootstrap!$B$39:$B$59,1)))/(INDEX(Bootstrap!$B$39:$B$59,MATCH(((WORKDAY(A19,-5)-MarketData!$B$4)/360),Bootstrap!$B$39:$B$59,1)+1)-INDEX(Bootstrap!$B$39:$B$59,MATCH(((WORKDAY(A19,-5)-MarketData!$B$4)/360),Bootstrap!$B$39:$B$59,1)))) -> 0.96126295 | E19: =EXP(INDEX(Bootstrap!$D$39:$D$59,MATCH(((WORKDAY(B19,-5)-MarketData!$B$4)/360),Bootstrap!$B$39:$B$59,1))+(INDEX(Bootstrap!$D$39:$D$59,MATCH(((WORKDAY(B19,-5)-MarketData!$B$4)/360),Bootstrap!$B$39:$B$59,1)+1)-INDEX(Bootstrap!$D$39:$D$59,MATCH(((WORKDAY(B19,-5)-MarketData!$B$4)/360),Bootstrap!$B$39:$B$59,1)))*((((WORKDAY(B19,-5)-MarketData!$B$4)/360))-INDEX(Bootstrap!$B$39:$B$59,MATCH(((WORKDAY(B19,-5)-MarketData!$B$4)/360),Bootstrap!$B$39:$B$59,1)))/(INDEX(Bootstrap!$B$39:$B$59,MATCH(((WORKDAY(B19,-5)-MarketData!$B$4)/360),Bootstrap!$B$39:$B$59,1)+1)-INDEX(Bootstrap!$B$39:$B$59,MATCH(((WORKDAY(B19,-5)-MarketData!$B$4)/360),Bootstrap!$B$39:$B$59,1)))) -> 0.95164674 | F19: =(D19/E19-1)/C19 -> 0.039975115 | G19: =(EXP(INDEX(Bootstrap!$D$39:$D$59,MATCH((($A19-MarketData!$B$4)/360),Bootstrap!$B$39:$B$59,1))+(INDEX(Bootstrap!$D$39:$D$59,MATCH((($A19-MarketData!$B$4)/360),Bootstrap!$B$39:$B$59,1)+1)-INDEX(Bootstrap!$D$39:$D$59,MATCH((($A19-MarketData!$B$4)/360),Bootstrap!$B$39:$B$59,1)))*(((($A19-MarketData!$B$4)/360))-INDEX(Bootstrap!$B$39:$B$59,MATCH((($A19-MarketData!$B$4)/360),Bootstrap!$B$39:$B$59,1)))/(INDEX(Bootstrap!$B$39:$B$59,MATCH((($A19-MarketData!$B$4)/360),Bootstrap!$B$39:$B$59,1)+1)-INDEX(Bootstrap!$B$39:$B$59,MATCH((($A19-MarketData!$B$4)/360),Bootstrap!$B$39:$B$59,1))))/EXP(INDEX(Bootstrap!$D$39:$D$59,MATCH((($B19-MarketData!$B$4)/360),Bootstrap!$B$39:$B$59,1))+(INDEX(Bootstrap!$D$39:$D$59,MATCH((($B19-MarketData!$B$4)/360),Bootstrap!$B$39:$B$59,1)+1)-INDEX(Bootstrap!$D$39:$D$59,MATCH((($B19-MarketData!$B$4)/360),Bootstrap!$B$39:$B$59,1)))*(((($B19-MarketData!$B$4)/360))-INDEX(Bootstrap!$B$39:$B$59,MATCH((($B19-MarketData!$B$4)/360),Bootstrap!$B$39:$B$59,1)))/(INDEX(Bootstrap!$B$39:$B$59,MATCH((($B19-MarketData!$B$4)/360),Bootstrap!$B$39:$B$59,1)+1)-INDEX(Bootstrap!$B$39:$B$59,MATCH((($B19-MarketData!$B$4)/360),Bootstrap!$B$39:$B$59,1))))-1)/C19 -> 0.039968648
A22: Row 1 (2028-06-20 → 2030-06-20) is the cancellation window: its compounded forward ≈ the rate that matters for the 2028 exercise decision.

Sheet Methodology
A1: METHODOLOGY — how this workbook reproduces Pandora, and where it differs
A3: 1. Single SOFR curve
B4: Discount = projection. Forwards are read straight off the discount factors: fwd = (DF_start / DF_end − 1) / τ (ACT/360).
B5: Verified: implied forwards from Pandora's own DFs match Pandora's printed forwards to < 0.3 bp.
A6: 2. Instrument set & calibration
B7: Front: O/N (SOFR 1D) + 8 FOMC-dated step quotes, bootstrapped exactly (DF = prevDF/(1+rate·τ)).
B8: Middle: 8 EUSD quarterly futures, convexity-adjusted fwd = (100 − price − convexity)/100, DF telescoping.
B9: Long end: par swaps. The 4Y is solved closed-form for DF(2030); the 5Y is solved as a sentinel node.
B10: Pandora itself reprices this set to 0–5 bp; the XML tags the curve "Iterative" = a global simultaneous solve.
A11: 3. Five-business-day lookback (Lag)
B12: Forwards use compounded SOFR observed over a window shifted back 5 business days (Excel WORKDAY(date,−5)).
B13: Replicated: the 5bd shift cuts the mean forward error from 0.090 bp to 0.029 bp (worst case −0.30 → −0.04 bp).
A14: 4. Interpolation
B15: Pandora uses a SMOOTH CUBIC interpolation. Holding out monthly DFs and predicting them from quarterly DFs:
A16: log-linear DF | B16: RMS 6.2e-6 (this workbook)
A17: linear zero | B17: RMS 10.8e-6
A18: cubic spline / monotone-cubic | B18: RMS 1.4e-6 (Pandora's method)
B19: This workbook uses LOG-LINEAR (transparent, robust, no matrix/iterative formulas).
B20: Tested: over THIS bootstrap's nodes, cubic vs log-linear give the SAME Pandora match (within ~1 bp) — because the
B21: 2029-30 forward shape comes from the global multi-swap fit, not the interpolation, so cubic interpolation alone
B22: does not close the gap. The global iterative cubic solve is not expressible in plain spreadsheet formulas.
A23: 5. Accuracy vs Pandora (see Curve sheet)
B24: Discount factors: ~0–1.6 bp (hump peaks in the futures region, ~0 at the front and at the 4Y node).
B25: Forwards: ~2 bp on average, up to ~4 bp in the smooth 2029-30 gap (log-linear gives a flat forward there).
B26: The residual is (a) convexity — Pandora prices the futures slightly richer than the stated adjustment — and
B27: (b) the global cubic fit to 4Y–12Y. A Python global-spline calibration closes it to ~0.5–1 bp; that requires an
B28: iterative solver. Everything here is plain formulas, so the honest formula-driven match is ~1.5 bp (DF) / ~2 bp (fwd).
A29: 6. Not investment advice
B30: A curve reconstruction from the published market quotes for analysis; not an official valuation.

Sheet Pandora vs APCEXO
A1: PAR-RATE COMPARISON — Pandora curve vs APCEXO, at the APCEXO tenors
A2: Pandora par = repricing each APCEXO instrument (same conventions) off the Pandora discount factors interpolated from this workbook’s own node grid (log-linear on ln DF). Δ = Pandora − APCEXO.
A3: Pandora is calibrated only to 5Y (last node 08-Jun-2031); APCEXO tenors beyond 5Y are not shown (they would only extrapolate Pandora).
A5: Tenor | B5: Maturity | C5: Days | D5: APCEXO par | E5: Pandora DF @ mat | F5: Pandora par | G5: Δ par (bp) | I5: time | J5: idx
A6: 1D | B6: 46178 | C6: =B6-MarketData!$B$4 -> 1 | D6: 0.0357641 | E6: =EXP(INDEX(Bootstrap!$D$39:$D$59,J6)+(INDEX(Bootstrap!$D$39:$D$59,J6+1)-INDEX(Bootstrap!$D$39:$D$59,J6))*(I6-INDEX(Bootstrap!$B$39:$B$59,J6))/(INDEX(Bootstrap!$B$39:$B$59,J6+1)-INDEX(Bootstrap!$B$39:$B$59,J6))) -> 0.99990022 | F6: =(1/E6-1)*360/C6 -> 0.03592369 | G6: =(F6-D6)*10000 -> 1.5958979 | I6: =(B6-MarketData!$B$4)/360 -> 0.0027777778 | J6: =MIN(MATCH(I6,Bootstrap!$B$39:$B$59,1),20) -> 1
A7: 1M | B7: 46213 | C7: =B7-MarketData!$B$4 -> 36 | D7: 0.0361229 | E7: =EXP(INDEX(Bootstrap!$D$39:$D$59,J7)+(INDEX(Bootstrap!$D$39:$D$59,J7+1)-INDEX(Bootstrap!$D$39:$D$59,J7))*(I7-INDEX(Bootstrap!$B$39:$B$59,J7))/(INDEX(Bootstrap!$B$39:$B$59,J7+1)-INDEX(Bootstrap!$B$39:$B$59,J7))) -> 0.99638462 | F7: =(1/E7-1)*360/C7 -> 0.03628496 | G7: =(F7-D7)*10000 -> 1.6205988 | I7: =(B7-MarketData!$B$4)/360 -> 0.1 | J7: =MIN(MATCH(I7,Bootstrap!$B$39:$B$59,1),20) -> 3
A8: 2M | B8: 46246 | C8: =B8-MarketData!$B$4 -> 69 | D8: 0.0363331 | E8: =EXP(INDEX(Bootstrap!$D$39:$D$59,J8)+(INDEX(Bootstrap!$D$39:$D$59,J8+1)-INDEX(Bootstrap!$D$39:$D$59,J8))*(I8-INDEX(Bootstrap!$B$39:$B$59,J8))/(INDEX(Bootstrap!$B$39:$B$59,J8+1)-INDEX(Bootstrap!$B$39:$B$59,J8))) -> 0.99305064 | F8: =(1/E8-1)*360/C8 -> 0.036511271 | G8: =(F8-D8)*10000 -> 1.7817091 | I8: =(B8-MarketData!$B$4)/360 -> 0.19166667 | J8: =MIN(MATCH(I8,Bootstrap!$B$39:$B$59,1),20) -> 3
A9: 3M | B9: 46275 | C9: =B9-MarketData!$B$4 -> 98 | D9: 0.0365327 | E9: =EXP(INDEX(Bootstrap!$D$39:$D$59,J9)+(INDEX(Bootstrap!$D$39:$D$59,J9+1)-INDEX(Bootstrap!$D$39:$D$59,J9))*(I9-INDEX(Bootstrap!$B$39:$B$59,J9))/(INDEX(Bootstrap!$B$39:$B$59,J9+1)-INDEX(Bootstrap!$B$39:$B$59,J9))) -> 0.99012998 | F9: =(1/E9-1)*360/C9 -> 0.03661863 | G9: =(F9-D9)*10000 -> 0.85929639 | I9: =(B9-MarketData!$B$4)/360 -> 0.27222222 | J9: =MIN(MATCH(I9,Bootstrap!$B$39:$B$59,1),20) -> 3
A10: 4M | B10: 46308 | C10: =B10-MarketData!$B$4 -> 131 | D10: 0.0367449 | E10: =EXP(INDEX(Bootstrap!$D$39:$D$59,J10)+(INDEX(Bootstrap!$D$39:$D$59,J10+1)-INDEX(Bootstrap!$D$39:$D$59,J10))*(I10-INDEX(Bootstrap!$B$39:$B$59,J10))/(INDEX(Bootstrap!$B$39:$B$59,J10+1)-INDEX(Bootstrap!$B$39:$B$59,J10))) -> 0.98677428 | F10: =(1/E10-1)*360/C10 -> 0.036832628 | G10: =(F10-D10)*10000 -> 0.87727563 | I10: =(B10-MarketData!$B$4)/360 -> 0.36388889 | J10: =MIN(MATCH(I10,Bootstrap!$B$39:$B$59,1),20) -> 4
A11: 5M | B11: 46338 | C11: =B11-MarketData!$B$4 -> 161 | D11: 0.0369724 | E11: =EXP(INDEX(Bootstrap!$D$39:$D$59,J11)+(INDEX(Bootstrap!$D$39:$D$59,J11+1)-INDEX(Bootstrap!$D$39:$D$59,J11))*(I11-INDEX(Bootstrap!$B$39:$B$59,J11))/(INDEX(Bootstrap!$B$39:$B$59,J11+1)-INDEX(Bootstrap!$B$39:$B$59,J11))) -> 0.9837065 | F11: =(1/E11-1)*360/C11 -> 0.037036123 | G11: =(F11-D11)*10000 -> 0.63722795 | I11: =(B11-MarketData!$B$4)/360 -> 0.44722222 | J11: =MIN(MATCH(I11,Bootstrap!$B$39:$B$59,1),20) -> 5
A12: 6M | B12: 46366 | C12: =B12-MarketData!$B$4 -> 189 | D12: 0.0371647 | E12: =EXP(INDEX(Bootstrap!$D$39:$D$59,J12)+(INDEX(Bootstrap!$D$39:$D$59,J12+1)-INDEX(Bootstrap!$D$39:$D$59,J12))*(I12-INDEX(Bootstrap!$B$39:$B$59,J12))/(INDEX(Bootstrap!$B$39:$B$59,J12+1)-INDEX(Bootstrap!$B$39:$B$59,J12))) -> 0.98083418 | F12: =(1/E12-1)*360/C12 -> 0.037219673 | G12: =(F12-D12)*10000 -> 0.54972532 | I12: =(B12-MarketData!$B$4)/360 -> 0.525 | J12: =MIN(MATCH(I12,Bootstrap!$B$39:$B$59,1),20) -> 6
A13: 7M | B13: 46399 | C13: =B13-MarketData!$B$4 -> 222 | D13: 0.0374783 | E13: =EXP(INDEX(Bootstrap!$D$39:$D$59,J13)+(INDEX(Bootstrap!$D$39:$D$59,J13+1)-INDEX(Bootstrap!$D$39:$D$59,J13))*(I13-INDEX(Bootstrap!$B$39:$B$59,J13))/(INDEX(Bootstrap!$B$39:$B$59,J13+1)-INDEX(Bootstrap!$B$39:$B$59,J13))) -> 0.97737466 | F13: =(1/E13-1)*360/C13 -> 0.03753908 | G13: =(F13-D13)*10000 -> 0.60780058 | I13: =(B13-MarketData!$B$4)/360 -> 0.61666667 | J13: =MIN(MATCH(I13,Bootstrap!$B$39:$B$59,1),20) -> 6
A14: 8M | B14: 46428 | C14: =B14-MarketData!$B$4 -> 251 | D14: 0.0377353 | E14: =EXP(INDEX(Bootstrap!$D$39:$D$59,J14)+(INDEX(Bootstrap!$D$39:$D$59,J14+1)-INDEX(Bootstrap!$D$39:$D$59,J14))*(I14-INDEX(Bootstrap!$B$39:$B$59,J14))/(INDEX(Bootstrap!$B$39:$B$59,J14+1)-INDEX(Bootstrap!$B$39:$B$59,J14))) -> 0.97434476 | F14: =(1/E14-1)*360/C14 -> 0.037765242 | G14: =(F14-D14)*10000 -> 0.29942228 | I14: =(B14-MarketData!$B$4)/360 -> 0.69722222 | J14: =MIN(MATCH(I14,Bootstrap!$B$39:$B$59,1),20) -> 7
A15: 9M | B15: 46456 | C15: =B15-MarketData!$B$4 -> 279 | D15: 0.0379217 | E15: =EXP(INDEX(Bootstrap!$D$39:$D$59,J15)+(INDEX(Bootstrap!$D$39:$D$59,J15+1)-INDEX(Bootstrap!$D$39:$D$59,J15))*(I15-INDEX(Bootstrap!$B$39:$B$59,J15))/(INDEX(Bootstrap!$B$39:$B$59,J15+1)-INDEX(Bootstrap!$B$39:$B$59,J15))) -> 0.9714285 | F15: =(1/E15-1)*360/C15 -> 0.037950767 | G15: =(F15-D15)*10000 -> 0.29066843 | I15: =(B15-MarketData!$B$4)/360 -> 0.775 | J15: =MIN(MATCH(I15,Bootstrap!$B$39:$B$59,1),20) -> 7
A16: 10M | B16: 46489 | C16: =B16-MarketData!$B$4 -> 312 | D16: 0.0381585 | E16: =EXP(INDEX(Bootstrap!$D$39:$D$59,J16)+(INDEX(Bootstrap!$D$39:$D$59,J16+1)-INDEX(Bootstrap!$D$39:$D$59,J16))*(I16-INDEX(Bootstrap!$B$39:$B$59,J16))/(INDEX(Bootstrap!$B$39:$B$59,J16+1)-INDEX(Bootstrap!$B$39:$B$59,J16))) -> 0.96795868 | F16: =(1/E16-1)*360/C16 -> 0.038194555 | G16: =(F16-D16)*10000 -> 0.3605474 | I16: =(B16-MarketData!$B$4)/360 -> 0.86666667 | J16: =MIN(MATCH(I16,Bootstrap!$B$39:$B$59,1),20) -> 8
A17: 11M | B17: 46519 | C17: =B17-MarketData!$B$4 -> 342 | D17: 0.0384102 | E17: =EXP(INDEX(Bootstrap!$D$39:$D$59,J17)+(INDEX(Bootstrap!$D$39:$D$59,J17+1)-INDEX(Bootstrap!$D$39:$D$59,J17))*(I17-INDEX(Bootstrap!$B$39:$B$59,J17))/(INDEX(Bootstrap!$B$39:$B$59,J17+1)-INDEX(Bootstrap!$B$39:$B$59,J17))) -> 0.96478008 | F17: =(1/E17-1)*360/C17 -> 0.038427 | G17: =(F17-D17)*10000 -> 0.16800488 | I17: =(B17-MarketData!$B$4)/360 -> 0.95 | J17: =MIN(MATCH(I17,Bootstrap!$B$39:$B$59,1),20) -> 9
A18: 12M | B18: 46548 | C18: =B18-MarketData!$B$4 -> 371 | D18: 0.038634 | E18: =EXP(INDEX(Bootstrap!$D$39:$D$59,J18)+(INDEX(Bootstrap!$D$39:$D$59,J18+1)-INDEX(Bootstrap!$D$39:$D$59,J18))*(I18-INDEX(Bootstrap!$B$39:$B$59,J18))/(INDEX(Bootstrap!$B$39:$B$59,J18+1)-INDEX(Bootstrap!$B$39:$B$59,J18))) -> 0.96168933 | F18: =(1/E18-1)*360/C18 -> 0.038655695 | G18: =(F18-D18)*10000 -> 0.21695331 | I18: =(B18-MarketData!$B$4)/360 -> 1.0305556 | J18: =MIN(MATCH(I18,Bootstrap!$B$39:$B$59,1),20) -> 10
A19: 15M | B19: 46640 | C19: =B19-MarketData!$B$4 -> 463 | D19: 0.0389056 | E19: =EXP(INDEX(Bootstrap!$D$39:$D$59,J19)+(INDEX(Bootstrap!$D$39:$D$59,J19+1)-INDEX(Bootstrap!$D$39:$D$59,J19))*(I19-INDEX(Bootstrap!$B$39:$B$59,J19))/(INDEX(Bootstrap!$B$39:$B$59,J19+1)-INDEX(Bootstrap!$B$39:$B$59,J19))) -> 0.95196219 | F19: =(1-E19)/(C9/360*E9+(C19-C9)/360*E19) -> 0.038905856 | G19: =(F19-D19)*10000 -> 0.0025577562 | I19: =(B19-MarketData!$B$4)/360 -> 1.2861111 | J19: =MIN(MATCH(I19,Bootstrap!$B$39:$B$59,1),20) -> 11
A20: 18M | B20: 46731 | C20: =B20-MarketData!$B$4 -> 554 | D20: 0.0391016 | E20: =EXP(INDEX(Bootstrap!$D$39:$D$59,J20)+(INDEX(Bootstrap!$D$39:$D$59,J20+1)-INDEX(Bootstrap!$D$39:$D$59,J20))*(I20-INDEX(Bootstrap!$B$39:$B$59,J20))/(INDEX(Bootstrap!$B$39:$B$59,J20+1)-INDEX(Bootstrap!$B$39:$B$59,J20))) -> 0.94245334 | F20: =(1-E20)/(C12/360*E12+(C20-C12)/360*E20) -> 0.039134582 | G20: =(F20-D20)*10000 -> 0.32982155 | I20: =(B20-MarketData!$B$4)/360 -> 1.5388889 | J20: =MIN(MATCH(I20,Bootstrap!$B$39:$B$59,1),20) -> 12
A21: 21M | B21: 46822 | C21: =B21-MarketData!$B$4 -> 645 | D21: 0.0392184 | E21: =EXP(INDEX(Bootstrap!$D$39:$D$59,J21)+(INDEX(Bootstrap!$D$39:$D$59,J21+1)-INDEX(Bootstrap!$D$39:$D$59,J21))*(I21-INDEX(Bootstrap!$B$39:$B$59,J21))/(INDEX(Bootstrap!$B$39:$B$59,J21+1)-INDEX(Bootstrap!$B$39:$B$59,J21))) -> 0.93309367 | F21: =(1-E21)/(C15/360*E15+(C21-C15)/360*E21) -> 0.039321918 | G21: =(F21-D21)*10000 -> 1.035182 | I21: =(B21-MarketData!$B$4)/360 -> 1.7916667 | J21: =MIN(MATCH(I21,Bootstrap!$B$39:$B$59,1),20) -> 13
A22: 2Y | B22: 46916 | C22: =B22-MarketData!$B$4 -> 739 | D22: 0.0392987 | E22: =EXP(INDEX(Bootstrap!$D$39:$D$59,J22)+(INDEX(Bootstrap!$D$39:$D$59,J22+1)-INDEX(Bootstrap!$D$39:$D$59,J22))*(I22-INDEX(Bootstrap!$B$39:$B$59,J22))/(INDEX(Bootstrap!$B$39:$B$59,J22+1)-INDEX(Bootstrap!$B$39:$B$59,J22))) -> 0.92365908 | F22: =(1-E22)/F30 -> 0.039447388 | G22: =(F22-D22)*10000 -> 1.4868832 | I22: =(B22-MarketData!$B$4)/360 -> 2.0527778 | J22: =MIN(MATCH(I22,Bootstrap!$B$39:$B$59,1),20) -> 14
A23: 3Y | B23: 47281 | C23: =B23-MarketData!$B$4 -> 1104 | D23: 0.0391685 | E23: =EXP(INDEX(Bootstrap!$D$39:$D$59,J23)+(INDEX(Bootstrap!$D$39:$D$59,J23+1)-INDEX(Bootstrap!$D$39:$D$59,J23))*(I23-INDEX(Bootstrap!$B$39:$B$59,J23))/(INDEX(Bootstrap!$B$39:$B$59,J23+1)-INDEX(Bootstrap!$B$39:$B$59,J23))) -> 0.88856747 | F23: =(1-E23)/F31 -> 0.039289824 | G23: =(F23-D23)*10000 -> 1.2132357 | I23: =(B23-MarketData!$B$4)/360 -> 3.0666667 | J23: =MIN(MATCH(I23,Bootstrap!$B$39:$B$59,1),20) -> 18
A24: 4Y | B24: 47646 | C24: =B24-MarketData!$B$4 -> 1469 | D24: 0.0391098 | E24: =EXP(INDEX(Bootstrap!$D$39:$D$59,J24)+(INDEX(Bootstrap!$D$39:$D$59,J24+1)-INDEX(Bootstrap!$D$39:$D$59,J24))*(I24-INDEX(Bootstrap!$B$39:$B$59,J24))/(INDEX(Bootstrap!$B$39:$B$59,J24+1)-INDEX(Bootstrap!$B$39:$B$59,J24))) -> 0.85517183 | F24: =(1-E24)/F32 -> 0.039108745 | G24: =(F24-D24)*10000 -> -0.010549287 | I24: =(B24-MarketData!$B$4)/360 -> 4.0805556 | J24: =MIN(MATCH(I24,Bootstrap!$B$39:$B$59,1),20) -> 20
A25: 5Y | B25: 48010 | C25: =B25-MarketData!$B$4 -> 1833 | D25: 0.0392161 | E25: =EXP(INDEX(Bootstrap!$D$39:$D$59,J25)+(INDEX(Bootstrap!$D$39:$D$59,J25+1)-INDEX(Bootstrap!$D$39:$D$59,J25))*(I25-INDEX(Bootstrap!$B$39:$B$59,J25))/(INDEX(Bootstrap!$B$39:$B$59,J25+1)-INDEX(Bootstrap!$B$39:$B$59,J25))) -> 0.82218338 | F25: =(1-E25)/F33 -> 0.039213853 | G25: =(F25-D25)*10000 -> -0.022467309 | I25: =(B25-MarketData!$B$4)/360 -> 5.0916667 | J25: =MIN(MATCH(I25,Bootstrap!$B$39:$B$59,1),20) -> 20
A27: Pandora annual annuity grid (single-curve OIS coupons, years 1–5; DF read from the table above)
A28: Year | B28: Date | C28: Days | D28: τ (ACT/360) | E28: Pandora DF | F28: Cum. annuity
A29: 1 | B29: =B18 -> 46548 | C29: =C18 -> 371 | D29: =C29/360 -> 1.0305556 | E29: =E18 -> 0.96168933 | F29: =D29*E29 -> 0.99107429
A30: 2 | B30: =B22 -> 46916 | C30: =C22 -> 739 | D30: =(C30-C29)/360 -> 1.0222222 | E30: =E22 -> 0.92365908 | F30: =F29+D30*E30 -> 1.9352591
A31: 3 | B31: =B23 -> 47281 | C31: =C23 -> 1104 | D31: =(C31-C30)/360 -> 1.0138889 | E31: =E23 -> 0.88856747 | F31: =F30+D31*E31 -> 2.8361678
A32: 4 | B32: =B24 -> 47646 | C32: =C24 -> 1469 | D32: =(C32-C31)/360 -> 1.0138889 | E32: =E24 -> 0.85517183 | F32: =F31+D32*E32 -> 3.703217
A33: 5 | B33: =B25 -> 48010 | C33: =C25 -> 1833 | D33: =(C33-C32)/360 -> 1.0111111 | E33: =E25 -> 0.82218338 | F33: =F32+D33*E33 -> 4.5345358
A36: Mean |Δ par| (bp) | C36: {=AVERAGE(ABS(G6:G25))} -> 0.69829124
A37: Max |Δ par| (bp) | C37: {=MAX(ABS(G6:G25))} -> 1.7817091
